Workbook

Sheet Cover & Instructions
B2: ERP — User Acceptance Test (UAT) Plan
B4: Purpose | C4: End-to-end UAT for the ERP, organised one tab per module. Each row is a manually-executable test case for the QA team. Fill in Actual Result, Status, Severity, Tester and Run Date as you go; the Summary tab tallies results live.
B5: Total test cases | C5: 696
B6: Modules / tabs | C6: 27
B7: Generated | C7: 2026-06-27
B8: QA environment | C8: https://16.170.11.41/ (QA stack; data is durable — do not expect a clean DB)
B9: Login | C9: Use a NON-root user with the relevant role for permission cases (root bypasses all permission checks and will mask RBAC defects). Switch branch via the top-bar branch picker where a test needs a specific branch.
B11: How to run a case | C11: 1) Read Preconditions and set them up. 2) Follow Steps in the app. 3) Compare what you see to Expected Result. 4) Put Pass/Fail/Blocked in Status; if Fail, write what happened in Actual Result, set Severity, and log it on the 'Defects Log' tab.
B13: Status values | C13: Not Run (default) · Pass · Fail · Blocked · N/A
B14: Severity (for fails) | C14: Critical (blocks a core flow / data loss) · High · Medium · Low (cosmetic)
B15: Type | C15: Positive (happy path) · Negative (rejection/validation) · Permission (RBAC) · Edge
B16: Priority | C16: High = must pass for sign-off · Medium · Low
B18: Column guide | C18: ID = stable case id · Area = feature · Route = where in the app · Permission = the RBAC code involved. 'Expected Result' is the pass criterion.
B19: Note | C19: Some cases intentionally document a KNOWN issue (look for 'DEFECT'/'known issue' in the scenario or expected text) — verify the stated current behaviour.

Sheet Summary
A1: UAT Summary Dashboard
A2: Module | B2: Cases | C2: Not Run | D2: Pass | E2: Fail | F2: Blocked | G2: N/A | H2: Pass %
A3: IAM & Access | B3: 47 | C3: =COUNTIF('IAM & Access'!$M$3:$M$100000,"Not Run") | D3: =COUNTIF('IAM & Access'!$M$3:$M$100000,"Pass") | E3: =COUNTIF('IAM & Access'!$M$3:$M$100000,"Fail") | F3: =COUNTIF('IAM & Access'!$M$3:$M$100000,"Blocked") | G3: =COUNTIF('IAM & Access'!$M$3:$M$100000,"N/A") | H3: =IFERROR(D3/(D3+E3),"")
A4: RBAC | B4: 20 | C4: =COUNTIF('RBAC'!$M$3:$M$100000,"Not Run") | D4: =COUNTIF('RBAC'!$M$3:$M$100000,"Pass") | E4: =COUNTIF('RBAC'!$M$3:$M$100000,"Fail") | F4: =COUNTIF('RBAC'!$M$3:$M$100000,"Blocked") | G4: =COUNTIF('RBAC'!$M$3:$M$100000,"N/A") | H4: =IFERROR(D4/(D4+E4),"")
A5: Platform – Documents | B5: 11 | C5: =COUNTIF('Platform – Documents'!$M$3:$M$100000,"Not Run") | D5: =COUNTIF('Platform – Documents'!$M$3:$M$100000,"Pass") | E5: =COUNTIF('Platform – Documents'!$M$3:$M$100000,"Fail") | F5: =COUNTIF('Platform – Documents'!$M$3:$M$100000,"Blocked") | G5: =COUNTIF('Platform – Documents'!$M$3:$M$100000,"N/A") | H5: =IFERROR(D5/(D5+E5),"")
A6: Platform – Notifications | B6: 7 | C6: =COUNTIF('Platform – Notifications'!$M$3:$M$100000,"Not Run") | D6: =COUNTIF('Platform – Notifications'!$M$3:$M$100000,"Pass") | E6: =COUNTIF('Platform – Notifications'!$M$3:$M$100000,"Fail") | F6: =COUNTIF('Platform – Notifications'!$M$3:$M$100000,"Blocked") | G6: =COUNTIF('Platform – Notifications'!$M$3:$M$100000,"N/A") | H6: =IFERROR(D6/(D6+E6),"")
A7: Platform – Approvals | B7: 17 | C7: =COUNTIF('Platform – Approvals'!$M$3:$M$100000,"Not Run") | D7: =COUNTIF('Platform – Approvals'!$M$3:$M$100000,"Pass") | E7: =COUNTIF('Platform – Approvals'!$M$3:$M$100000,"Fail") | F7: =COUNTIF('Platform – Approvals'!$M$3:$M$100000,"Blocked") | G7: =COUNTIF('Platform – Approvals'!$M$3:$M$100000,"N/A") | H7: =IFERROR(D7/(D7+E7),"")
A8: Platform – Audit | B8: 6 | C8: =COUNTIF('Platform – Audit'!$M$3:$M$100000,"Not Run") | D8: =COUNTIF('Platform – Audit'!$M$3:$M$100000,"Pass") | E8: =COUNTIF('Platform – Audit'!$M$3:$M$100000,"Fail") | F8: =COUNTIF('Platform – Audit'!$M$3:$M$100000,"Blocked") | G8: =COUNTIF('Platform – Audit'!$M$3:$M$100000,"N/A") | H8: =IFERROR(D8/(D8+E8),"")
A9: Conventions | B9: 31 | C9: =COUNTIF('Conventions'!$M$3:$M$100000,"Not Run") | D9: =COUNTIF('Conventions'!$M$3:$M$100000,"Pass") | E9: =COUNTIF('Conventions'!$M$3:$M$100000,"Fail") | F9: =COUNTIF('Conventions'!$M$3:$M$100000,"Blocked") | G9: =COUNTIF('Conventions'!$M$3:$M$100000,"N/A") | H9: =IFERROR(D9/(D9+E9),"")
A10: Masters – Parties | B10: 24 | C10: =COUNTIF('Masters – Parties'!$M$3:$M$100000,"Not Run") | D10: =COUNTIF('Masters – Parties'!$M$3:$M$100000,"Pass") | E10: =COUNTIF('Masters – Parties'!$M$3:$M$100000,"Fail") | F10: =COUNTIF('Masters – Parties'!$M$3:$M$100000,"Blocked") | G10: =COUNTIF('Masters – Parties'!$M$3:$M$100000,"N/A") | H10: =IFERROR(D10/(D10+E10),"")
A11: Masters – Catalog | B11: 20 | C11: =COUNTIF('Masters – Catalog'!$M$3:$M$100000,"Not Run") | D11: =COUNTIF('Masters – Catalog'!$M$3:$M$100000,"Pass") | E11: =COUNTIF('Masters – Catalog'!$M$3:$M$100000,"Fail") | F11: =COUNTIF('Masters – Catalog'!$M$3:$M$100000,"Blocked") | G11: =COUNTIF('Masters – Catalog'!$M$3:$M$100000,"N/A") | H11: =IFERROR(D11/(D11+E11),"")
A12: Sales – Order to Cash | B12: 43 | C12: =COUNTIF('Sales – Order to Cash'!$M$3:$M$100000,"Not Run") | D12: =COUNTIF('Sales – Order to Cash'!$M$3:$M$100000,"Pass") | E12: =COUNTIF('Sales – Order to Cash'!$M$3:$M$100000,"Fail") | F12: =COUNTIF('Sales – Order to Cash'!$M$3:$M$100000,"Blocked") | G12: =COUNTIF('Sales – Order to Cash'!$M$3:$M$100000,"N/A") | H12: =IFERROR(D12/(D12+E12),"")
A13: Sales – Pricing | B13: 18 | C13: =COUNTIF('Sales – Pricing'!$M$3:$M$100000,"Not Run") | D13: =COUNTIF('Sales – Pricing'!$M$3:$M$100000,"Pass") | E13: =COUNTIF('Sales – Pricing'!$M$3:$M$100000,"Fail") | F13: =COUNTIF('Sales – Pricing'!$M$3:$M$100000,"Blocked") | G13: =COUNTIF('Sales – Pricing'!$M$3:$M$100000,"N/A") | H13: =IFERROR(D13/(D13+E13),"")
A14: POS | B14: 23 | C14: =COUNTIF('POS'!$M$3:$M$100000,"Not Run") | D14: =COUNTIF('POS'!$M$3:$M$100000,"Pass") | E14: =COUNTIF('POS'!$M$3:$M$100000,"Fail") | F14: =COUNTIF('POS'!$M$3:$M$100000,"Blocked") | G14: =COUNTIF('POS'!$M$3:$M$100000,"N/A") | H14: =IFERROR(D14/(D14+E14),"")
A15: Procurement (P2P) | B15: 41 | C15: =COUNTIF('Procurement (P2P)'!$M$3:$M$100000,"Not Run") | D15: =COUNTIF('Procurement (P2P)'!$M$3:$M$100000,"Pass") | E15: =COUNTIF('Procurement (P2P)'!$M$3:$M$100000,"Fail") | F15: =COUNTIF('Procurement (P2P)'!$M$3:$M$100000,"Blocked") | G15: =COUNTIF('Procurement (P2P)'!$M$3:$M$100000,"N/A") | H15: =IFERROR(D15/(D15+E15),"")
A16: Inventory | B16: 40 | C16: =COUNTIF('Inventory'!$M$3:$M$100000,"Not Run") | D16: =COUNTIF('Inventory'!$M$3:$M$100000,"Pass") | E16: =COUNTIF('Inventory'!$M$3:$M$100000,"Fail") | F16: =COUNTIF('Inventory'!$M$3:$M$100000,"Blocked") | G16: =COUNTIF('Inventory'!$M$3:$M$100000,"N/A") | H16: =IFERROR(D16/(D16+E16),"")
A17: Manufacturing | B17: 38 | C17: =COUNTIF('Manufacturing'!$M$3:$M$100000,"Not Run") | D17: =COUNTIF('Manufacturing'!$M$3:$M$100000,"Pass") | E17: =COUNTIF('Manufacturing'!$M$3:$M$100000,"Fail") | F17: =COUNTIF('Manufacturing'!$M$3:$M$100000,"Blocked") | G17: =COUNTIF('Manufacturing'!$M$3:$M$100000,"N/A") | H17: =IFERROR(D17/(D17+E17),"")
A18: General Ledger | B18: 35 | C18: =COUNTIF('General Ledger'!$M$3:$M$100000,"Not Run") | D18: =COUNTIF('General Ledger'!$M$3:$M$100000,"Pass") | E18: =COUNTIF('General Ledger'!$M$3:$M$100000,"Fail") | F18: =COUNTIF('General Ledger'!$M$3:$M$100000,"Blocked") | G18: =COUNTIF('General Ledger'!$M$3:$M$100000,"N/A") | H18: =IFERROR(D18/(D18+E18),"")
A19: Accounts Receivable | B19: 23 | C19: =COUNTIF('Accounts Receivable'!$M$3:$M$100000,"Not Run") | D19: =COUNTIF('Accounts Receivable'!$M$3:$M$100000,"Pass") | E19: =COUNTIF('Accounts Receivable'!$M$3:$M$100000,"Fail") | F19: =COUNTIF('Accounts Receivable'!$M$3:$M$100000,"Blocked") | G19: =COUNTIF('Accounts Receivable'!$M$3:$M$100000,"N/A") | H19: =IFERROR(D19/(D19+E19),"")
A20: Accounts Payable | B20: 20 | C20: =COUNTIF('Accounts Payable'!$M$3:$M$100000,"Not Run") | D20: =COUNTIF('Accounts Payable'!$M$3:$M$100000,"Pass") | E20: =COUNTIF('Accounts Payable'!$M$3:$M$100000,"Fail") | F20: =COUNTIF('Accounts Payable'!$M$3:$M$100000,"Blocked") | G20: =COUNTIF('Accounts Payable'!$M$3:$M$100000,"N/A") | H20: =IFERROR(D20/(D20+E20),"")
A21: Cash & Bank | B21: 27 | C21: =COUNTIF('Cash & Bank'!$M$3:$M$100000,"Not Run") | D21: =COUNTIF('Cash & Bank'!$M$3:$M$100000,"Pass") | E21: =COUNTIF('Cash & Bank'!$M$3:$M$100000,"Fail") | F21: =COUNTIF('Cash & Bank'!$M$3:$M$100000,"Blocked") | G21: =COUNTIF('Cash & Bank'!$M$3:$M$100000,"N/A") | H21: =IFERROR(D21/(D21+E21),"")
A22: Tax (VAT/WHT) | B22: 29 | C22: =COUNTIF('Tax (VAT-WHT)'!$M$3:$M$100000,"Not Run") | D22: =COUNTIF('Tax (VAT-WHT)'!$M$3:$M$100000,"Pass") | E22: =COUNTIF('Tax (VAT-WHT)'!$M$3:$M$100000,"Fail") | F22: =COUNTIF('Tax (VAT-WHT)'!$M$3:$M$100000,"Blocked") | G22: =COUNTIF('Tax (VAT-WHT)'!$M$3:$M$100000,"N/A") | H22: =IFERROR(D22/(D22+E22),"")
A23: FX & Multicurrency | B23: 19 | C23: =COUNTIF('FX & Multicurrency'!$M$3:$M$100000,"Not Run") | D23: =COUNTIF('FX & Multicurrency'!$M$3:$M$100000,"Pass") | E23: =COUNTIF('FX & Multicurrency'!$M$3:$M$100000,"Fail") | F23: =COUNTIF('FX & Multicurrency'!$M$3:$M$100000,"Blocked") | G23: =COUNTIF('FX & Multicurrency'!$M$3:$M$100000,"N/A") | H23: =IFERROR(D23/(D23+E23),"")
A24: Reporting & BI | B24: 23 | C24: =COUNTIF('Reporting & BI'!$M$3:$M$100000,"Not Run") | D24: =COUNTIF('Reporting & BI'!$M$3:$M$100000,"Pass") | E24: =COUNTIF('Reporting & BI'!$M$3:$M$100000,"Fail") | F24: =COUNTIF('Reporting & BI'!$M$3:$M$100000,"Blocked") | G24: =COUNTIF('Reporting & BI'!$M$3:$M$100000,"N/A") | H24: =IFERROR(D24/(D24+E24),"")
A25: Fixed Assets | B25: 20 | C25: =COUNTIF('Fixed Assets'!$M$3:$M$100000,"Not Run") | D25: =COUNTIF('Fixed Assets'!$M$3:$M$100000,"Pass") | E25: =COUNTIF('Fixed Assets'!$M$3:$M$100000,"Fail") | F25: =COUNTIF('Fixed Assets'!$M$3:$M$100000,"Blocked") | G25: =COUNTIF('Fixed Assets'!$M$3:$M$100000,"N/A") | H25: =IFERROR(D25/(D25+E25),"")
A26: Budgeting | B26: 21 | C26: =COUNTIF('Budgeting'!$M$3:$M$100000,"Not Run") | D26: =COUNTIF('Budgeting'!$M$3:$M$100000,"Pass") | E26: =COUNTIF('Budgeting'!$M$3:$M$100000,"Fail") | F26: =COUNTIF('Budgeting'!$M$3:$M$100000,"Blocked") | G26: =COUNTIF('Budgeting'!$M$3:$M$100000,"N/A") | H26: =IFERROR(D26/(D26+E26),"")
A27: HR & Payroll | B27: 37 | C27: =COUNTIF('HR & Payroll'!$M$3:$M$100000,"Not Run") | D27: =COUNTIF('HR & Payroll'!$M$3:$M$100000,"Pass") | E27: =COUNTIF('HR & Payroll'!$M$3:$M$100000,"Fail") | F27: =COUNTIF('HR & Payroll'!$M$3:$M$100000,"Blocked") | G27: =COUNTIF('HR & Payroll'!$M$3:$M$100000,"N/A") | H27: =IFERROR(D27/(D27+E27),"")
A28: CRM | B28: 30 | C28: =COUNTIF('CRM'!$M$3:$M$100000,"Not Run") | D28: =COUNTIF('CRM'!$M$3:$M$100000,"Pass") | E28: =COUNTIF('CRM'!$M$3:$M$100000,"Fail") | F28: =COUNTIF('CRM'!$M$3:$M$100000,"Blocked") | G28: =COUNTIF('CRM'!$M$3:$M$100000,"N/A") | H28: =IFERROR(D28/(D28+E28),"")
A29: Projects | B29: 26 | C29: =COUNTIF('Projects'!$M$3:$M$100000,"Not Run") | D29: =COUNTIF('Projects'!$M$3:$M$100000,"Pass") | E29: =COUNTIF('Projects'!$M$3:$M$100000,"Fail") | F29: =COUNTIF('Projects'!$M$3:$M$100000,"Blocked") | G29: =COUNTIF('Projects'!$M$3:$M$100000,"N/A") | H29: =IFERROR(D29/(D29+E29),"")
A30: TOTAL | B30: =SUM(B3:B29) | C30: =SUM(C3:C29) | D30: =SUM(D3:D29) | E30: =SUM(E3:E29) | F30: =SUM(F3:F29) | G30: =SUM(G3:G29) | H30: =IFERROR(D30/(D30+E30),"")

Sheet IAM & Access
A1: IAM & Access — UAT
A2: ID | B2: Area | C2: Test Scenario | D2: Type | E2: Priority | F2: Preconditions | G2: Steps | H2: Test Data | I2: Expected Result | J2: Route | K2: Permission | L2: Actual Result | M2: Status | N2: Severity | O2: Tester | P2: Run Date | Q2: Comments
A3: IAM-001 | B3: Authentication | C3: Successful login lands in admin shell with correct user and branch displayed | D3: Positive | E3: High | F3: App running. rootadmin user exists with known password. At least one active company and branch exist. | G3: 1. Navigate to /login. 2. Enter username 'rootadmin' and its known password. 3. Click Sign In. 4. Wait for the admin shell to load. | H3: username: rootadmin, password: RootPass12345 | I3: Redirect to /admin. Topbar shows the user's display name or initials. The active branch name appears in the branch selector. No raw uid is shown anywhere on screen. | J3: /login | M3: Not Run
A4: IAM-002 | B4: Authentication | C4: Login with wrong password returns generic error — no user enumeration | D4: Negative | E4: High | F4: Known existing username (e.g. org.admin). | G4: 1. Navigate to /login. 2. Enter username 'org.admin' and password 'totally-wrong-1'. 3. Click Sign In. | H4: username: org.admin, password: totally-wrong-1 | I4: Stays on /login. Inline error message appears (generic 'Sign-in failed' or similar). No red modal dialog. POST /api/v1/auth/login returns 401. Error text is identical to the unknown-username case (IAM-003) — no user enumeration. | J4: /login | M4: Not Run
A5: IAM-003 | B5: Authentication | C5: Login with unknown username returns the same generic error as wrong password | D5: Negative | E5: High | F5: None. | G5: 1. Navigate to /login. 2. Enter username 'does.not.exist' and password 'Whatever123'. 3. Click Sign In. 4. Compare the error text to IAM-002's error text. | H5: username: does.not.exist, password: Whatever123 | I5: Stays on /login. Error text is word-for-word identical to the wrong-password error. 401 returned. No timing difference observable. No indication whether the username exists. | J5: /login | M5: Not Run
A6: IAM-004 | B6: Authentication | C6: Account lockout after 5 consecutive failed attempts; locked message appears | D6: Edge | E6: High | F6: A dedicated non-root test user (e.g. lockme.user) exists with a known correct password. | G6: 1. Navigate to /login. 2. Submit wrong password 5 times for 'lockme.user'. 3. On the 6th attempt submit the CORRECT password. | H6: username: lockme.user, wrong password: bad-pass-1 (×5), correct password: known value | I6: Attempts 1–4 return generic invalid-credentials message. Attempt 5 (threshold) and attempt 6 with correct password both return a distinct 'Account is locked. Try again later or contact an administrator.' message. Login is refused even with correct credentials while locked. | J6: /login | M6: Not Run
A7: IAM-005 | B7: Authentication | C7: Disabled (INACTIVE) user cannot log in | D7: Negative | E7: High | F7: A user disabled via IAM-021 (status INACTIVE). Correct password is known. | G7: 1. Navigate to /login. 2. Enter the disabled user's username and correct password. 3. Click Sign In. | H7: username: disabled.user, correct password | I7: Stays on /login. Generic invalid-credentials error shown. 401 returned. Reason for refusal not disclosed. | J7: /login | M7: Not Run
A8: IAM-006 | B8: Authentication | C8: Token refresh rotates the refresh token (single-use); reuse triggers chain revocation | D8: Edge | E8: Medium | F8: A valid login session. Capture the refreshToken R1 from the login response. | G8: 1. POST /api/v1/auth/refresh with R1 — capture new tokens (access2, R2). 2. POST /api/v1/auth/refresh again with R1 (the already-used token). 3. POST /api/v1/auth/refresh with R2 (the valid new one). | H8: R1: captured refresh token from login | I8: Step 1: 200, new access and refresh tokens returned. Step 2: 401 'Refresh token already used. Please sign in again.' (chain revoked). Step 3: also 401 — the whole chain is revoked upon reuse detection. | M8: Not Run
A9: IAM-007 | B9: Authentication | C9: Logout revokes the refresh token and clears the session | D9: Positive | E9: Medium | F9: An active logged-in session. | G9: 1. Log in as any user. 2. Open the user menu in the topbar; click Logout. 3. Attempt to navigate to /admin. 4. After logout, replay the revoked refresh token via POST /api/v1/auth/refresh. | H9: Any active user | I9: POST /api/v1/auth/logout returns 204. Browser redirects to /login. Navigating to /admin again redirects back to /login. Replaying the revoked refresh token returns 401. | J9: /admin | M9: Not Run
A10: IAM-008 | B10: Authentication | C10: Expired/invalid access token triggers session-expired toast and redirect to login | D10: Negative | E10: Medium | F10: A logged-in session. | G10: 1. Log in. 2. Corrupt or manually expire the stored access token (tamper localStorage). 3. Navigate to /admin/users to trigger an API call. | H10: Tampered access token | I10: The API returns 401. The auth error interceptor clears the session, shows a toast 'Your session has expired. Please sign in again.', and redirects to /login. No infinite redirect loop. | J10: /admin/users | M10: Not Run
A11: IAM-009 | B11: Authentication | C11: Login client-side guard: blank username/password prevents form submission | D11: Negative | E11: Medium | F11: None. | G11: 1. Navigate to /login. 2. Leave both username and password blank. 3. Click Sign In. | H11: No input | I11: Inline validation error appears ('Enter your username and password.' or similar). No POST /api/v1/auth/login is issued. Whitespace-only username is treated as empty. | J11: /login | M11: Not Run
A12: IAM-010 | B12: Authentication | C12: GET /auth/me drives permission-aware navigation (items hidden for missing permissions) | D12: Positive | E12: High | F12: Three users: NO-PERMISSION user (no roles), a CUSTOM-role user (COMPANY.VIEW + USER.VIEW only), ORG_ADMIN. | G12: 1. Log in as the NO-PERMISSION user; inspect the sidebar items. 2. Log out; log in as the CUSTOM-role user; inspect the sidebar. 3. Log out; log in as ORG_ADMIN; inspect the sidebar. | H12: Users: qa.noperm, qa.custom (COMPANY.VIEW+USER.VIEW), qa.orgadmin | I12: NO-PERMISSION: no permission-gated nav items visible. CUSTOM: only Companies and Users nav items appear. ORG_ADMIN: all Administration items visible. GET /api/v1/auth/me returns the corresponding permissions[] array for each. | J12: /admin | M12: Not Run
A13: IAM-011 | B13: Authentication | C13: GET /auth/my-branches lists only ACTIVE switchable branches for the user | D13: Positive | E13: Medium | F13: A user assigned to at least 2 ACTIVE branches and 1 ARCHIVED/inactive branch. | G13: 1. Log in as that user. 2. Open the topbar branch selector. | H13: User with branches: HQ (ACTIVE), Mwanza (ACTIVE), Old Branch (ARCHIVED) | I13: Only the two ACTIVE branches appear in the selector. The archived branch is not listed. Branches are shown by name, not by uid. The current active branch is highlighted. | J13: /admin | M13: Not Run
A14: IAM-012 | B14: Authentication | C14: Branch switch re-resolves permissions and sends X-Branch-Uid header | D14: Positive | E14: High | F14: A user assigned to Branch A (default) and Branch B, with different effective grants per branch. | G14: 1. Log in (lands on Branch A). Note the nav items. 2. Open the branch selector; pick Branch B by name. 3. Observe the nav items and confirm subsequent API calls carry X-Branch-Uid: <B-uid>. | H14: Branch A: HQ (default), Branch B: Mwanza Depot | I14: After switching to Branch B, GET /api/v1/auth/me is called with X-Branch-Uid header set to Branch B's uid. Nav recomputes to reflect Branch B's effective permissions. No re-login required. Branch is selected by name — uid only goes in the header. | J14: /admin | M14: Not Run
A15: IAM-013 | B15: Users | C15: Create a user with valid data | D15: Positive | E15: High | F15: Logged in as ORG_ADMIN (holds USER.MANAGE). | G15: 1. Navigate to /admin/users. 2. Fill the create form: username, display name, password. 3. Submit. | H15: username: new.clerk, displayName: New Clerk, password: Welcome123 | I15: POST /api/v1/users returns 201. New row appears in the table showing username and display name (no uid visible). Toast 'User created'. is_root is false. User status is ACTIVE. | J15: /admin/users | K15: USER.MANAGE | M15: Not Run
A16: IAM-014 | B16: Users | C16: Create user: duplicate username rejected (case-insensitive) | D16: Negative | E16: High | F16: Logged in as ORG_ADMIN. Existing username 'org.admin' is present. | G16: 1. Navigate to /admin/users. 2. Submit create form with username 'ORG.ADMIN' (different case). | H16: username: ORG.ADMIN (duplicate of org.admin) | I16: 409 returned. Inline form error 'Username already exists: org.admin'. No new row added. | J16: /admin/users | K16: USER.MANAGE | M16: Not Run
A17: IAM-015 | B17: Users | C17: Create user: password too short (< 8 chars) rejected | D17: Negative | E17: High | F17: Logged in as ORG_ADMIN. | G17: 1. Navigate to /admin/users. 2. Submit create form with password 'Ab1' (3 chars). | H17: password: Ab1 | I17: 400 or 409 with error 'Password must be at least 8 characters.' Inline error shown. User not created. Boundary: exactly 8 chars passes; 7 chars fails. | J17: /admin/users | K17: USER.MANAGE | M17: Not Run
A18: IAM-016 | B18: Users | C18: Create user: common password rejected; no-letter and no-digit passwords rejected | D18: Negative | E18: High | F18: Logged in as ORG_ADMIN. | G18: 1. Attempt (a) password 'abcdefgh' (no digit). 2. Attempt (b) password 'password1' (common list). 3. Attempt (c) password '12345678' (no letter + common). 4. Attempt (d) password 'Welcome123' (valid). | H18: passwords: abcdefgh, password1, 12345678, Welcome123 | I18: (a) 'Password must contain letters and at least one number.' (b) 'Password is too common; choose a stronger one.' (c) rejected (no letter and common). (d) user created successfully. Each common-list entry (password, password1, 12345678, qwerty123, admin123, letmein123, changeme, welcome1, passw0rd) is rejected. | J18: /admin/users | K18: USER.MANAGE | M18: Not Run
A19: IAM-017 | B19: Users | C19: Disable an active user (status → INACTIVE) | D19: Positive | E19: High | F19: Logged in as ORG_ADMIN. An ACTIVE non-root user exists. | G19: 1. Navigate to /admin/users. 2. On the target row, click Disable. 3. Reload the page. | H19: Target user: new.clerk (ACTIVE) | I19: PUT /api/v1/users/uid/{uid}/disable returns 204. On reload GET /api/v1/users shows the user with status 'INACTIVE'. Disable action is NOT rendered for root users. | J19: /admin/users | K19: USER.MANAGE | M19: Not Run
A20: IAM-018 | B20: Users | C20: Enable a disabled user (status → ACTIVE); re-login then succeeds | D20: Positive | E20: Medium | F20: An INACTIVE user (from IAM-017). | G20: 1. Navigate to /admin/users. 2. On the disabled row, click Enable. 3. Log out; log in as the re-enabled user. | H20: Target user: new.clerk (INACTIVE) | I20: PUT /api/v1/users/uid/{uid}/enable returns 204. Status returns to ACTIVE on reload. The user can log in again. | J20: /admin/users | K20: USER.MANAGE | M20: Not Run
A21: IAM-019 | B21: Users | C21: Admin unlock clears lockout; login then succeeds | D21: Positive | E21: Medium | F21: A locked user (from IAM-004). | G21: 1. Log in as ORG_ADMIN; navigate to /admin/users. 2. Locate the locked user; click Unlock. 3. Log out; log in as the unlocked user with the correct password. | H21: Locked user: lockme.user | I21: PUT /api/v1/users/uid/{uid}/unlock returns 204. User row no longer shows locked status. Subsequent login with correct password succeeds. | J21: /admin/users | K21: USER.MANAGE | M21: Not Run
A22: IAM-020 | B22: Users | C22: Admin password reset; user can log in with new password | D22: Positive | E22: High | F22: Logged in as ORG_ADMIN. A non-root user exists. | G22: 1. Navigate to /admin/users. 2. Expand the set-password form for the target user. 3. Enter a policy-valid password; save. 4. Log out; log in as that user with the new password. | H22: New password: Reset2026 | I22: PUT /api/v1/users/uid/{uid}/password returns 204. Toast 'Password updated'. Password never appears in a log or audit detail. Login with the new password succeeds. | J22: /admin/users | K22: USER.MANAGE | M22: Not Run
A23: IAM-021 | B23: Users | C23: Viewer-only user (USER.VIEW, no USER.MANAGE) cannot perform management actions | D23: Permission | E23: High | F23: A user holding USER.VIEW but NOT USER.MANAGE. | G23: 1. Log in as the view-only user. 2. Navigate to /admin/users (list loads). 3. Attempt to click Disable, Unlock, or the set-password form. 4. Force POST /api/v1/users directly. | H23: User: qa.viewer (USER.VIEW only) | I23: List renders. Management actions (Disable, Enable, Unlock, Set Password, Create) are hidden. Forced POST returns 403. No red modal — 403 is handled as a calm state. | J23: /admin/users | K23: USER.VIEW | M23: Not Run
A24: IAM-022 | B24: Users | C24: No-permission user cannot reach /admin/users; route guard redirects to /admin/home | D24: Permission | E24: High | F24: A user with no roles/permissions (qa.noperm). | G24: 1. Log in as qa.noperm. 2. Navigate directly to /admin/users. | H24: User: qa.noperm | I24: Route guard redirects to /admin/home. The Users nav item is absent from the sidebar. GET /api/v1/users returns 403. | J24: /admin/users | M24: Not Run
A25: IAM-023 | B25: Users | C25: User detail: uid only in URL, never displayed; branch/role panels use name pickers | D25: Positive | E25: High | F25: Logged in as ORG_ADMIN. A user exists. | G25: 1. From /admin/users, click the row action to open /admin/users/uid/:uid. 2. Inspect the page header, branch-assignment panel, and role-grant panel. 3. Scan all visible text for uid strings. | H25: Any existing user | I25: Header shows username/display name/status — no uid text. The uid appears only in the URL path. Branch and role pickers select by name from dropdowns. No raw uid is typed or shown in any label or cell. | J25: /admin/users/uid/:uid | K25: USER.VIEW | M25: Not Run
A26: IAM-024 | B26: Roles | C26: Create a role with org-unique code | D26: Positive | E26: High | F26: Logged in as ORG_ADMIN (holds ROLE.MANAGE). | G26: 1. Navigate to /admin/roles. 2. Fill create form: code, name, optional description. 3. Submit. | H26: code: BRANCH_SUP, name: Branch Supervisor, description: Reviews branch ops | I26: POST /api/v1/roles returns 201. New row appears. Role is non-system (system: false), status ACTIVE, empty permissionCodes. Row links to /admin/roles/uid/:uid — uid only in URL. | J26: /admin/roles | K26: ROLE.MANAGE | M26: Not Run
A27: IAM-025 | B27: Roles | C27: Create role: duplicate code rejected | D27: Negative | E27: High | F27: Role with code BRANCH_SUP already exists. | G27: 1. Navigate to /admin/roles. 2. Submit create form with code 'BRANCH_SUP'. | H27: code: BRANCH_SUP (duplicate) | I27: 409 returned. Inline error 'Role code already exists: BRANCH_SUP'. No row added. | J27: /admin/roles | K27: ROLE.MANAGE | M27: Not Run
A28: IAM-026 | B28: Roles | C28: Set role permissions via grouped checkbox UI (replace semantics) | D28: Positive | E28: High | F28: Logged in as ORG_ADMIN (holds ROLE.MANAGE + PERMISSION.VIEW). A custom role exists. | G28: 1. Navigate to /admin/roles/uid/:uid for the custom role. 2. Check USER.VIEW and USER.MANAGE; uncheck all others. 3. Save permissions. | H28: Role: BRANCH_SUP; permissions to set: USER.VIEW, USER.MANAGE | I28: PUT /api/v1/roles/uid/{uid}/permissions returns 200 RoleDto with sorted permissionCodes [USER.MANAGE, USER.VIEW]. Checkbox state reflects the saved set. Saving an empty list is valid (clears all permissions). | J28: /admin/roles/uid/:uid | K28: ROLE.MANAGE | M28: Not Run
A29: IAM-027 | B29: Roles | C29: Archive a non-system role; system role archive blocked | D29: Positive | E29: High | F29: Logged in as ORG_ADMIN. A custom non-system role and a seeded system role (e.g. ORG_ADMIN) both exist. | G29: 1. Archive the custom role BRANCH_SUP. 2. Attempt to archive the system role ORG_ADMIN. | H29: Custom role: BRANCH_SUP, System role: ORG_ADMIN | I29: Custom role: 204, status ARCHIVED (soft-delete, row still exists). System role attempt: 409 'System role cannot be archived: ORG_ADMIN'. Cache invalidated after archive. | J29: /admin/roles | K29: ROLE.MANAGE | M29: Not Run
A30: IAM-028 | B30: Roles | C30: ROLE.VIEW-only user cannot create or edit roles; edit route redirects to home | D30: Permission | E30: High | F30: A user holding ROLE.VIEW but NOT ROLE.MANAGE. | G30: 1. Log in as the ROLE.VIEW-only user. 2. Navigate to /admin/roles (list loads). 3. Navigate directly to /admin/roles/uid/:uid (the edit screen). | H30: User: qa.roleviewer (ROLE.VIEW only) | I30: List loads. Create form/button is hidden. Direct navigation to the edit route redirects to /admin/home. PUT /api/v1/roles/uid/{uid}/permissions returns 403. | J30: /admin/roles | K30: ROLE.VIEW | M30: Not Run
A31: IAM-029 | B31: Role Assignment | C31: Grant a company-wide role to a user via pickers (no uid typed) | D31: Positive | E31: High | F31: Logged in as ORG_ADMIN (holds ROLE.MANAGE). Target user and role exist. | G31: 1. Navigate to /admin/role-grants. 2. Choose user by display name (picker), role by name, company by name; leave branch blank. 3. Click Grant. | H31: user: New Clerk, role: Branch Supervisor, company: (active company name) | I31: POST /api/v1/user-roles returns 201 UserRoleDto with branchUid: null. Toast 'Role granted'. Grant appears when the user's grants are listed. No uid typed or shown during the process. | J31: /admin/role-grants | K31: ROLE.MANAGE | M31: Not Run
A32: IAM-030 | B32: Role Assignment | C32: Grant role scoped to a specific branch (branch picker loads on company selection) | D32: Positive | E32: High | F32: Logged in as ORG_ADMIN. Multi-branch company exists. | G32: 1. Navigate to /admin/role-grants. 2. Pick user, role, company; after company selection the branch picker reloads. 3. Pick a branch by name; click Grant. | H32: user: New Clerk, role: Branch Supervisor, branch: Mwanza Depot | I32: 201 with branchUid set to the chosen branch. Grant is effective only in that branch context. Branch selected by name — uid stored under the hood. | J32: /admin/role-grants | K32: ROLE.MANAGE | M32: Not Run
A33: IAM-031 | B33: Role Assignment | C33: Duplicate active grant rejected (same user/role/company/branch combination) | D33: Negative | E33: Medium | F33: An existing active grant for a user+role+company+branch combination. | G33: 1. Navigate to /admin/role-grants. 2. Attempt to re-grant the exact same combination. | H33: Same user, role, company, branch as an existing active grant | I33: 409 'Active grant already exists for this user/role/company/branch combination.' Inline form error. No duplicate row created. | J33: /admin/role-grants | K33: ROLE.MANAGE | M33: Not Run
A34: IAM-032 | B34: Role Assignment | C34: Revoke a role grant; grantee's effective permissions drop | D34: Positive | E34: High | F34: Logged in as ORG_ADMIN. A grant exists for a target user. | G34: 1. Navigate to /admin/role-grants; look up grants for the target user. 2. On a grant row, click Revoke. 3. Have the target user call GET /api/v1/customers to verify permission loss. | H34: Target user with an active grant | I34: DELETE /api/v1/user-roles/uid/{uid} returns 204. Row removed from list on reload. Target user immediately loses the revoked permissions (cache invalidated). Their subsequent API call returns 403. | J34: /admin/role-grants | K34: ROLE.MANAGE | M34: Not Run
A35: IAM-033 | B35: Role Assignment | C35: Cross-tenant role grant denied (ScopeGuard): acting in Company A cannot grant in Company B | D35: Permission | E35: High | F35: Two companies A and B. Non-root ORG_ADMIN scoped to Company A. Company B has a grant to revoke. | G35: 1. Log in as Company A's admin (active company = A). 2. POST /api/v1/user-roles with companyUid = Company B. 3. DELETE a Company-B grant uid. | H35: companyUid: Company B's uid | I35: Both calls return 403. ScopeGuard.assertCanActIn denies cross-company action. rootadmin performing the same action succeeds and emits a ROOT.BYPASS audit row. | J35: /admin/role-grants | K35: ROLE.MANAGE | M35: Not Run
A36: IAM-034 | B36: Branch Assignment | C36: Assign a user to a branch (non-default) via the user-detail panel | D36: Positive | E36: High | F36: Logged in as ORG_ADMIN (holds BRANCH.ASSIGN). A user with no branch assignment and a company with branches exist. | G36: 1. Navigate to /admin/users/uid/:uid. 2. In the Branch panel: pick company by name, then pick branch by name; leave make-default unchecked. 3. Click Assign. | H36: Branch: HQ | I36: POST /api/v1/user-branches returns 201. Branch appears in the user's assignments by name. No uid typed or shown. | J36: /admin/users/uid/:uid | K36: BRANCH.ASSIGN | M36: Not Run
... A49: IAM-047 | B49: Companies & Branches | C49: rootadmin cannot be disabled via the API (409 safeguard) | D49: Edge | E49: High | F49: Logged in as ORG_ADMIN with USER.MANAGE. | G49: 1. Call PUT /api/v1/users/uid/{rootadmin-uid}/disable directly. | H49: rootadmin uid | I49: 409 'A root administrator cannot be disabled via the API.' No status change. The Disable action is not rendered for root users in the UI. | J49: /admin/users | K49: USER.MANAGE | M49: Not Run

Sheet RBAC
A1: RBAC — UAT
A2: ID | B2: Area | C2: Test Scenario | D2: Type | E2: Priority | F2: Preconditions | G2: Steps | H2: Test Data | I2: Expected Result | J2: Route | K2: Permission | L2: Actual Result | M2: Status | N2: Severity | O2: Tester | P2: Run Date | Q2: Comments
A3: RBAC-001 | B3: Role Bundles | C3: /auth/me returns correct effective permission set per role | D3: Positive | E3: High | F3: Operational role bundles seeded for: ORG_ADMIN, SALES_MANAGER, SALES_REP, ACCOUNTANT, STOREKEEPER, PURCHASE_OFFICER, CUSTOM (CUSTOMER.VIEW+PRODUCT.VIEW only), NO-PERM. | G3: 1. Log in as each test user in turn. 2. Call GET /api/v1/auth/me and capture permissions[]. | H3: Users: qa.orgadmin, qa.salesmgr, qa.salesrep, qa.accountant, qa.storekeeper, qa.purchaser, qa.custom, qa.noperm | I3: ORG_ADMIN: superset covering all modules. Each operational user: set equals its intended bundle. qa.noperm: permissions: []. rootadmin: isRoot: true. Any divergence from the design matrix is logged as a finding. | J3: /admin | M3: Not Run
A4: RBAC-002 | B4: Role Bundles | C4: ORG_ADMIN can administer companies, users, and roles | D4: Positive | E4: High | F4: qa.orgadmin logged in. | G4: 1. Navigate to /admin/companies, /admin/users, /admin/roles. 2. Confirm all three nav items are visible. 3. Open a create form on each. | H4: qa.orgadmin | I4: All three screens load (four states: loading → loaded). Create forms are reachable. POST on each returns 201. No uid shown in any cell or label. | J4: /admin/companies | K4: COMPANY.MANAGE | M4: Not Run
A5: RBAC-003 | B5: Role Bundles | C5: SALES_MANAGER can create/confirm sales orders; cannot access GL or IAM-admin | D5: Positive | E5: High | F5: qa.salesmgr logged in. At least one customer and product seeded. | G5: 1. Navigate to /admin/sales-orders; create an order (pick customer + product by name). 2. Confirm the order. 3. Navigate directly to /admin/gl/journals. 4. Navigate directly to /admin/users. 5. Call GET /api/v1/gl/journals and GET /api/v1/users directly. | H5: Customer: Acme Traders, product: Sugar 1kg, qty: 5 | I5: Create and Confirm succeed. /admin/gl/journals and /admin/users redirect to /admin/home. GL and Users nav items are absent. Both direct API calls return 403 with the generic message. | J5: /admin/sales-orders | K5: SALES.ORDER.CREATE | M5: Not Run
A6: RBAC-004 | B6: Role Bundles | C6: SALES_REP can create sales orders but NOT confirm or cancel them | D6: Permission | E6: High | F6: qa.salesrep logged in. A DRAFT sales order exists created by the rep. | G6: 1. Create a sales order (succeeds). 2. Look for Confirm and Cancel controls on the order detail. 3. Call PUT /api/v1/sales-orders/uid/{uid}/confirm directly. | H6: qa.salesrep; a DRAFT order | I6: Create returns 201. Confirm and Cancel buttons are NOT rendered (action-level gating). Direct confirm API returns 403. | J6: /admin/sales-orders | K6: SALES.ORDER.CREATE | M6: Not Run
A7: RBAC-005 | B7: Role Bundles | C7: ACCOUNTANT can post GL, record AR receipts, run AP payments; cannot create sales or manage users | D7: Positive | E7: High | F7: qa.accountant logged in. Open fiscal period; an AR invoice and AP bill exist. | G7: 1. Post a balanced journal (pick accounts by name). 2. Record an AR receipt. 3. Run an AP payment. 4. Navigate to /admin/sales-orders/create and /admin/users directly. 5. POST /api/v1/sales-orders directly. | H7: qa.accountant | I7: Steps 1-3 succeed. Steps 4-5: sales-create and users redirect to home / nav hidden. POST /api/v1/sales-orders returns 403. | J7: /admin/gl/journals | K7: GL.POST | M7: Not Run
A8: RBAC-006 | B8: Role Bundles | C8: STOREKEEPER can adjust stock and create/receive stock transfers; cannot access GL or sales | D8: Positive | E8: High | F8: qa.storekeeper logged in. At least one product and two stock locations exist. | G8: 1. Navigate to /admin/stock; adjust on-hand (pick product by name). 2. Navigate to /admin/stock-transfers; create a transfer (pick locations by name); receive it. 3. Navigate directly to /admin/gl/journals and /admin/sales-orders. 4. GET /api/v1/gl/journals directly. | H8: qa.storekeeper | I8: Steps 1-2 succeed. Steps 3-4: GL and sales redirect to home / nav hidden; direct API returns 403. | J8: /admin/stock | K8: STOCK.ADJUST | M8: Not Run
A9: RBAC-007 | B9: Role Bundles | C9: PURCHASE_OFFICER can create POs; cannot approve or void them | D9: Permission | E9: High | F9: qa.purchaser logged in. At least one supplier exists. | G9: 1. Create a PO (pick supplier by name). 2. Look for Approve and Void controls on the PO detail. 3. Call POST /api/v1/purchase-orders/uid/{uid}/approve directly. | H9: qa.purchaser; supplier: ABC Supplies | I9: Create returns 201. Approve and Void controls not rendered (action-level gating). Direct approve returns 403. Segregation of duties enforced by permission code, not ownership. | J9: /admin/purchase-orders | K9: PURCHASE.ORDER.CREATE | M9: Not Run
A10: RBAC-008 | B10: Role Bundles | C10: CUSTOM role (CUSTOMER.VIEW + PRODUCT.VIEW) sees only those two screens; all else hidden/403 | D10: Permission | E10: High | F10: qa.custom user assigned the CUSTOM role (exactly CUSTOMER.VIEW + PRODUCT.VIEW). | G10: 1. Log in as qa.custom. 2. Inspect the sidebar items. 3. Navigate to /admin/customers and /admin/products (load). 4. Navigate to /admin/suppliers, /admin/sales-orders, /admin/gl/journals directly. 5. POST /api/v1/customers and GET /api/v1/suppliers directly. | H10: qa.custom | I10: Sidebar shows only Customers and Products (no Create button — lacks MANAGE codes). Other routes redirect to /admin/home. POST /api/v1/customers returns 403. GET /api/v1/suppliers returns 403. | J10: /admin/customers | K10: CUSTOMER.VIEW | M10: Not Run
A11: RBAC-009 | B11: Role Bundles | C11: NO-PERM user: empty nav, every protected screen redirects, every API returns 403 | D11: Permission | E11: High | F11: qa.noperm user has no role grant. | G11: 1. Log in as qa.noperm. 2. Inspect the sidebar. 3. Navigate directly to /admin/customers, /admin/users, /admin/gl/journals. 4. Call GET /api/v1/customers and GET /api/v1/users. | H11: qa.noperm | I11: Sidebar shows no permission-gated items. Every protected route redirects to /admin/home. All protected API calls return 403 with the generic message. GET /api/v1/auth/me returns permissions: []. GET /auth/my-branches still succeeds (authentication, not authorization). | J11: /admin | M11: Not Run
A12: RBAC-010 | B12: Scope Enforcement | C12: Cross-tenant denial: ORG_ADMIN of Tenant A cannot touch Tenant B's customer | D12: Permission | E12: High | F12: Two tenants A and B, each with a customer. Company A's qa.orgadmin is granted ORG_ADMIN in Company A only. | G12: 1. Log in as Company A admin (active company = A). 2. Obtain Company B customer uid out-of-band. 3. Call PUT /api/v1/customers/uid/{B_customer_uid}. 4. Call GET /api/v1/customers/uid/{B_customer_uid}. | H12: Company B customer: Bravo Ltd | I12: Both calls return 403. ScopeGuard.canActOn detects target's company = B ≠ active A. Company B's customer never appears in Company A's list. An unresolvable uid also returns 403 (not 404 — avoids existence leak). | J12: /admin/customers | K12: CUSTOMER.MANAGE | M12: Not Run
A13: RBAC-011 | B13: Scope Enforcement | C13: @perm.scoped on body companyUid: create denied when companyUid != active company | D13: Permission | E13: High | F13: Two companies A and B. User holds SALES.ORDER.CREATE scoped to Company A. | G13: 1. Log in (active company A). 2. POST /api/v1/sales-orders with companyUid = Company B. 3. POST /api/v1/gl/journals with companyUid = Company B. | H13: companyUid: Company B's uid | I13: Both return 403 (body-scoped guard: holds perm but B != active A). Same calls with companyUid = A succeed (201), proving the gate is scope not the permission itself. | J13: /admin/sales-orders | K13: SALES.ORDER.CREATE | M13: Not Run
A14: RBAC-012 | B14: Scope Enforcement | C14: Branch-scoped grant: user with role only in Branch 1 is denied STOCK.VIEW in Branch 2 | D14: Permission | E14: High | F14: Company A with branch1 (default) and branch2. User granted STOCK.VIEW/STOCK.ADJUST scoped to branch1 only. | G14: 1. Log in (default branch1). View stock → 200. 2. Switch active branch to branch2 (branch selector by name). 3. Call GET /api/v1/stock. | H14: branch1, branch2; STOCK.VIEW grant on branch1 only | I14: branch1: stock loads. After switching to branch2: GET /api/v1/stock returns 403 (no grant in branch2). Nav reflects loss of STOCK.VIEW. Switch back to branch1 restores access — all without re-login. | J14: /admin/stock | K14: STOCK.VIEW | M14: Not Run
A15: RBAC-013 | B15: Scope Enforcement | C15: Company-wide grant (branch_id NULL) works in all branches of the same company | D15: Positive | E15: Medium | F15: Company A with branch1 and branch2. User has STOCK.VIEW granted with branch_id = NULL (all branches). | G15: 1. Log in (branch1). View stock → 200. 2. Switch to branch2. View stock → expect 200. | H15: NULL-branch grant | I15: Stock loads in both branches (NULL branch_id = effective company-wide). Data differs per branch (branch-scoped rows) but the permission holds in both. Switching to a different company branch fails (cross-tenant). | J15: /admin/stock | K15: STOCK.VIEW | M15: Not Run
A16: RBAC-014 | B16: Scope Enforcement | C16: Acting in an unassigned branch via forged X-Branch-Uid is denied | D16: Permission | E16: High | F16: User assigned (UserBranch) to branch1 only. Branch2 exists in the same company. | G16: 1. Log in. 2. Confirm branch2 is NOT in the branch selector (only branch1 listed). 3. Send an API call with X-Branch-Uid: branch2. | H16: branch2 uid (not assigned) | I16: Branch selector shows only branch1. Forged override to branch2 is rejected by the filter (no effective scope there) → 403. The UI cannot reach branch2 at all for this user. | J16: /admin | M16: Not Run
A17: RBAC-015 | B17: Scope Enforcement | C17: Effective permissions update promptly after grant/revoke (cache invalidated) | D17: Edge | E17: Medium | F17: ORG_ADMIN and a target user holding a role with CUSTOMER.VIEW. | G17: 1. As ORG_ADMIN, revoke the target's role (DELETE /api/v1/user-roles/uid/{uid}). 2. Immediately, as the target, call GET /api/v1/customers. 3. Re-grant and retry. | H17: Target user; role with CUSTOMER.VIEW | I17: After revoke: GET /api/v1/customers returns 403 promptly (cache invalidated by invalidate()). After re-grant: 200 returned. GET /api/v1/auth/me reflects the change in the permissions array. | J17: /admin/customers | K17: CUSTOMER.VIEW | M17: Not Run
A18: RBAC-016 | B18: Security Contract | C18: 401 vs 403 response contract; error message never names the required permission | D18: Negative | E18: Medium | F18: A protected endpoint accessible by ORG_ADMIN. | G18: 1. Call the endpoint with no bearer token. 2. Call the same endpoint with a valid token from qa.noperm (insufficient permission). | H18: No token; qa.noperm token | I18: Step 1: 401, body ApiResponse.error('Authentication is required.'). Step 2: 403, body ApiResponse.error('You do not have permission to perform this action.'). Neither message names the required permission code, the resource, or whether it exists. | J18: /api/v1/customers | M18: Not Run
A19: RBAC-017 | B19: Security Contract | C19: Nav-hidden / route-guarded / API-gated are consistent for the same permission code | D19: Positive | E19: High | F19: A user lacking COMPANY.VIEW. | G19: 1. Confirm the Companies nav item is absent from the sidebar. 2. Navigate directly to /admin/companies — confirm redirect to /admin/home. 3. Call GET /api/v1/companies — confirm 403. | H19: User lacking COMPANY.VIEW | I19: All three enforcement points (nav, route guard, API) agree: no Companies access. The same test repeated for STOCK.VIEW (stock), SALES.ORDER.VIEW (sales-orders), GL.VIEW (gl/journals), PURCHASE.ORDER.VIEW (purchase-orders). Any mismatch is a finding. | J19: /admin/companies | K19: COMPANY.VIEW | M19: Not Run
A20: RBAC-018 | B20: Security Contract | C20: POS session/sale/till: non-root users (including ORG_ADMIN) receive 403 — known defect | D20: Negative | E20: High | F20: qa.orgadmin (holds SALES.POS.* codes from V43 seed). A POS till exists. | G20: 1. Log in as qa.orgadmin. 2. Navigate to /admin/pos/sessions; attempt to open a session. 3. Navigate to /admin/pos/sell; attempt to ring a sale. 4. Navigate to /admin/pos/tills; attempt to list/create. 5. Call POST /api/v1/pos/sessions, POST /api/v1/pos/sales, GET /api/v1/pos/tills directly. | H20: qa.orgadmin | I20: EXPECTED FAILURE (known defect): All non-root users get 403 on POS endpoints. Controllers require POS.SESSION.*/POS.SALE.CREATE/POS.TILL.* codes; the seeded catalogue defines SALES.POS.* codes — these do not match. POS nav items are hidden for non-root. Only rootadmin (bypass) can operate POS. Record the defect; do not mark as a pass. | J20: /admin/pos/sessions | K20: POS.SESSION.OPEN | M20: Not Run
A21: RBAC-019 | B21: Security Contract | C21: GL.YEAR.CLOSE restricted to ORG_ADMIN; ACCOUNTANT is denied | D21: Permission | E21: Medium | F21: qa.orgadmin and qa.accountant. A fiscal year eligible to close exists. | G21: 1. As ORG_ADMIN: open the year-end close screen; run the close. 2. As ACCOUNTANT: navigate to the year-end close route; attempt the same via API. | H21: qa.orgadmin, qa.accountant | I21: ORG_ADMIN: close succeeds. ACCOUNTANT: nav hidden, route redirects to home, API returns 403. Closing an already-closed year returns a business 4xx (distinct from 403). | J21: /admin/gl/periods/fiscal-years | K21: GL.YEAR.CLOSE | M21: Not Run
A22: RBAC-020 | B22: Security Contract | C22: NOTIFICATION.ADMIN restricted to ORG_ADMIN; all operational roles get NOTIFICATION.VIEW | D22: Permission | E22: Medium | F22: qa.salesmgr (holds NOTIFICATION.VIEW) and qa.orgadmin (holds NOTIFICATION.ADMIN). | G22: 1. As qa.salesmgr: view notifications and manage own preferences (succeed). Attempt the admin type-catalogue endpoint. 2. As qa.orgadmin: open the admin type catalogue (succeeds). | H22: qa.salesmgr, qa.orgadmin | I22: Operational user: view/preferences OK; admin catalogue endpoint returns 403. ORG_ADMIN: all notifications endpoints succeed. qa.noperm: even NOTIFICATION.VIEW returns 403. | J22: /admin/notifications | K22: NOTIFICATION.ADMIN | M22: Not Run

Sheet Platform – Documents
A1: Platform – Documents — UAT
A2: ID | B2: Area | C2: Test Scenario | D2: Type | E2: Priority | F2: Preconditions | G2: Steps | H2: Test Data | I2: Expected Result | J2: Route | K2: Permission | L2: Actual Result | M2: Status | N2: Severity | O2: Tester | P2: Run Date | Q2: Comments
A3: PLAT-001 | B3: Document Log | C3: Generated documents log lists for the active company | D3: Positive | E3: High | F3: Logged in as ORG_ADMIN (holds DOCUMENT.VIEW). At least one rendered document exists for the company. | G3: 1. Navigate to /admin/documents. 2. Observe the list loads with columns: document number, type badge, source reference, generated-at, download action. | H3: company: Acme Co (default) | I3: GET /api/v1/documents returns 200 ApiResponse<List> + meta (page, size, totalElements, totalPages, hasNext). Table renders rows. No raw uid shown in any column. Paginator present and self-hides when only one page. | J3: /admin/documents | K3: DOCUMENT.VIEW | M3: Not Run
A4: PLAT-002 | B4: Document Log | C4: Documents log: four screen states (loading / empty / error / forbidden) | D4: Edge | E4: Medium | F4: ORG_ADMIN for normal states; NO-PERMISSION user for forbidden state. | G4: 1. Throttle the list response to observe the loading spinner. 2. Switch to a company with no documents to observe the empty state. 3. Force a network error to observe the error state. 4. Log in as NO-PERMISSION user and navigate to /admin/documents. | H4: Empty company; simulated 500; qa.noperm | I4: Each state is visually distinct: loading spinner, explicit 'no documents' message, error panel with retry, forbidden message. Never a silent blank page. NO-PERMISSION: Documents nav group hidden; 403 on direct API call. | J4: /admin/documents | K4: DOCUMENT.VIEW | M4: Not Run
A5: PLAT-003 | B5: Document Log | C5: Filter documents log by DocumentType | D5: Positive | E5: Medium | F5: Logged in as ORG_ADMIN. Documents of mixed types exist. | G5: 1. On /admin/documents choose 'Invoice' in the Type filter. 2. Assert only INVOICE rows show. 3. Switch to 'AR Statement' → only AR_STATEMENT rows. 4. Switch to 'All types' → full list. | H5: Types: INVOICE, AR_STATEMENT | I5: Server-side filter applied (request carries type=INVOICE). Page resets to 0 on filter change. Badge per type. Reserved types (PAYSLIP, QUOTATION, DEBIT_NOTE) are not offered in the filter select. Filter with no matches → empty state. | J5: /admin/documents | K5: DOCUMENT.VIEW | M5: Not Run
A6: PLAT-004 | B6: Document Render | C6: Render an INVOICE document — source chosen via picker by invoice number | D6: Positive | E6: High | F6: Logged in as ORG_ADMIN (holds DOCUMENT.RENDER). A finalised sales invoice exists. | G6: 1. On /admin/documents, click 'Render document'; choose Type = Invoice. 2. In the source picker select the invoice BY its invoice number (not uid). 3. Submit; observe toast and new log row. | H6: Invoice number: INV-2026-0007 | I6: POST /api/v1/documents/render returns 200 GeneratedDocumentDto with downloadUrl. New row appears at top of log showing INVOICE badge. No uid typed or shown during the process. DOCUMENT.VIEW-only user cannot see the render button. | J6: /admin/documents | K6: DOCUMENT.RENDER | M6: Not Run
A7: PLAT-005 | B7: Document Render | C7: Render each renderable DocumentType: PURCHASE_ORDER, GOODS_RECEIPT, DELIVERY_NOTE, CREDIT_NOTE | D7: Positive | E7: High | F7: Logged in as ORG_ADMIN. Source records exist for each type. | G7: For each type (PURCHASE_ORDER, GOODS_RECEIPT, DELIVERY_NOTE, CREDIT_NOTE): 1. Open render form. 2. Select type; pick source by its human number. 3. Submit. | H7: PO-0003, GRN-0002, DEL-0005, RET-0001 | I7: Each render succeeds (200). Correct documentType badge on the new row. Correct source linkage. Source picker for each type shows only records of that type. | J7: /admin/documents | K7: DOCUMENT.RENDER | M7: Not Run
A8: PLAT-006 | B8: Document Render | C8: Render an AR_STATEMENT with JSON sourceParams (customer chosen by name) | D8: Positive | E8: Medium | F8: Logged in as ACCOUNTANT (holds DOCUMENT.RENDER). A customer with open AR items exists. | G8: 1. Open render form; choose Type = AR Statement. 2. The form switches to JSON params input; enter customer (chosen by name via picker) and date range. 3. Submit. | H8: customer: (picked by name), fromDate: 2026-01-01, toDate: 2026-06-30 | I8: Statement renders; row shows AR_STATEMENT badge; 200 returned. AR_STATEMENT submitted with empty params returns inline validation error. Non-statement type with no source uid also fails inline. | J8: /admin/documents | K8: DOCUMENT.RENDER | M8: Not Run
A9: PLAT-007 | B9: Document Render | C9: Render a reserved DocumentType (PAYSLIP) is rejected by the server | D9: Negative | E9: Low | F9: Logged in as ORG_ADMIN. | G9: 1. Call POST /api/v1/documents/render with documentType=PAYSLIP (not selectable in UI). | H9: documentType: PAYSLIP | I9: Request rejected with error envelope (4xx). No log row created. The UI does not offer PAYSLIP/QUOTATION/DEBIT_NOTE in the type select — server enforcement is the backstop. | J9: /admin/documents | K9: DOCUMENT.RENDER | M9: Not Run
A10: PLAT-008 | B10: Document Render | C10: Download a generated PDF (requires DOCUMENT.RENDER; DOCUMENT.VIEW-only is denied) | D10: Positive | E10: High | F10: Logged in as ORG_ADMIN. A generated-document row exists. | G10: 1. On /admin/documents, click the row's Download action. 2. Assert a PDF blob downloads. | H10: Generated document: INV-2026-0007 | I10: GET /api/v1/documents/uid/{uid}/download returns 200 application/pdf, Content-Disposition: attachment; filename='invoice-INV-2026-0007.pdf'. DOCUMENT.VIEW-only user: download returns 403. Cross-tenant uid: 403. | J10: /admin/documents | K10: DOCUMENT.RENDER | M10: Not Run
A11: PLAT-009 | B11: Document Templates | C11: Template registry lists + toggle a template status (DOCUMENT.TEMPLATE.MANAGE) | D11: Positive | E11: High | F11: Logged in as ORG_ADMIN. Seeded template registry rows exist. | G11: 1. Navigate to /admin/document-templates; list loads (full array, not paginated). 2. On the INVOICE row, change status to INACTIVE and edit the title. 3. Save; reload to verify change persisted. | H11: Template: INVOICE / TRANSACTIONAL_PDF; title: Tax Invoice | I11: GET /api/v1/documents/templates returns the template array. PUT /api/v1/documents/templates/{uid} returns 200 with updated DocumentTemplateDto. Status reflected. User without DOCUMENT.TEMPLATE.MANAGE → 403 on PUT and nav item hidden. | J11: /admin/document-templates | K11: DOCUMENT.TEMPLATE.MANAGE | M11: Not Run
A12: PLAT-010 | B12: Document Branding | C12: Edit the company branding profile (singleton — no uid in URL) | D12: Positive | E12: High | F12: Logged in as ORG_ADMIN (holds DOCUMENT.BRANDING.MANAGE). | G12: 1. Navigate to /admin/document-branding; the singleton profile loads into an edit form. 2. Edit display name, legal name, tax id, contact email. 3. Save; reload to verify values persisted. | H12: displayName: Acme Trading, legalName: Acme Trading Ltd, taxId: TIN-123456789, contactEmail: ar@acme.test | I12: PUT /api/v1/documents/branding returns 200 DocumentBrandingDto with updatedAt advanced. Changes persist on reload. Stale version returns conflict error. User without permission → 403; nav item hidden. | J12: /admin/document-branding | K12: DOCUMENT.BRANDING.MANAGE | M12: Not Run
A13: PLAT-011 | B13: Document Branding | C13: Updated branding is reflected in a freshly rendered document (visual check) | D13: Positive | E13: Medium | F13: Logged in as ORG_ADMIN. An invoice source exists. | G13: 1. Change the branding display name. 2. Render a new INVOICE. 3. Download and open the PDF. | H13: New display name: Updated Co Name | I13: The rendered PDF header shows the updated branding display name. Previously generated documents are unchanged (append-only log). This is a visual/manual verification. | J13: /admin/document-branding | K13: DOCUMENT.BRANDING.MANAGE | M13: Not Run

Sheet Platform – Notifications
A1: Platform – Notifications — UAT
A2: ID | B2: Area | C2: Test Scenario | D2: Type | E2: Priority | F2: Preconditions | G2: Steps | H2: Test Data | I2: Expected Result | J2: Route | K2: Permission | L2: Actual Result | M2: Status | N2: Severity | O2: Tester | P2: Run Date | Q2: Comments
A3: PLAT-012 | B3: Inbox | C3: In-app inbox lists the caller's notifications scoped to active company | D3: Positive | E3: High | F3: Logged in as ACCOUNTANT (holds NOTIFICATION.VIEW). Notifications addressed to this user exist. | G3: 1. Navigate to /admin/notifications. 2. Read rows: title, body, severity badge (INFO/WARNING/CRITICAL), created-at. | H3: ACCOUNTANT user with at least 3 notifications | I3: GET /api/v1/notifications returns 200 + meta. Only this user's company notifications shown. Severity badges are visually distinct. Paginator present. NO-PERMISSION user: forbidden. | J3: /admin/notifications | K3: NOTIFICATION.VIEW | M3: Not Run
A4: PLAT-013 | B4: Inbox | C4: Inbox unread filter and shell unread-count badge | D4: Positive | E4: Medium | F4: Logged in as ACCOUNTANT. Mix of read and unread notifications exist. | G4: 1. Toggle 'Unread only' filter on — only unread rows show; request carries unread=true. 2. Read the shell unread-count badge; cross-check against GET /api/v1/notifications/unread-count. | H4: Mix of read + unread notifications | I4: Filtered list shows only unread. Badge value equals UnreadCountDto.count. With zero unread: filter shows empty state; badge shows 0 or is hidden. Page resets to 0 on filter toggle. | J4: /admin/notifications | K4: NOTIFICATION.VIEW | M4: Not Run
A5: PLAT-014 | B5: Inbox | C5: Mark a single notification read; marking another user's notification is denied | D5: Positive | E5: High | F5: Logged in as ACCOUNTANT. An unread notification exists for this user. Another user's notification uid is known. | G5: 1. On /admin/notifications, click 'Mark read' on an unread row. 2. Assert the row flips to read and unread count decrements. 3. Attempt POST /api/v1/notifications/uid/{other-user-uid}/read. | H5: Own unread notification; another user's notification uid | I5: POST /api/v1/notifications/uid/{uid}/read returns 204. Row marked read; readAt set on next fetch. Another user's notification: 403 (recipient-is-me enforced by service, BR-NOTIF-04). Already-read row: no-op. | J5: /admin/notifications | K5: NOTIFICATION.VIEW | M5: Not Run
A6: PLAT-015 | B6: Inbox | C6: Mark all notifications read clears the unread count | D6: Positive | E6: Medium | F6: Logged in as ACCOUNTANT. Several unread notifications exist. | G6: 1. Click 'Mark all read'. 2. Observe toast. 3. Reload — unread count is 0. | H6: Multiple unread notifications | I6: POST /api/v1/notifications/read-all returns 204. All caller notifications marked read. Badge cleared. With no unread: no-op success. | J6: /admin/notifications | K6: NOTIFICATION.VIEW | M6: Not Run
A7: PLAT-016 | B7: Preferences | C7: Per-user notification preferences: list and upsert a preference (NOTIFICATION.PREFERENCE.MANAGE) | D7: Positive | E7: High | F7: Logged in as ACCOUNTANT (holds NOTIFICATION.PREFERENCE.MANAGE). Type catalogue seeded. | G7: 1. Navigate to /admin/notification-preferences; preferences load (plain array). 2. For typeKey LOW_STOCK, toggle muted=true and set channelsEnabled=IN_APP. 3. Save; reload to verify. | H7: typeKey: LOW_STOCK, muted: true, channelsEnabled: IN_APP | I7: PUT /api/v1/notification-preferences/{typeKey} returns 200 NotificationPreferenceDto. Preference persisted per-user scope. Unknown typeKey returns handled error. User without the permission: 403. | J7: /admin/notification-preferences | K7: NOTIFICATION.PREFERENCE.MANAGE | M7: Not Run
A8: PLAT-017 | B8: Admin Catalogue | C8: Admin notification type catalogue: list + toggle company state OFF (NOTIFICATION.ADMIN) | D8: Positive | E8: High | F8: Logged in as ORG_ADMIN (holds NOTIFICATION.ADMIN). Type catalogue seeded. | G8: 1. Navigate to /admin/notification-types; types load with displayName, audiencePermission, severity, companyEnabled. 2. Toggle typeKey LOW_STOCK company state to disabled (enabled=false). 3. Reload — companyEnabled: false. | H8: typeKey: LOW_STOCK | I8: PUT /api/v1/admin/notifications/types/{typeKey}/state returns 200 NotificationTypeDto. companyEnabled=false. Per-company scope — other companies unaffected. NOTIFICATION.VIEW-only user: 403 on toggle; nav item hidden. | J8: /admin/notification-types | K8: NOTIFICATION.ADMIN | M8: Not Run
A9: PLAT-018 | B9: Admin Delivery Log | C9: Admin delivery log lists + filters by channel and outcome (NOTIFICATION.ADMIN) | D9: Positive | E9: High | F9: Logged in as ORG_ADMIN. Delivery attempts of mixed channel/outcome exist. | G9: 1. Navigate to /admin/notification-deliveries; paged delivery log loads. 2. Filter channel=EMAIL → only EMAIL rows. 3. Filter outcome=SUPPRESSED → assert suppressionReason column populated (NO_EMAIL, CHANNEL_DISABLED, COMPANY_TYPE_OFF, MUTED, or NO_AUDIENCE). | H9: channel: EMAIL; outcome: SUPPRESSED | I9: GET /api/v1/admin/notifications/deliveries returns 200 + meta. Correct filtered subsets. outcome + suppressionReason visible (answers 'why didn't I get it?'). Empty filter → empty state. | J9: /admin/notification-deliveries | K9: NOTIFICATION.ADMIN | M9: Not Run

Sheet Platform – Approvals
A1: Platform – Approvals — UAT
A2: ID | B2: Area | C2: Test Scenario | D2: Type | E2: Priority | F2: Preconditions | G2: Steps | H2: Test Data | I2: Expected Result | J2: Route | K2: Permission | L2: Actual Result | M2: Status | N2: Severity | O2: Tester | P2: Run Date | Q2: Comments
A3: PLAT-019 | B3: Approval Policies | C3: Approval policy list for the active company (APPROVALS.POLICY.VIEW) | D3: Positive | E3: High | F3: Logged in as ORG_ADMIN. At least one policy exists. | G3: 1. Navigate to /admin/approvals/policies. 2. Read list: name, documentType, branchScope, amount band, status. | H3: Any company with policies | I3: GET /api/v1/approvals/policies returns 200 + meta. Paginator present. No raw uid in cells. Amount band formatted. NO-PERMISSION: nav items hidden; forbidden state. | J3: /admin/approvals/policies | K3: APPROVALS.POLICY.VIEW | M3: Not Run
A4: PLAT-020 | B4: Approval Policies | C4: Create a COMPANY_WIDE single-step approval policy (APPROVALS.POLICY.MANAGE) | D4: Positive | E4: High | F4: Logged in as ORG_ADMIN. A role code (ACCOUNTANT) exists to use as approverRoleCode. | G4: 1. Click 'New policy'; set documentType=PURCHASE_ORDER, name, branchScope=COMPANY_WIDE. 2. Set minAmount=0, maxAmount=1000000; add 1 step with approverRoleCode=ACCOUNTANT. 3. Submit. | H4: documentType: PURCHASE_ORDER, name: PO <= 1M -> Accountant, minAmount: 0, maxAmount: 1000000, step1 role: ACCOUNTANT | I4: POST /api/v1/approvals/policies returns 201 ApprovalPolicyDto. List reloads with the new ACTIVE policy. Missing name/documentType/minAmount → inline validation, no POST. Empty steps → 'At least one approval step is required'. POLICY.VIEW-only user: 403. | J4: /admin/approvals/policies | K4: APPROVALS.POLICY.MANAGE | M4: Not Run
A5: PLAT-021 | B5: Approval Policies | C5: Create a BRANCH-scoped policy; branch chosen via picker by name | D5: Positive | E5: High | F5: Logged in as ORG_ADMIN. Multi-branch company; a non-default ACTIVE branch exists. | G5: 1. New policy; set branchScope=BRANCH; the branch picker appears. 2. Choose the non-default branch BY NAME. 3. Fill documentType and a step; submit. | H5: branch: Mwanza Depot (non-default), documentType: PURCHASE_ORDER, step role: PURCHASE_OFFICER | I5: Policy created with branchScope=BRANCH and branchId set to the picked branch; 201. branchScope=BRANCH with no branch chosen → inline 'Branch UID is required when branch scope is BRANCH'. COMPANY_WIDE with a branchUid → rejected by server. | J5: /admin/approvals/policies | K5: APPROVALS.POLICY.MANAGE | M5: Not Run
A6: PLAT-022 | B6: Approval Policies | C6: Create a multi-step policy; sequences are dense from 1 | D6: Positive | E6: High | F6: Logged in as ORG_ADMIN. At least 2 role codes exist. | G6: 1. New policy; add 2 steps (ACCOUNTANT, ORG_ADMIN). 2. Remove the middle step — remaining step resequences to dense 1. 3. Submit. | H6: step1 role: ACCOUNTANT, step2 role: ORG_ADMIN | I6: Policy created with steps in order (sequences dense from 1). Blank approverRoleCode on a step → 'Step N: approver role code is required'. Non-dense sequences are prevented by the UI's resequencing. | J6: /admin/approvals/policies | K6: APPROVALS.POLICY.MANAGE | M6: Not Run
A7: PLAT-023 | B7: Approval Policies | C7: Create an unbounded top-band policy (maxAmount null) | D7: Edge | E7: Medium | F7: Logged in as ORG_ADMIN. | G7: 1. New policy; set minAmount=1000000; leave maxAmount blank; submit. | H7: minAmount: 1000000, maxAmount: (blank) | I7: Policy created with maxAmount=null (top band). List shows '>= 1,000,000' or unbounded indicator. minAmount blank → required error. Negative minAmount → DecimalMin('0') rejection. | J7: /admin/approvals/policies | K7: APPROVALS.POLICY.MANAGE | M7: Not Run
A8: PLAT-024 | B8: Approval Policies | C8: Edit a policy (saves changes; in-flight PENDING requests are unaffected) | D8: Positive | E8: High | F8: Logged in as ORG_ADMIN. An ACTIVE policy with a PENDING in-flight request under it. | G8: 1. Open the policy detail by clicking a list row. 2. Change name and a step role; save. 3. Verify the previously-submitted PENDING request is unchanged. | H8: New name: PO <= 1M v2 | I8: PUT /api/v1/approvals/policies/uid/{uid} returns 200. In-flight request retains its original chain (BR-APR-05 — edits affect only future submissions). POLICY.VIEW-only user: save button hidden / 403 on PUT. | J8: /admin/approvals/policies/uid/:uid | K8: APPROVALS.POLICY.MANAGE | M8: Not Run
A9: PLAT-025 | B9: Approval Policies | C9: Deactivate a policy (ACTIVE → INACTIVE); re-deactivating an inactive policy blocked | D9: Positive | E9: High | F9: Logged in as ORG_ADMIN. An ACTIVE policy exists. | G9: 1. On policy detail, click Deactivate. 2. Assert status flips to INACTIVE and Deactivate control is now hidden. 3. Verify the control does not appear when already INACTIVE. | H9: Policy: PO <= 1M v2 (ACTIVE) | I9: POST /api/v1/approvals/policies/uid/{uid}/deactivate returns 200 with status=INACTIVE. Control is hidden for INACTIVE policies (UI guards illegal transition). User without MANAGE → 403. | J9: /admin/approvals/policies/uid/:uid | K9: APPROVALS.POLICY.MANAGE | M9: Not Run
A10: PLAT-026 | B10: Approval Requests | C10: Approval inbox shows PENDING requests the caller can decide (APPROVALS.DECIDE) | D10: Positive | E10: High | F10: ACCOUNTANT logged in (the approver role for the seeded policy step). A PENDING request exists whose current open step routes to ACCOUNTANT. | G10: 1. Navigate to /admin/approvals/inbox. 2. Read rows: requestNumber, documentType, amount, status badge. | H10: PENDING request routed to ACCOUNTANT | I10: GET /api/v1/approvals/requests/inbox returns 200 + meta. Only requests where caller can decide the current open step appear. NO-DECIDE user → forbidden. Status badge shows PENDING. | J10: /admin/approvals/inbox | K10: APPROVALS.DECIDE | M10: Not Run
A11: PLAT-027 | B11: Approval Requests | C11: All-requests list + filter by status (APPROVALS.REQUEST.VIEW) | D11: Positive | E11: High | F11: ORG_ADMIN logged in. Requests across multiple statuses exist. | G11: 1. Navigate to /admin/approvals/requests. 2. Filter status=PENDING → only PENDING. Then APPROVED. Then REJECTED. Clear → all. | H11: Mixed-status requests | I11: Server filter status=... returns correct subset. Page resets to 0 on filter change. Status badge per row. Company-scoped (only active company's requests). | J11: /admin/approvals/requests | K11: APPROVALS.REQUEST.VIEW | M11: Not Run
A12: PLAT-028 | B12: Approval Requests | C12: Request detail shows the step chain and current open step | D12: Positive | E12: High | F12: ORG_ADMIN logged in. A multi-step PENDING request exists. | G12: 1. Open the request detail from the list row. 2. Read header (requestNumber, documentType, amount, currency, status, submittedBy/At) and steps table. | H12: Multi-step PENDING request | I12: GET /api/v1/approvals/requests/uid/{uid} returns ApprovalRequestDto incl. steps[]. Current open step = lowest-sequence PENDING. uid in URL only — never as visible text. Amount and dates formatted. Cross-tenant request uid → forbidden. | J12: /admin/approvals/requests/uid/:uid | K12: APPROVALS.REQUEST.VIEW | M12: Not Run
A13: PLAT-029 | B13: Approval Requests | C13: Approve the current open step; single-step → APPROVED; multi-step stays PENDING, advances | D13: Positive | E13: High | F13: ACCOUNTANT logged in (current-step approver). A PENDING request on a step routed to ACCOUNTANT. | G13: 1. On request detail, click Approve; add a comment; submit. 2. For single-step: assert status → APPROVED. 3. For multi-step: assert this step → APPROVED; request still PENDING with next step open. | H13: comment: Looks good | I13: POST /api/v1/approvals/requests/uid/{uid}/approve returns updated ApprovalRequestDto. Correct status per variation. Only the current-step approver may decide (BR-APR-04). Non-approver with APPROVALS.DECIDE but wrong role → service routing denial. | J13: /admin/approvals/requests/uid/:uid | K13: APPROVALS.DECIDE | M13: Not Run
A14: PLAT-030 | B14: Approval Requests | C14: Reject the current open step; entire chain killed (later steps → SKIPPED) | D14: Positive | E14: High | F14: ACCOUNTANT logged in. A multi-step PENDING request on step 1. | G14: 1. On request detail, click Reject; add comment; submit. 2. Check status of the request and all steps. | H14: comment: Budget exceeded; multi-step request | I14: POST /api/v1/approvals/requests/uid/{uid}/reject returns status=REJECTED. Step 1 → REJECTED. Remaining steps → SKIPPED. This is terminal — Approve/Reject/Recall controls are hidden. Any further forced API call rejected (BR-APR-07). | J14: /admin/approvals/requests/uid/:uid | K14: APPROVALS.DECIDE | M14: Not Run
... A19: PLAT-035 | B19: Approval Requests | C19: Branch-specificity: BRANCH policy beats COMPANY_WIDE when both match | D19: Edge | E19: Medium | F19: ORG_ADMIN logged in. One COMPANY_WIDE and one BRANCH policy for the same documentType/band; the BRANCH policy targets the non-default branch. | G19: 1. Trigger a gated action in the BRANCH-policy's branch within the overlapping band. 2. Open the resulting request; read sourcePolicy. | H19: Overlapping policies; action in the branch-specific branch | I19: sourcePolicy on the request is the BRANCH-scoped policy (branch-specificity wins on a tie, ADR-0022). An action in a different branch (only COMPANY_WIDE matches) uses the COMPANY_WIDE policy. | J19: /admin/approvals/requests | K19: APPROVALS.REQUEST.VIEW | M19: Not Run

Sheet Platform – Audit
A1: Platform – Audit — UAT
A2: ID | B2: Area | C2: Test Scenario | D2: Type | E2: Priority | F2: Preconditions | G2: Steps | H2: Test Data | I2: Expected Result | J2: Route | K2: Permission | L2: Actual Result | M2: Status | N2: Severity | O2: Tester | P2: Run Date | Q2: Comments
A3: PLAT-036 | B3: Audit Trail | C3: Audit trail lists newest-first, read-only, paginated (AUDIT.VIEW) | D3: Positive | E3: High | F3: Logged in as ORG_ADMIN (holds AUDIT.VIEW). Audit rows exist (any login or master action generates them). | G3: 1. Navigate to /admin/audit. 2. Read columns: actor username, action, target type, company/branch, time, IP. 3. Confirm there are NO create/edit/delete controls anywhere on the page. | H3: Any active company with audit history | I3: GET /api/v1/audit returns 200 + meta (sorted DESC by time). Rows show actorUsername (not internal id). No write affordance — append-only trail. Paginator present (default page size 50). NO-PERMISSION: nav hidden + forbidden. Page size capped at 200 server-side. | J3: /admin/audit | K3: AUDIT.VIEW | M3: Not Run
A4: PLAT-037 | B4: Audit Trail | C4: Filter audit by actor (chosen via user picker by name) | D4: Positive | E4: High | F4: Logged in as ORG_ADMIN. Actions by at least 2 distinct users exist. | G4: 1. Open the actor filter; select a user BY display name or username from the picker. 2. Apply → only that actor's rows; request carries actorUid=<picked>. 3. Clear filters → full list. | H4: Actor: ORG_ADMIN user | I4: Filtered to chosen actor. The actor uid resolved server-side — never typed by the user. Page resets to 0. Unknown actor uid resolves to no match → empty state. | J4: /admin/audit | K4: AUDIT.VIEW | M4: Not Run
A5: PLAT-038 | B5: Audit Trail | C5: Filter audit by action code, targetType, and date range | D5: Positive | E5: High | F5: Logged in as ORG_ADMIN. Known audit actions exist. | G5: 1. Set action filter to USER.CREATE. 2. Set from date and to date. 3. Apply → only matching rows. 4. Combine with targetType filter. | H5: action: USER.CREATE, from: 2026-06-01, to: 2026-06-30 | I5: Combined AND filter applied. Dates sent as ISO-8601 instants (Z). Blank filters dropped (not sent as null binds). from > to → empty result (not error). Page resets on each filter change. | J5: /admin/audit | K5: AUDIT.VIEW | M5: Not Run
A6: PLAT-039 | B6: Audit Trail | C6: Audit is confined to the caller's active company; rootadmin reads org-wide | D6: Positive | E6: High | F6: Two companies A and B with distinct audit rows. Non-root ORG_ADMIN of Company A. rootadmin. | G6: 1. Log in as Company A's non-root ORG_ADMIN → open /admin/audit; read rows. 2. Log out; log in as rootadmin → open /admin/audit. | H6: Company A and B audit rows | I6: Non-root: only Company A's rows returned (AuditReadService scopes to active company). rootadmin: rows across all companies. Company A admin cannot see Company B rows even by setting a Company B targetUid filter. | J6: /admin/audit | K6: AUDIT.VIEW | M6: Not Run
A7: PLAT-040 | B7: Audit Trail | C7: Audit captures platform-domain actions (approvals create/decide/recall, notification type toggle) | D7: Positive | E7: Low | F7: ORG_ADMIN with AUDIT.VIEW. Perform: create a policy, decide a step, recall a request, toggle a notification type. | G7: 1. Create an approval policy. 2. Decide (approve) an approval step. 3. Recall an approval request. 4. Toggle a notification type state. 5. Filter audit by each action code. | H7: Actions: APPROVAL.POLICY.CREATE, APPROVAL.STEP.DECIDE, APPROVAL.REQUEST.RECALL, NOTIFICATION.TYPE.TOGGLE | I7: Each action produces an audit row with the correct action code, actor username, target uid, and timestamp. Read-only views (opening a list) do NOT generate audit rows. | J7: /admin/audit | K7: AUDIT.VIEW | M7: Not Run
A8: PLAT-041 | B8: Audit Trail | C8: Audit pagination: page size cap enforced; FIRST/PREV/numbers/NEXT/LAST controls function | D8: Positive | E8: Medium | F8: Logged in as ORG_ADMIN. More than 50 audit rows exist (to span at least 2 pages at default size 50). | G8: 1. Load page 0 (default size 50); click NEXT → page 1. 2. Click LAST; click FIRST; click a numbered page; click PREV. 3. Attempt to request size=300 via URL param. | H8: >50 audit rows | I8: Correct page slices on each navigation. meta.hasNext drives NEXT button state. Server clamps size to 200 (MAX_PAGE_SIZE) when >200 is requested; size <1 clamps to 1. Paginator self-hides when only one page. | J8: /admin/audit | K8: AUDIT.VIEW | M8: Not Run

Sheet Conventions
A1: Conventions — UAT
A2: ID | B2: Area | C2: Test Scenario | D2: Type | E2: Priority | F2: Preconditions | G2: Steps | H2: Test Data | I2: Expected Result | J2: Route | K2: Permission | L2: Actual Result | M2: Status | N2: Severity | O2: Tester | P2: Run Date | Q2: Comments
A3: CONV-001 | B3: C1 – uid never shown | C3: No raw uid is visible on a master list (customers) | D3: Positive | E3: High | F3: Logged in as ORG_ADMIN. At least 3 customers exist. | G3: 1. Navigate to /admin/customers. 2. Read all visible cell text and all visible labels and action link texts. | H3: Customers: Acme Distributors Ltd (BUSINESS), Jane Walk-in (INDIVIDUAL) | I3: Each row shows display name, type, kind, status badge. No uid string (26-char ULID) is visible in any table cell, label, or action link text. Action links may carry uid in the href path (allowed) but the visible link text must be human ('View Acme Distributors Ltd'), not the uid. | J3: /admin/customers | K3: CUSTOMER.VIEW | M3: Not Run
A4: CONV-002 | B4: C1 – uid never shown | C4: uid appears ONLY in the URL path on a detail screen, never in on-screen text | D4: Positive | E4: High | F4: Logged in as ORG_ADMIN. A confirmed sales order with at least 2 lines exists. | G4: 1. From the SO list, open a row → /admin/sales-orders/uid/<uid>. 2. Capture the page URL. 3. Read all visible detail text: header, customer, lines, totals. | H4: SO number: SO-2026-0007, customer: Acme Distributors Ltd | I4: URL path contains /uid/<uid>. Screen body shows the SO number and customer name — no uid text. Numeric DB id appears nowhere (not in URL, not on screen). Customer is linked as name to /admin/customers/uid/<customerUid> — uid only in the href. | J4: /admin/sales-orders/uid/:uid | K4: SALES.ORDER.VIEW | M4: Not Run
A5: CONV-003 | B5: C1 – uid never shown | C5: Multi-FK form: every resource reference is an app-uid-picker chosen by name (POS sale form) | D5: Positive | E5: High | F5: Logged in as ORG_ADMIN (holds POS.SALE.CREATE). One OPEN POS session; at least 2 GOODS products; 1 customer; 1 agent. | G5: 1. Navigate to /admin/pos/sell. 2. For each of: Session, Customer, Agent — assert it is a <select> picker and choose by name. 3. Click 'Add Line'; for the line's Product and Unit, choose by name. | H5: session: Till-1 / 2026-06-14, customer: Jane Walk-in, agent: Internal Rep, product: Widget A, unit: EA | I5: All five references (session, customer, agent, product, unit) are chosen from pickers by human label. No free-text uid input exists for any of them. Submit with no session selected → client formError 'Session is required.', no API call. | J5: /admin/pos/sell | K5: POS.SALE.CREATE | M5: Not Run
A6: CONV-004 | B6: C1 – uid never shown | C6: Large option set in a picker shows the name-filter input box (never a uid box) | D6: Positive | E6: Medium | F6: Logged in as ORG_ADMIN. More than 12 GOODS products exist. | G6: 1. Open /admin/pos/sell; click Add Line. 2. Inspect the product picker region. 3. Type a partial name in the filter input. | H6: 13+ products; filter text: Wid | I6: A filter input with aria-label ending '— filter by name' and placeholder 'Type to filter by name…' appears above the <select>. Typing narrows the option list by label. The bound value remains a uid stored under the hood — the user types only a name fragment, never a uid. With <=12 products the filter box is absent. | J6: /admin/pos/sell | K6: POS.SALE.CREATE | M6: Not Run
A7: CONV-005 | B7: C2 – ApiResponse envelope | C7: Non-paginated GET is auto-unwrapped (component sees raw T, not the envelope) | D7: Positive | E7: High | F7: Logged in as ORG_ADMIN. One customer exists. | G7: 1. Open the customer detail; capture the raw HTTP response body for GET /api/v1/customers/uid/{uid}. 2. Confirm the wire body is { data: {...}, errors: [] }. 3. Confirm the screen rendered the customer fields. | H7: Customer: Acme Distributors Ltd | I7: Wire body = envelope with data + errors[]. Component receives the unwrapped data object — no 'data.' prefix leaks into the UI. The apiResponseInterceptor strips the envelope for non-paginated responses. | J7: /admin/customers/uid/:uid | K7: CUSTOMER.VIEW | M7: Not Run
A8: CONV-006 | B8: C2 – ApiResponse envelope | C8: Paginated GET preserves meta {page, size, totalElements, totalPages, hasNext} | D8: Positive | E8: High | F8: Logged in as ORG_ADMIN. More than 20 customers (default page size). | G8: 1. Open /admin/customers; capture the raw HTTP response body. 2. Confirm the body has a populated meta field. 3. Confirm the paginator renders using totalPages/hasNext. | H8: 25 customers, size 20 → page 0, totalPages 2, hasNext: true | I8: List request opts out of unwrap (SKIP_UNWRAP); component receives {rows, meta}. meta.totalPages=2, meta.hasNext=true. Paginator shows controls. Empty result: meta.totalElements=0, totalPages=0; paginator self-hides. | J8: /admin/customers | K8: CUSTOMER.VIEW | M8: Not Run
A9: CONV-007 | B9: C2 – ApiResponse envelope | C9: Error envelope: errors[0] surfaced as inline form error (role=alert) | D9: Negative | E9: High | F9: Logged in as ORG_ADMIN. | G9: 1. Open the customer create form; choose partyType BUSINESS; submit without a TIN (triggers a server rule). 2. Capture the response and the on-screen message. | H9: displayName: Bad Biz, partyType: BUSINESS, no TIN | I9: Response: envelope {data:null, errors:['...']}. Component's messageFrom(err) surfaces errors[0] in formError rendered as role='alert'. A 5xx with no errors[] → authErrorInterceptor pops the centered alert. A 403 does NOT pop the modal. | J9: /admin/customers | K9: CUSTOMER.MANAGE | M9: Not Run
A10: CONV-008 | B10: C3 – RBAC gating | C10: Nav hides items the user lacks permission for (by code, not role name) | D10: Positive | E10: High | F10: A CUSTOM-role user holding ONLY CUSTOMER.VIEW. | G10: 1. Log in as the custom-role user. 2. Read the rendered nav items. | H10: Custom role: CUSTOMER.VIEW only | I10: Only the Customers nav item is visible. POS / GL journals / sales-orders / Users / Roles nav items are absent. rootadmin sees ALL items (isRoot bypass) — positive smoke only. | J10: /admin | K10: CUSTOMER.VIEW | M10: Not Run
A11: CONV-009 | B11: C3 – RBAC gating | C11: Route guard redirects to /admin/home when permission absent — not a 403 page | D11: Negative | E11: High | F11: A user lacking POS.SALE.CREATE. | G11: 1. While logged in, navigate directly to /admin/pos/sell. | H11: User without POS.SALE.CREATE | I11: The guard returns createUrlTree(['/admin/home']) — the user lands on /admin/home, NOT on a 403 screen. No error modal appears. A user WITH the code reaches /admin/pos/sell normally. | J11: /admin/pos/sell | K11: POS.SALE.CREATE | M11: Not Run
A12: CONV-010 | B12: C3 – RBAC gating | C12: API returns 403 for a missing code; UI shows a calm state — no red modal | D12: Negative | E12: High | F12: A user with CUSTOMER.VIEW but NOT CUSTOMER.MANAGE. | G12: 1. Open /admin/customers (allowed by VIEW). Confirm the Create button/form is not rendered. 2. Force the POST /api/v1/customers (e.g. replay). | H12: User: CUSTOMER.VIEW only | I12: Create button not rendered (canManage computed false). Forced POST returns 403. authErrorInterceptor does NOT show the global red alert for 403 (line 101 of interceptor). Rejection propagates to the component handler (calm state). A 5xx on the same screen DOES pop the centered alert. | J12: /admin/customers | K12: CUSTOMER.VIEW | M12: Not Run
A13: CONV-011 | B13: C4 – Four screen states | C13: Loading state on a list shows spinner with aria-live before data arrives | D13: Positive | E13: High | F13: Logged in as ORG_ADMIN. | G13: 1. Intercept GET /api/v1/customers to add 1s latency. 2. Navigate to /admin/customers; assert the loading branch renders before data. | H13: 1s delayed response | I13: state='loading': spinner rendered with aria-live='polite'. The table is not yet shown. Distinct from the empty and error states. | J13: /admin/customers | K13: CUSTOMER.VIEW | M13: Not Run
A14: CONV-012 | B14: C4 – Four screen states | C14: Empty state (idle + 0 rows) is distinct from loading | D14: Positive | E14: High | F14: Logged in as ORG_ADMIN. A company with no customers (or a search with no matches). | G14: 1. Navigate to /admin/customers with a non-matching search term 'zzzz-no-match'. | H14: Search query: zzzz-no-match | I14: isEmpty() true → an explicit 'no customers' empty message, NOT the spinner and NOT an error. Paginator absent (totalPages <= 1). Distinct from the loading state. | J14: /admin/customers | K14: CUSTOMER.VIEW | M14: Not Run
... A23: CONV-021 | B23: C7 – Multi-tenancy | C23: Company isolation: Tenant A user cannot see Tenant B's customers | D23: Positive | E23: High | F23: Two companies A and B each with distinct customers. A user belonging to Company A only. | G23: 1. Log in as Company A user; open /admin/customers. 2. Read all rows. | H23: Company A customer: A-Customer; Company B customer: B-Customer | I23: Only A-Customer listed. B-Customer never appears. The company selector shows only Company A (hidden when single company). Forcing ?companyId=<B's id> → backend scope check denies (403 or empty). | J23: /admin/customers | K23: CUSTOMER.VIEW | M23: Not Run
A24: CONV-022 | B24: C7 – Multi-tenancy | C24: Branch switch changes X-Branch-Uid header and reloads branch-scoped data | D24: Positive | E24: High | F24: A user assigned to at least 2 branches. Branch-scoped data differs per branch. | G24: 1. Note the active branch name in the switcher. 2. Open the branch menu; pick another branch BY NAME. 3. Capture a subsequent API call's request headers. | H24: Branch HQ (default) and Mwanza Depot | I24: auth.switchBranch(branchUid) updates SessionStore.activeBranchUid. Subsequent requests carry X-Branch-Uid: <new branch uid> (authHeaderInterceptor). Branch-scoped lists reload. Branch selected by name — uid never shown or typed. | J24: /admin | M24: Not Run
A25: CONV-023 | B25: C7 – Multi-tenancy | C25: Acting in an unassigned branch via forged X-Branch-Uid is denied | D25: Negative | E25: High | F25: User assigned to branch HQ only. Branch Mwanza exists but user is NOT assigned. | G25: 1. Issue an API call with X-Branch-Uid: <Mwanza uid> while logged in as the HQ-only user. | H25: Mwanza branch uid | I25: Backend rejects the request (403 / scope error). The user cannot act in a branch they are not assigned to. The shell switcher never offers Mwanza to this user so the UI cannot reach this state normally. | M25: Not Run
A26: CONV-024 | B26: C8 – Money/date formatting | C26: Money rendered as 2-decimal amount paired with currency code; date rendered as ISO yyyy-MM-dd | D26: Positive | E26: High | F26: Logged in as ORG_ADMIN. An AR invoice with a non-trivial total (e.g. 1234.5) exists. A POS receipt exists. | G26: 1. Open the AR invoices list; read the rendered amount strings. 2. Open a POS sale receipt; read the total. 3. Open a journal detail; read the posting date. | H26: Total: 1234.5 in TZS; posting date: 2026-06-14 | I26: Amount renders with exactly 2 decimals paired with currency code. Wire value is a string (no floating-point artifacts). POS uses number:'1.2-2' → groups (TZS 1,234.50). AR uses fmtMoney → toFixed(2) → does NOT group (1234.50 TZS). Null amount renders 0.00, never NaN. Date displays as ISO 2026-06-14. | J26: /admin/ar/invoices | K26: AR.VIEW | M26: Not Run
A27: CONV-025 | B27: C9 – Soft-delete / append-only | C27: Customer archive sets a status (ARCHIVED), not a hard delete; row remains retrievable | D27: Positive | E27: High | F27: Logged in as ORG_ADMIN (holds CUSTOMER.MANAGE). One ACTIVE customer. | G27: 1. Archive the customer from its detail screen. 2. Re-fetch the customer by uid. | H27: Customer: Old Client (ACTIVE) | I27: PUT /api/v1/customers/uid/{uid}/archive returns 204. Customer still exists on GET /api/v1/customers/uid/{uid} with status=ARCHIVED (muted badge). Not removed from the database. CUSTOMER.VIEW-only: archive button hidden + forced PUT 403. | J27: /admin/customers/uid/:uid | K27: CUSTOMER.MANAGE | M27: Not Run
A28: CONV-026 | B28: C9 – Soft-delete / append-only | C28: Archived customer can be restored (reversible soft-delete) | D28: Positive | E28: High | F28: Logged in as ORG_ADMIN. An ARCHIVED customer (from CONV-025). | G28: 1. Restore the customer from its detail screen. 2. Re-fetch the customer. | H28: Customer: Old Client (ARCHIVED) | I28: PUT /api/v1/customers/uid/{uid}/restore returns 204. Status flips back to ACTIVE. Proves soft-delete is reversible. Restoring an already-ACTIVE customer is idempotent or returns a benign 4xx surfaced in errors[0]. | J28: /admin/customers/uid/:uid | K28: CUSTOMER.MANAGE | M28: Not Run
A29: CONV-027 | B29: C9 – Soft-delete / append-only | C29: GL account 'delete' is a deactivate (soft-delete) — not removal | D29: Positive | E29: High | F29: Logged in as ORG_ADMIN (holds GL.MANAGE). One unused ACTIVE GL account. | G29: 1. Trigger the account 'delete' action. 2. Re-fetch the account by uid. 3. Open the journal line account picker and confirm the account is excluded. | H29: Account: 9999 — Suspense | I29: DELETE /api/v1/gl/accounts/uid/{uid} calls service.deactivate (returns 204). Account still exists on GET with status=INACTIVE. Not removed. Account is excluded from the journal line picker (inactive filtered out). Existing postings unaffected. | J29: /admin/gl/accounts | K29: GL.MANAGE | M29: Not Run
A30: CONV-028 | B30: C9 – Soft-delete / append-only | C30: Journal is corrected by a reversal entry (append-only); no edit/delete of a posted entry | D30: Positive | E30: High | F30: Logged in as ORG_ADMIN (holds GL.POST). One posted JournalEntry. | G30: 1. Open the posted journal detail. 2. Confirm there is NO edit or delete affordance — only a Reverse action. 3. Reverse the entry (with a reversal date). 4. Check the original entry and the new reversing entry. | H30: Original journal: JE-2026-0011; reversalDate: 2026-06-14 | I30: POST /api/v1/gl/journals/uid/{uid}/reverse returns 201 with a new JournalEntryDto (debits/credits swapped). Original entry is unchanged and still present. No PUT/DELETE for posted journals. GL.VIEW-only user: reverse returns 403. Reversing an already-reversed entry → server rule rejects (errors[0]). | J30: /admin/gl/journals | K30: GL.POST | M30: Not Run
A31: CONV-029 | B31: C9 – Soft-delete / append-only | C31: Archived master is hidden from active pickers but visible in an archive filter on the master list | D31: Positive | E31: Medium | F31: Logged in as ORG_ADMIN. One ARCHIVED customer and several ACTIVE customers. | G31: 1. Open a transaction screen that picks a customer (e.g. POS sale); check if the ARCHIVED customer appears. 2. Open /admin/customers; search or apply status filter; locate the archived customer. | H31: Archived customer: Old Client | I31: The archived customer does NOT appear in transaction pickers (excluded from active use). It DOES appear in the master list with an ARCHIVED status badge (discoverable for audit). Demonstrates soft-delete preserves history while removing from active use. | J31: /admin/customers | K31: CUSTOMER.VIEW | M31: Not Run
A32: CONV-030 | B32: C1-C9 IAM screens sweep | C32: No raw uid displayed across all IAM screens (companies, branches, users, roles, role-grants) | D32: Positive | E32: High | F32: Logged in as ORG_ADMIN. | G32: 1. Visit each IAM screen in order: /admin/companies, /admin/companies/:companyUid/branches, /admin/users, /admin/users/uid/:uid, /admin/roles, /admin/roles/uid/:uid, /admin/role-grants. 2. On each screen scan all visible text and inputs for uid strings. | H32: All IAM screens | I32: uids appear ONLY in URL path segments (/uid/<uid>). Every cross-resource reference is selected via a NAME-bearing select or picker. No <input> accepts a raw uid. Tables/labels show codes/names, never uids. The grant/branch panels show a picker placeholder ('— select —') by name. | J32: /admin/companies | K32: COMPANY.VIEW | M32: Not Run
A33: CONV-031 | B33: C6 – Accessibility – IAM screens | C33: Axe scan clean across all IAM routes | D33: Positive | E33: Medium | F33: Logged in as ORG_ADMIN. | G33: 1. Load each route and run an axe scan: /login, /admin/companies, /admin/companies/:companyUid/branches, /admin/users, /admin/users/uid/:uid, /admin/roles, /admin/roles/uid/:uid, /admin/role-grants. 2. Tab through forms on each screen. | H33: All IAM routes | I33: Zero WCAG 2.1 AA serious/critical violations on each screen. All inputs/selects have labels or aria-labels. Tables have captions and scope='col' headers. Branch and user menus are keyboard-operable. axe passes on the /login page. | J33: /login | M33: Not Run

Sheet Masters – Parties
A1: Masters – Parties — UAT
A2: ID | B2: Area | C2: Test Scenario | D2: Type | E2: Priority | F2: Preconditions | G2: Steps | H2: Test Data | I2: Expected Result | J2: Route | K2: Permission | L2: Actual Result | M2: Status | N2: Severity | O2: Tester | P2: Run Date | Q2: Comments
A3: CUST-001 | B3: Customers | C3: Customer list loads scoped to active company | D3: Positive | E3: High | F3: Logged in as ORG_ADMIN. Company A has at least 3 active customers (mix of CASH_WALK_IN and CREDIT_ACCOUNT). | G3: 1. Navigate to /admin/customers. 2. Wait for the table to render. 3. Verify rows show code (CUST-####), display name, party type, customer kind, and status badge. 4. Confirm the company selector defaults to the active company. 5. Confirm no raw uid is visible in any table cell. | H3: Customers: 'Acme Traders' (BUSINESS/CREDIT_ACCOUNT), 'Jane Walk-in' (INDIVIDUAL/CASH_WALK_IN), 'Mega Distributors' (BUSINESS/CREDIT_ACCOUNT). | I3: Table lists only Company A customers. HTTP 200. ApiResponse envelope with data[] and meta. No uid visible in cells. Status badge text readable. | J3: /admin/customers | GET /api/v1/customers?companyId=&q=&page=&size= | K3: CUSTOMER.VIEW | M3: Not Run
A4: CUST-002 | B4: Customers | C4: Customer list empty state | D4: Edge | E4: Medium | F4: A company with zero customers exists. Logged in as ORG_ADMIN. | G4: 1. Navigate to /admin/customers. 2. Switch the company selector to the empty company. 3. Observe the rendered state. | H4: Company with 0 customers. | I4: Distinct empty-state message rendered (not a spinner, not an error). No table rows. Paginator hidden. Create button still reachable for MANAGE-role users. | J4: /admin/customers | GET /api/v1/customers | K4: CUSTOMER.VIEW | M4: Not Run
A5: CUST-003 | B5: Customers | C5: Customer list forbidden for user without CUSTOMER.VIEW | D5: Permission | E5: High | F5: A user with zero permissions is available. | G5: 1. Log in as the NO-PERMISSION user. 2. Confirm 'Customers' nav item is absent from the shell. 3. Navigate directly to /admin/customers. 4. Observe the screen state. 5. Call GET /api/v1/customers directly. | H5: NO-PERMISSION user account. | I5: Nav item hidden. Route guard blocks direct navigation – forbidden screen shown. Direct API call returns HTTP 403 with ApiResponse errors[]. | J5: /admin/customers | GET /api/v1/customers | K5: CUSTOMER.VIEW | M5: Not Run
A6: CUST-004 | B6: Customers | C6: Customer search by name (substring) and by TIN/phone/code (exact) | D6: Positive | E6: High | F6: Company A has customers with known name 'Acme Traders', TIN 123456789, phone 0712000111, code CUST-0007. Logged in as ORG_ADMIN. | G6: 1. Navigate to /admin/customers. 2. Type 'Acme' in the search box; wait 300 ms debounce; assert only matching rows appear. 3. Clear; type exact TIN '123456789'; assert the matching customer appears. 4. Clear; type exact phone '0712000111'; assert match. 5. Clear; type exact code 'CUST-0007'; assert match. 6. Clear search; assert full list returns at page 0. | H6: Customers as described in preconditions. | I6: Name search is case-insensitive substring. TIN/phone/code are exact-match only. Partial TIN returns no match. Blank query returns unfiltered list. Page resets to 0 on each new query. | J6: /admin/customers | GET /api/v1/customers?q= | K6: CUSTOMER.VIEW | M6: Not Run
A7: CUST-005 | B7: Customers | C7: Create INDIVIDUAL + CASH_WALK_IN customer (happy path) | D7: Positive | E7: High | F7: Logged in as ORG_ADMIN. Active company selected. | G7: 1. Navigate to /admin/customers; click 'New Customer'. 2. Enter display name 'Jane Walk-in', party type = Individual, kind = Cash/Walk-in. 3. Submit. 4. Verify new row appears with server-assigned code (CUST-#### prefix). | H7: displayName='Jane Walk-in', partyType=INDIVIDUAL, customerKind=CASH_WALK_IN. | I7: HTTP 201. Success alert. New row appears with CUST-#### code. status=ACTIVE. No credit-limit or payment-terms fields sent. No uid visible in any label or cell. | J7: /admin/customers | POST /api/v1/customers | K7: CUSTOMER.MANAGE | M7: Not Run
A8: CUST-006 | B8: Customers | C8: Create BUSINESS + CREDIT_ACCOUNT customer with credit limit and payment terms | D8: Positive | E8: High | F8: Logged in as ORG_ADMIN. Active company selected. | G8: 1. Open create form: displayName='Mega Distributors', party type=Business, TIN=100200300, vatRegistered=yes, VRN='40-123456-X', kind=Credit Account. Submit. 2. Open the created customer at /admin/customers/uid/:uid. 3. Set creditLimit amount=5000000, currency=TZS, paymentTermsDays=30. Save. | H8: creditLimit={amount:'5000000',currency:'TZS'}, paymentTermsDays=30. | I8: Create returns 201. Edit returns 200. Credit limit stored as MoneyDto. Detail shows 'TZS 5,000,000.00'. paymentTermsDays=30 persisted. | J8: /admin/customers | POST /api/v1/customers | PUT /api/v1/customers/uid/{uid} | K8: CUSTOMER.MANAGE | M8: Not Run
A9: CUST-007 | B9: Customers | C9: Reject BUSINESS customer without TIN (BR-PARTY-04) | D9: Negative | E9: High | F9: Logged in as ORG_ADMIN. | G9: 1. Open create form; party type=Business; leave TIN blank; displayName='No-TIN Ltd'. 2. Submit. 3. If UI is bypassed, call POST /api/v1/customers with partyType=BUSINESS, tin=null. | H9: partyType=BUSINESS, tin=null. | I9: UI blocks with 'A business party must have a TIN'. API returns HTTP 400 with BR-PARTY-04 message in errors[]. Whitespace-only TIN also rejected. | J9: POST /api/v1/customers | K9: CUSTOMER.MANAGE | M9: Not Run
A10: CUST-008 | B10: Customers | C10: Reject VRN when vatRegistered=false (BR-PARTY-06) | D10: Negative | E10: Medium | F10: Logged in as ORG_ADMIN. | G10: 1. POST /api/v1/customers with vatRegistered=false, vrn='40-9999'. 2. In the UI, verify unchecking VAT clears the VRN field and prevents submission with a VRN. | H10: vatRegistered=false, vrn='40-9999'. | I10: HTTP 400. Message 'VRN may only be set when the customer is VAT-registered (BR-PARTY-06)'. UI prevents this combination by clearing VRN when VAT is unchecked. | J10: POST /api/v1/customers | K10: CUSTOMER.MANAGE | M10: Not Run
A11: CUST-009 | B11: Customers | C11: Credit fields hidden for CASH_WALK_IN, shown for CREDIT_ACCOUNT | D11: Positive | E11: High | F11: An existing CASH_WALK_IN customer. Logged in as ORG_ADMIN. | G11: 1. Open /admin/customers/uid/:uid for a CASH_WALK_IN customer. 2. Confirm Credit Limit and Payment Terms fields are NOT shown. 3. Change kind to Credit Account; confirm fields appear. 4. Change back to Cash/Walk-in; confirm fields hide. | H11: Existing CASH_WALK_IN customer. | I11: Fields are conditionally shown based on customerKind. Switching to cash clears credit data on save. No half-credit-pair sent. | J11: /admin/customers/uid/:uid | PUT /api/v1/customers/uid/{uid} | K11: CUSTOMER.MANAGE | M11: Not Run
A12: CUST-010 | B12: Customers | C12: VIEW-only role: no create/edit/archive affordances | D12: Permission | E12: High | F12: A custom role user with CUSTOMER.VIEW only (no CUSTOMER.MANAGE). | G12: 1. Log in as view-only user. 2. Navigate to /admin/customers: list renders but 'New Customer' button is hidden. 3. Open a detail: Save and Archive controls are hidden. 4. Attempt POST /api/v1/customers directly. 5. Attempt PUT /api/v1/customers/uid/{uid}/archive directly. | H12: Custom role: CUSTOMER.VIEW only. | I12: List and detail readable. All mutation buttons hidden (canManage=false). Direct POST and archive PUT return HTTP 403. | J12: /admin/customers | /admin/customers/uid/:uid | POST /api/v1/customers | PUT /api/v1/customers/uid/{uid}/archive | K12: CUSTOMER.VIEW (denied CUSTOMER.MANAGE) | M12: Not Run
A13: CUST-011 | B13: Customers | C13: Archive then restore a customer (ACTIVE → ARCHIVED → ACTIVE) | D13: Positive | E13: High | F13: An ACTIVE customer. Logged in as ORG_ADMIN. | G13: 1. Open an ACTIVE customer; click Archive. 2. Verify status badge shows ARCHIVED. HTTP 204. 3. Click Restore. 4. Verify status badge shows ACTIVE. HTTP 204. | H13: Any existing ACTIVE customer. | I13: HTTP 204 each. Soft-delete (status flip, record retained). Audit events CUSTOMER_ARCHIVE and CUSTOMER_RESTORE recorded. Re-archiving an already-ARCHIVED customer is idempotent. | J13: PUT /api/v1/customers/uid/{uid}/archive | PUT /api/v1/customers/uid/{uid}/restore | K13: CUSTOMER.MANAGE | M13: Not Run
A14: CUST-012 | B14: Customers | C14: Assign customer to branch (same company); duplicate rejected; cross-company denied | D14: Positive | E14: High | F14: Customer in Company A. Company A has at least 2 branches. Logged in as ORG_ADMIN. | G14: 1. Open customer detail; Branch Associations panel. 2. Select company by name, then select branch by 'code — name'; click Assign. HTTP 201. 3. Assign the same branch again. Expect 409. 4. Via API, POST with a Company-B branch uid. Expect 403. | H14: Branch 'BR-02 — Mwanza'. Company-B branch uid for negative test. | I14: Step 2: HTTP 201; association row shows 'code — name'. Step 3: HTTP 409 'already associated'. Step 4: HTTP 403 (BR-PARTY-01). Branch uid is never typed by the user — selected from dropdown. | J14: POST /api/v1/customers/uid/{uid}/branches | DELETE /api/v1/customers/uid/{uid}/branches/{branchUid} | K14: PARTY.BRANCH.ASSIGN | M14: Not Run
... A26: OPTY-002 | B26: Other Parties | C26: Other party MANAGE vs VIEW-only; cross-company isolation | D26: Permission | E26: Medium | F26: Company A with 2 other parties. Company B with 1 other party. VIEW-only user in Company A. | G26: 1. VIEW-only user: list loads; no create/archive buttons; direct PUT returns 403. 2. ORG_ADMIN listing Company B: Company A parties not shown. 3. GET /api/v1/other-parties/uid/{B-uid} as Company A user — expect 403. | H26: Company A and B other-party data. | I26: VIEW-only: reads OK, writes 403. Cross-tenant GET returns 403. Company A list never includes Company B rows. | J26: /admin/other-parties | GET/POST/PUT /api/v1/other-parties | K26: OTHERPARTY.VIEW | OTHERPARTY.MANAGE | M26: Not Run

Sheet Masters – Catalog
A1: Masters – Catalog — UAT
A2: ID | B2: Area | C2: Test Scenario | D2: Type | E2: Priority | F2: Preconditions | G2: Steps | H2: Test Data | I2: Expected Result | J2: Route | K2: Permission | L2: Actual Result | M2: Status | N2: Severity | O2: Tester | P2: Run Date | Q2: Comments
A3: PROD-001 | B3: Products | C3: Create GOODS product with auto-assigned code | D3: Positive | E3: High | F3: Active company with at least 1 ACTIVE UoM (e.g. EA — Each). Logged in as ORG_ADMIN. | G3: 1. Navigate to /admin/products; click 'New product'. 2. Leave Code blank; Name='Sugar 1kg'; Type=GOODS; Stockable=checked; Sellable=checked. 3. Select Base Unit 'EA — Each' from the unit dropdown by name. 4. Cost=1000 TZS; VAT Status=STANDARD. Submit. | H3: name='Sugar 1kg', baseUnit='EA', cost=TZS 1000, vatStatus=STANDARD. | I3: HTTP 201. New row with system code PROD-####. stockable=true. type=GOODS. status=ACTIVE. Base unit chosen by name — uid not typed. | J3: /admin/products | POST /api/v1/products | K3: PRODUCT.MANAGE | M3: Not Run
A4: PROD-002 | B4: Products | C4: Create SERVICE product forces stockable=false (BR-PROD-01) | D4: Positive | E4: High | F4: Active company with at least 1 ACTIVE UoM. Logged in as ORG_ADMIN. | G4: 1. Open product create form. 2. Set Type=SERVICE. 3. Observe Stockable checkbox becomes disabled and unchecked. 4. Fill name='Delivery Service', base unit='EA'. Submit. | H4: name='Delivery Service', type=SERVICE. | I4: HTTP 201. type=SERVICE, stockable=false. UI never permits stockable SERVICE. Attempting POST with type=SERVICE, stockable=true directly returns a DB CHECK error. | J4: POST /api/v1/products | K4: PRODUCT.MANAGE | M4: Not Run
A5: PROD-003 | B5: Products | C5: Duplicate product code per company rejected | D5: Negative | E5: Medium | F5: Product with code 'SKU-001' already exists in Company A. Logged in as ORG_ADMIN. | G5: 1. Create a second product with code='SKU-001' in the same company. Submit. | H5: code='SKU-001' (duplicate). | I5: HTTP 409/constraint error. Duplicate code rejected (uq_product_company_code). Same code in a different company is allowed. | J5: POST /api/v1/products | K5: PRODUCT.MANAGE | M5: Not Run
A6: PROD-004 | B6: Products | C6: Archive and restore a product (ACTIVE → ARCHIVED → ACTIVE) | D6: Positive | E6: High | F6: An ACTIVE product. Logged in as ORG_ADMIN. | G6: 1. Open product detail; click Archive. Verify status=ARCHIVED (HTTP 204). 2. Click Restore. Verify status=ACTIVE (HTTP 204). 3. Confirm archived products are excluded from component/base-unit pickers. | H6: Any ACTIVE product. | I6: HTTP 204 each. Soft-delete preserved. ARCHIVED products not selectable in recipe-component or BOM pickers (BR-PROD-05). | J6: PUT /api/v1/products/uid/{uid}/archive | PUT /api/v1/products/uid/{uid}/restore | K6: PRODUCT.MANAGE | M6: Not Run
A7: PROD-005 | B7: Products | C7: Add bulk pack with conversion factor; reject factor <= 0 | D7: Positive | E7: High | F7: Product with base unit EA. An ACTIVE UoM 'CTN' in the same company. Logged in as ORG_ADMIN. | G7: 1. Open product detail; Bulk Packs panel. 2. Select unit 'CTN — Carton' by name; enter factor=24; Add. 3. Attempt Add with factor=0; expect validation error. | H7: unit=CTN, factorToBase=24. Negative test: factor=0. | I7: Step 2: HTTP 201; row shows unit+factor. Step 3: 'factorToBase must be greater than zero (BR-PROD-03)' — no call made. API rejects factor<=0 via @DecimalMin 0.000001. | J7: POST /api/v1/products/uid/{uid}/bulk-packs | DELETE /api/v1/products/uid/{uid}/bulk-packs/{bulkPackUid} | K7: PRODUCT.MANAGE | M7: Not Run
A8: PROD-006 | B8: Products | C8: Line unit must be product's base or a configured bulk-pack unit (UoM restriction) | D8: Negative | E8: High | F8: Product 'Widget' has base unit EA and one bulk pack CTN (factor 24). Logged in as ORG_ADMIN. | G8: 1. Attempt to add a sales order line for 'Widget' with a unit that is neither EA nor CTN (e.g. KG). 2. Observe backend/UI rejection. | H8: Product with base EA and bulk pack CTN. Attempted line unit=KG. | I8: Line unit not in the product's configured units is rejected. Only EA (base) and CTN (configured pack) are selectable/valid for this product's lines. | J8: POST /api/v1/sales-orders/uid/{uid}/lines | POST /api/v1/quotations/uid/{uid}/lines | K8: SALES.ORDER.CREATE | M8: Not Run
A9: PROD-007 | B9: Products | C9: Set product price on a price list; remove price | D9: Positive | E9: High | F9: Product exists. An ACTIVE price list 'RETAIL' in the same company. Logged in as ORG_ADMIN. | G9: 1. Open product detail; Prices panel. 2. Select price list 'RETAIL — Retail' by name; enter amount=1500, currency=TZS; Set price (HTTP 201). 3. Click Remove on the price row (HTTP 204). | H9: priceList=RETAIL, amount=1500, currency=TZS. | I9: Step 2: HTTP 201; price row shows list name + formatted money. Step 3: HTTP 204; row removed. Price list chosen by code/name — uid stored under the hood. | J9: POST /api/v1/products/uid/{uid}/prices | DELETE /api/v1/products/uid/{uid}/prices/{priceListUid} | K9: PRODUCT.MANAGE | M9: Not Run
A10: PROD-008 | B10: Products | C10: POS barcode lookup resolves to product (company-scoped); cross-tenant barcode not found | D10: Positive | E10: High | F10: Product in Company A has barcode '6001234567890'. Company B has different products. Logged in as ORG_ADMIN of Company A. | G10: 1. On /admin/products, type barcode '6001234567890' in the scan box; trigger lookup. 2. Try a Company-B barcode value. | H10: Barcode '6001234567890' (Company A). A Company-B barcode value. | I10: Step 1: resolves to Company A product (name/code shown). Step 2: 404 not found — no cross-tenant leak. | J10: GET /api/v1/products/barcode-lookup?companyId=&barcode= | K10: PRODUCT.VIEW | M10: Not Run
A11: PROD-009 | B11: Products | C11: Product create blocked for VIEW-only role | D11: Permission | E11: High | F11: Custom role with PRODUCT.VIEW only. Logged in as that user. | G11: 1. Navigate to /admin/products; confirm 'New product' button is hidden. 2. Attempt POST /api/v1/products directly. | H11: Custom role: PRODUCT.VIEW only. | I11: Create button hidden (canManage=false). Direct POST returns HTTP 403. | J11: POST /api/v1/products | K11: PRODUCT.VIEW (denied PRODUCT.MANAGE) | M11: Not Run
A12: UOM-001 | B12: Units of Measure | C12: Create UoM; duplicate code per company rejected; archived UoM excluded from pickers | D12: Positive | E12: High | F12: Active company. Logged in as ORG_ADMIN. | G12: 1. Navigate to /admin/units; click 'New unit'; code='CTN', name='Carton'. Submit (HTTP 201). 2. Create another unit with code='CTN' in the same company — expect rejection. 3. Archive the CTN unit; verify it no longer appears in product base-unit or bulk-pack dropdowns. | H12: code=CTN, name=Carton. | I12: Step 1: HTTP 201; unit ACTIVE. Step 2: duplicate code rejected. Step 3: ARCHIVED unit absent from product unit pickers. | J12: /admin/units | POST /api/v1/units | PUT /api/v1/units/uid/{uid}/archive | K12: UOM.MANAGE | M12: Not Run
A13: PL-001 | B13: Price Lists | C13: Create, edit, archive, and restore a price list | D13: Positive | E13: High | F13: Active company. Logged in as ORG_ADMIN. | G13: 1. Navigate to /admin/price-lists; click 'New price list'; code='RETAIL', name='Retail'. Submit (201). 2. Edit name inline; save (200). 3. Archive (204) → badge ARCHIVED. 4. Restore (204) → badge ACTIVE. | H13: code=RETAIL, name=Retail. | I13: Full CRUD and lifecycle. PriceListDto envelopes. Duplicate code per company rejected. View-only role: writes hidden/403. | J13: /admin/price-lists | POST/PUT /api/v1/price-lists | PUT .../archive | PUT .../restore | K13: PRICELIST.MANAGE | M13: Not Run
A14: TAX-001 | B14: Tax Rates | C14: View the three seeded VAT bands; edit STANDARD rate | D14: Positive | E14: High | F14: Company with seeded tax rates (STANDARD, ZERO_RATED, EXEMPT). Logged in as ORG_ADMIN. | G14: 1. Navigate to /admin/tax-rates; confirm 3 rows with label, rate, status. 2. Click Edit on STANDARD; set rate=0.18; Save. 3. Attempt rate=1.0 — expect validation failure. | H14: rate=0.18 (valid). rate=1.0 (invalid — must be < 1). | I14: Step 2: HTTP 200; rate updated. Step 3: HTTP 400 (@DecimalMax 0.9999 + chk_tax_rate_value). No create or archive endpoint for tax rates. | J14: /admin/tax-rates | GET /api/v1/tax-rates | PUT /api/v1/tax-rates/uid/{uid} | K14: TAXRATE.MANAGE | M14: Not Run
... A22: FX-002 | B22: FX Rates | C22: FX rate list: SPOT vs MID type; paginator; cross-tenant rate isolation | D22: Positive | E22: Medium | F22: Company A with 25+ FX rates (mix of SPOT and MID). Company B with different rates. Logged in as Company A ORG_ADMIN. | G22: 1. Navigate to /admin/fx/rates; exercise paginator NEXT/LAST/FIRST. 2. Filter by rateType=SPOT — verify only SPOT rows shown. 3. Attempt to GET a Company-B rate uid as Company A user. | H22: Company A: 25+ rates. Company B: separate rate set. | I22: Paginator: NEXT/LAST/FIRST work; meta{page,size,totalElements,totalPages,hasNext} populated. Filter by type works. Company B rate returns 403 for Company A user. | J22: /admin/fx/rates | GET /api/v1/fx/rates?rateType=&page=&size= | K22: CURRENCY.VIEW | M22: Not Run

Sheet Sales – Order to Cash
A1: Sales – Order to Cash — UAT
A2: ID | B2: Area | C2: Test Scenario | D2: Type | E2: Priority | F2: Preconditions | G2: Steps | H2: Test Data | I2: Expected Result | J2: Route | K2: Permission | L2: Actual Result | M2: Status | N2: Severity | O2: Tester | P2: Run Date | Q2: Comments
A3: O2C-001 | B3: Quotation | C3: Create a draft quotation (CREDIT_ACCOUNT customer) | D3: Positive | E3: High | F3: Company with default branch. Active BUSINESS/CREDIT_ACCOUNT customer. Logged in as ORG_ADMIN with active branch header. | G3: 1. Navigate to /admin/quotations; click 'New quotation'. 2. Pick customer by name from the dropdown. 3. Set quoteDate=today, validUntil=today+30. 4. Submit. | H3: customer='Acme Ltd (CUST-0001)', quoteDate=today, validUntil=today+30, currency=TZS. | I3: HTTP 201. DRAFT quotation row appears with status badge DRAFT. No QUOTE-#### number yet (allocated on send). Customer chosen by name — no uid typed or shown. ApiResponse<QuotationDto>. | J3: /admin/quotations | POST /api/v1/quotations | K3: SALES.QUOTE.CREATE | M3: Not Run
A4: O2C-002 | B4: Quotation | C4: Add GOODS line to draft quotation with line discount %; reject invalid combinations | D4: Positive | E4: High | F4: DRAFT quotation (O2C-001). A sellable GOODS product with company price and VAT rate. Logged in as ORG_ADMIN. | G4: 1. Open quotation detail; product search → select product by code/name. 2. Choose unit, qty=10, discountPercent=5. Add line. 3. Verify line shows computed net/VAT/gross. Quotation totals recompute. 4. Attempt to set both discountPercent and discountAmount on the same line — expect rejection. | H4: product='Widget (PRD-0001)', unit='EACH', qty=10, lineDiscountPercent=5. | I4: HTTP 201 for line. Totals computed server-side (not client). Setting both discount types returns 400 (DiscountValidator). Qty<=0 returns validation error. Product with no price returns 400. | J4: POST /api/v1/quotations/uid/{uid}/lines | K4: SALES.QUOTE.CREATE | M4: Not Run
A5: O2C-003 | B5: Quotation | C5: Add SERVICE line to draft quotation | D5: Positive | E5: Medium | F5: DRAFT quotation. Sellable SERVICE product with company price and VAT rate. | G5: 1. Add a SERVICE product line (qty=2) to the quotation. | H5: product='Installation (SVC-0001)', qty=2. | I5: HTTP 201. Line added and priced identically to a goods line. No reservation concept applies to service lines. | J5: POST /api/v1/quotations/uid/{uid}/lines | K5: SALES.QUOTE.CREATE | M5: Not Run
A6: O2C-004 | B6: Quotation | C6: Send quotation (DRAFT → SENT, allocates QUOTE-#### number) | D6: Positive | E6: High | F6: DRAFT quotation with at least 1 line. validUntil >= today. | G6: 1. On quotation detail, click 'Send'. 2. Observe status badge changes to SENT and a QUOTE-#### number appears in the header. | H6: DRAFT quotation with 1+ lines and future validUntil. | I6: HTTP 204. status=SENT. quoteNumber allocated (QUOTE-####). sentAt stamped. Attempting to send with zero lines is blocked by UI (canSendNow = isDraft && lines>0). Sending with validUntil in the past returns 400. | J6: PUT /api/v1/quotations/uid/{uid}/send | K6: SALES.QUOTE.SEND | M6: Not Run
A7: O2C-005 | B7: Quotation | C7: Accept quotation (SENT → ACCEPTED) creates Sales Order | D7: Positive | E7: High | F7: SENT quotation with validUntil >= today. | G7: 1. On quotation detail, click 'Accept'. 2. Observe success toast with new SO number. 3. Navigate to the new Sales Order. | H7: SENT quotation. | I7: HTTP 201. quotation status=ACCEPTED with convertedOrderUid. New DRAFT Sales Order created with sourceQuotationUid set and lines copied. Accepting a DRAFT quotation returns 400. Accepting an expired SENT quotation auto-flips it to EXPIRED and returns 400. | J7: PUT /api/v1/quotations/uid/{uid}/accept | K7: SALES.QUOTE.ACCEPT | M7: Not Run
A8: O2C-006 | B8: Quotation | C8: Reject quotation (SENT → REJECTED) | D8: Positive | E8: Medium | F8: SENT quotation. | G8: 1. On quotation detail, click 'Reject'. 2. Verify status=REJECTED and rejectedAt stamped. | H8: SENT quotation. | I8: HTTP 204. status=REJECTED. Toast 'Quotation rejected'. Rejecting a DRAFT quotation returns 400. Reject shares the SALES.QUOTE.ACCEPT permission. | J8: PUT /api/v1/quotations/uid/{uid}/reject | K8: SALES.QUOTE.ACCEPT | M8: Not Run
A9: O2C-007 | B9: Quotation | C9: Illegal quotation transition matrix | D9: Negative | E9: Medium | F9: Quotations in each status: DRAFT, SENT, ACCEPTED, REJECTED, EXPIRED. Logged in as ORG_ADMIN. | G9: 1. Attempt to send a SENT/ACCEPTED/REJECTED/EXPIRED quote. 2. Attempt to accept a DRAFT/ACCEPTED/REJECTED/EXPIRED quote. 3. Attempt to reject a DRAFT/ACCEPTED/REJECTED/EXPIRED quote. 4. Attempt to add/remove a line on a SENT/ACCEPTED quote. | H9: Quotations in each status. | I9: Every illegal transition returns HTTP 400 with descriptive errors[]. No state change persisted. | J9: PUT /api/v1/quotations/uid/{uid}/send | /accept | /reject | POST/DELETE .../lines | K9: SALES.QUOTE.SEND | SALES.QUOTE.ACCEPT | SALES.QUOTE.CREATE | M9: Not Run
A10: O2C-008 | B10: Sales Order | C10: Create standalone draft Sales Order (CASH_WALK_IN customer) with document discount | D10: Positive | E10: High | F10: Company with default branch. An INDIVIDUAL/CASH_WALK_IN customer. Logged in as ORG_ADMIN. | G10: 1. Navigate to /admin/sales-orders; open create form. 2. Pick customer by name; set orderDate=today; docDiscountPercent=2. Submit. | H10: customer='Walk-in Joe (CUST-0009)', orderDate=today, docDiscountPercent=2, currency=TZS. | I10: HTTP 201. DRAFT SO with order number. No stock reserved yet. Setting both docDiscountPercent AND docDiscountAmount returns 400. Creating in an unassigned branch returns 403. | J10: /admin/sales-orders | POST /api/v1/sales-orders | K10: SALES.ORDER.CREATE | M10: Not Run
A11: O2C-009 | B11: Sales Order | C11: Add GOODS and SERVICE lines to draft Sales Order | D11: Positive | E11: High | F11: DRAFT Sales Order (O2C-008). Sellable GOODS and SERVICE products with company price and VAT rate. | G11: 1. Add a GOODS line: qty=20, lineDiscountAmount=1000. 2. Add a SERVICE line: qty=1. 3. Verify line totals and SO totals recompute server-side. | H11: GOODS product qty=20 discount=1000. SERVICE product qty=1. | I11: HTTP 201 each. Lines show orderedQty, listPrice, net/VAT/gross from DTO. qtyReservedBase/qtyFulfilledBase/qtyInvoicedBase start at 0. Adding a line to a CONFIRMED SO returns 400. | J11: POST /api/v1/sales-orders/uid/{uid}/lines | K11: SALES.ORDER.CREATE | M11: Not Run
A12: O2C-010 | B12: Sales Order | C12: Confirm Sales Order reserves stock (DRAFT → CONFIRMED) | D12: Positive | E12: High | F12: DRAFT SO with at least 1 GOODS line. Product has on-hand stock in the branch. Logged in as ORG_ADMIN. | G12: 1. On SO detail, click 'Confirm'. 2. Observe toast 'Order confirmed — stock reserved'. 3. Verify each line shows reservedQty = orderedQty. Status badge=CONFIRMED. 4. Verify reserved stock for the product/branch increased by the ordered base qty. | H12: DRAFT SO with a GOODS line (qty=10). | I12: HTTP 204. status=CONFIRMED. confirmedAt stamped. qtyReservedBase=qtyOrderedBase per line. Confirming an SO with zero lines returns 400. Confirming an already-CONFIRMED SO returns 400. | J12: PUT /api/v1/sales-orders/uid/{uid}/confirm | K12: SALES.ORDER.CONFIRM | M12: Not Run
A13: O2C-011 | B13: Sales Order | C13: Cancel confirmed Sales Order releases reservation (→ CANCELLED) | D13: Positive | E13: High | F13: CONFIRMED SO with reserved stock (O2C-010). Logged in as ORG_ADMIN. | G13: 1. On SO detail, open Cancel form; enter reason='Customer changed mind'. Submit. 2. Verify status=CANCELLED and per-line reserved qty returns to 0. 3. Verify stock reservation released. | H13: cancelReason='Customer changed mind'. | I13: HTTP 204. status=CANCELLED. cancelledAt and cancelReason stamped. Reservation negated. Cancelling a CLOSED SO returns 400. Reason is optional (null allowed). | J13: PUT /api/v1/sales-orders/uid/{uid}/cancel | K13: SALES.ORDER.CANCEL | M13: Not Run
A14: O2C-012 | B14: Sales Order | C14: SO status rollup: partial delivery → PARTIALLY_FULFILLED → FULFILLED | D14: Positive | E14: High | F14: CONFIRMED SO with single GOODS line qty=10. | G14: 1. Create delivery for qty=6 against the line. 2. Verify SO status=PARTIALLY_FULFILLED; line fulfilled=6, open=4. 3. Create second delivery for remaining qty=4. 4. Verify SO status=FULFILLED; line fulfilled=10, open=0. | H14: SO line qty=10. Delivery 1: qty=6. Delivery 2: qty=4. | I14: After partial delivery: PARTIALLY_FULFILLED. After full delivery: FULFILLED. Attempting to deliver qty=11 against open=10 returns 400 (BR-SO-11). | J14: POST /api/v1/deliveries | GET /api/v1/sales-orders/uid/{uid} | K14: SALES.DELIVERY.CREATE | SALES.ORDER.CONFIRM | M14: Not Run
... A45: O2C-043 | B45: O2C End-to-End | C45: Quotation for route-assigned customer: route and agent auto-populated; override accepted | D45: Positive | E45: Medium | F45: Route with customer and primary EXTERNAL agent assigned. Logged in as ORG_ADMIN. | G45: 1. Create quotation; pick the route-assigned customer. 2. Verify routeUid and agentUid auto-populated. 3. Override agentUid with another agent; confirm override saved. | H45: Route-assigned customer with primary agent. | I45: routeUid and agentUid pre-filled. Both fields overrideable. Quotation created with the overridden agentUid. | J45: POST /api/v1/quotations | K45: SALES.QUOTE.CREATE | M45: Not Run

Sheet Sales – Pricing
A1: Sales – Pricing — UAT
A2: ID | B2: Area | C2: Test Scenario | D2: Type | E2: Priority | F2: Preconditions | G2: Steps | H2: Test Data | I2: Expected Result | J2: Route | K2: Permission | L2: Actual Result | M2: Status | N2: Severity | O2: Tester | P2: Run Date | Q2: Comments
A3: SADV-001 | B3: Blanket Orders | C3: Blanket Orders list: pagination, four states, company scoping | D3: Positive | E3: High | F3: At least 21 ACTIVE blanket orders for the company. Logged in as ORG_ADMIN. | G3: 1. Navigate to /admin/blanket-orders; observe loading then idle. 2. Exercise paginator: NEXT, page number 2, LAST, FIRST, PREVIOUS. 3. Observe status badges and committed/drawn money. 4. Switch to a second company — verify data re-scopes. 5. Force error intercept — verify error state. 6. Log in as NO-PERMISSION user — verify nav item hidden + guard blocks. | H3: 21+ blanket orders. Two companies with distinct blanket sets. | I3: Rows render with order number, customer ID (known C1 deviation — shows numeric id per defect D-3), status badge, dates, money. Paginator full control set. Data re-scopes on company switch. Error/forbidden states distinct. | J3: /admin/blanket-orders | GET /api/v1/blanket-orders?companyId=&page=&size= | K3: SALES.BLANKET.VIEW | M3: Not Run
A4: SADV-002 | B4: Blanket Orders | C4: Create blanket order (customer + product pickers); date-window and required-field validation | D4: Positive | E4: High | F4: Active customer, product, unit, and branch for the company. Logged in as ORG_ADMIN. | G4: 1. Navigate to /admin/blanket-orders/create. 2. Select company; select branch. 3. Pick customer by 'code — name' via picker. 4. Set currency=TZS, validFrom=today, validTo=today+90d, notes='Q3 framework'. 5. Add line: pick product by name, pick unit, committedQty=100, unitPrice=1500.00; add second line qty=50 @ 2000.00. 6. Submit. | H4: customer='Beta Traders Ltd'. product='WIDGET-A' qty=100 @ 1500. Line 2 qty=50 @ 2000. | I4: HTTP 201. Status ACTIVE. totalCommittedAmount=250000.00. Both lines show drawn=0, remaining=committed. Customer and product chosen by name — uid only in URL. Blank customer/branch/currency/dates or validFrom>validTo blocked before POST. | J4: /admin/blanket-orders/create | POST /api/v1/blanket-orders | K4: SALES.BLANKET.CREATE | M4: Not Run
A5: SADV-003 | B5: Blanket Orders | C5: Blanket draw creates Sales Order; over-draw rejected; expired blanket rejected | D5: Positive | E5: High | F5: ACTIVE blanket with remaining>0. A user/role that holds SALES.BLANKET.MANAGE (note: under default V45 seed only rootadmin qualifies — see Defect D-1). Active agent. | G5: 1. Open blanket detail; click 'Draw Release'. 2. Enter Branch ID (numeric — C1 deviation per D-3); pick agent by name. 3. Set draw qty=40 on line 1; uncheck line 2. Click 'Create Release'. 4. Verify blanket line 1: drawn=40, remaining=60. SO stamped with source_blanket_uid. 5. Attempt draw qty=61 on a line with remaining=60. | H5: Branch ID numeric. Agent 'AG-001 — Inside Sales'. Draw qty=40. Over-draw test qty=61. | I5: Step 3: SO created (SalesOrderDto); toast with SO number. Step 4: remaining=60, totalDrawnAmount increased. Step 5: HTTP 409 'Draw quantity 61 exceeds remaining 60 on blanket line'. Drawing on a CANCELLED blanket returns 409 'not ACTIVE'. | J5: POST /api/v1/blanket-orders/uid/{uid}/draw | K5: SALES.BLANKET.MANAGE | M5: Not Run
A6: SADV-004 | B6: Blanket Orders | C6: Cancel blanket order; already-CANCELLED rejected; MANAGE permission gap (Defect D-1) | D6: Negative | E6: High | F6: An ACTIVE blanket. ORG_ADMIN logged in. | G6: 1. As ORG_ADMIN (holds VIEW/CREATE but NOT MANAGE per V45 seed), open blanket detail. 2. Confirm 'Cancel' button is NOT rendered (canManage=false). 3. Call DELETE /api/v1/blanket-orders/uid/{uid} directly as ORG_ADMIN. 4. As rootadmin, cancel the blanket (HTTP 200). 5. Attempt to cancel the same (now CANCELLED) blanket again. | H6: ACTIVE blanket. ORG_ADMIN and rootadmin credentials. | I6: Step 2: button absent. Step 3: HTTP 403 (SALES.BLANKET.MANAGE not granted to ORG_ADMIN by V45 seed). Step 4: status=CANCELLED. Step 5: HTTP 409 'already CANCELLED'. This documents Defect D-1 — MANAGE code is ungrafted. | J6: DELETE /api/v1/blanket-orders/uid/{uid} | K6: SALES.BLANKET.MANAGE (not seeded to any role — Defect D-1) | M6: Not Run
A7: SADV-005 | B7: Standing Orders | C7: Create MONTHLY standing order (uid-pickers); frequency variations | D7: Positive | E7: High | F7: Active customer, product, unit, and branch for the company. Logged in as ORG_ADMIN. | G7: 1. Navigate to /admin/standing-orders/create. 2. Pick branch via app-uid-picker by name; pick customer by name. 3. Set currency=TZS, frequency=Monthly, startDate=today, endDate=blank. 4. Add line: pick product + unit via pickers; qty=10, unitPrice=1200.00. Submit. | H7: customer='Beta Traders Ltd'. product='MILK-1L'. qty=10 @ 1200.00. frequency=MONTHLY. | I7: HTTP 201. Status ACTIVE. frequency=MONTHLY. nextRunDate populated. All pickers by name (uid in URL only). Creating for each of DAILY/WEEKLY/BIWEEKLY/MONTHLY succeeds. nextRunDate advances by correct cadence on trigger. | J7: /admin/standing-orders/create | POST /api/v1/standing-orders | K7: SALES.STANDING.CREATE | M7: Not Run
A8: SADV-006 | B8: Standing Orders | C8: Standing order lifecycle: pause/resume/cancel/trigger; illegal transitions rejected | D8: Positive | E8: High | F8: ACTIVE standing order. A user/role that holds SALES.STANDING.MANAGE (note: under V45 seed only rootadmin qualifies — Defect D-1). | G8: 1. Pause ACTIVE order → status=PAUSED (HTTP 200). 2. Pause already-PAUSED → 409. 3. Resume PAUSED → status=ACTIVE (HTTP 200). 4. Resume ACTIVE → 409. 5. Trigger ACTIVE → SO generated, nextRunDate advances by frequency (HTTP 200). 6. Trigger PAUSED → 409. 7. Cancel ACTIVE → status=CANCELLED (HTTP 200). 8. Cancel already-CANCELLED → 409. | H8: ACTIVE standing order (MONTHLY). | I8: Each legal transition returns 200 with updated StandingOrderDto. Each illegal returns 409 with descriptive message. Generated SO stamped with source_standing_uid. Outbox event STANDING_ORDER_GENERATED emitted on trigger. | J8: POST /api/v1/standing-orders/uid/{uid}/pause | /resume | /trigger | DELETE .../uid/{uid} | K8: SALES.STANDING.MANAGE | M8: Not Run
A9: SADV-007 | B9: Standing Orders | C9: Standing MANAGE permission gap (Defect D-1) — ORG_ADMIN cannot manage | D9: Permission | E9: High | F9: ORG_ADMIN logged in. Stock-seeded DB (V45 seed grants STANDING.GENERATE, not MANAGE). | G9: 1. Open a standing-order detail as ORG_ADMIN. 2. Observe action buttons (Pause/Resume/Cancel/Trigger). 3. Call each manage endpoint directly as ORG_ADMIN. | H9: ORG_ADMIN credentials. ACTIVE standing order. | I9: canManage() is false → NO Pause/Resume/Cancel/Trigger buttons. Direct API calls return HTTP 403. rootadmin succeeds (superuser bypass). Orphan permission SALES.STANDING.GENERATE is referenced by no controller. | J9: POST /api/v1/standing-orders/uid/{uid}/pause | /resume | /trigger | DELETE .../uid/{uid} | K9: SALES.STANDING.MANAGE (not seeded — Defect D-1) | M9: Not Run
A10: SADV-008 | B10: Pricing Rules | C10: Create price tier (product + price-list pickers); duplicate min-qty rejected | D10: Positive | E10: High | F10: A product and a price list for the company. Logged in as ORG_ADMIN. | G10: 1. Navigate to /admin/pricing-rules; Tiers tab. 2. Open create form; pick product by name; pick price list by name; minQty=10; unitPrice=950.00; currency=TZS. Save. 3. Create another tier for the same product+list+minQty=10. | H10: product='WIDGET-A'. priceList='Standard'. minQty=10 @ 950.00. | I10: Step 2: HTTP 201; tier row appears with status ACTIVE. Product and price-list chosen by name. Step 3: HTTP 409 'A tier with min_qty 10 already exists for this product+price_list'. Different minQty (25) is accepted. | J10: /admin/pricing-rules | POST /api/v1/pricing-rules/tiers | K10: SALES.PRICING.RULE.MANAGE | M10: Not Run
A11: SADV-009 | B11: Pricing Rules | C11: Deactivate price tier (soft delete); tier list is plain (no paginator) | D11: Positive | E11: Medium | F11: An ACTIVE tier in the loaded list (product + price-list filter applied). Logged in as ORG_ADMIN. | G11: 1. In Tiers tab with product+list filter, locate the tier row. 2. Click Deactivate. 3. Verify toast 'Price tier deactivated'; row removed from in-memory list. 4. Confirm list is a plain array with NO paginator. | H11: ACTIVE tier. | I11: DELETE sets status=INACTIVE (soft). Row removed from list. No app-paginator rendered (listTiers returns plain List). VIEW-only user gets 403 on deactivate. | J11: DELETE /api/v1/pricing-rules/tiers/uid/{uid} | K11: SALES.PRICING.RULE.MANAGE | M11: Not Run
A12: SADV-010 | B12: Pricing Rules | C12: Create customer price; unique (customer, product) rejected regardless of status | D12: Positive | E12: High | F12: Active customer and product for the company. Logged in as ORG_ADMIN. | G12: 1. Customer Prices tab; open create form. 2. Pick customer by name; pick product by name; unitPrice=880.00; currency=TZS; effectiveFrom=today; effectiveTo=today+180d. Save. 3. Create another price for the same customer+product. | H12: customer='Beta Traders Ltd'. product='WIDGET-A'. price=880.00. | I12: Step 2: HTTP 201; row ACTIVE. Step 3: rejected by DB uq_customer_price_scope — unique constraint is status-agnostic (cannot re-create even after deactivating the first). Omitting effective dates creates an open-ended price. | J12: POST /api/v1/pricing-rules/customer-prices | K12: SALES.PRICING.RULE.MANAGE | M12: Not Run
A13: SADV-011 | B13: Pricing Rules | C13: Promotions (backend-only; no UI — Defect D-2): create PRODUCT-target PERCENT_DISCOUNT | D13: Positive | E13: High | F13: A product in the company. ORG_ADMIN credentials. | G13: 1. POST /api/v1/pricing-rules/promotions with code='SUMMER10', name='Summer 10%', target=PRODUCT, targetProductUid=<product-uid>, effect=PERCENT_DISCOUNT, effectValue=10, effectiveFrom=today, effectiveTo=today+30d, priority=5. 2. Attempt effectValue=101 for PERCENT_DISCOUNT. 3. Attempt PRODUCT target without targetProductUid. 4. Verify via GET /api/v1/pricing-rules/promotions/uid/{uid} — no UI tab for promotions. | H13: Promotion code='SUMMER10', effectValue=10. Invalid: effectValue=101, missing targetProductUid. | I13: Step 1: HTTP 201 with PromotionDto. Step 2: 400 'effect_value must be 0-100'. Step 3: 400 'targetProductUid required when target=PRODUCT'. There is no Promotions tab in the Angular UI — Defect D-2. | J13: POST /api/v1/pricing-rules/promotions | GET /api/v1/pricing-rules/promotions/uid/{uid} | K13: SALES.PRICING.RULE.MANAGE | M13: Not Run
A14: SADV-012 | B14: Pricing Rules | C14: PriceSource diagnostic stamped on lines: CUSTOMER_PRICE > PROMOTION > TIER > LIST_PRICE > NONE | D14: Edge | E14: Low | F14: For one product+customer: active customer price, active promotion, active tier, and a list price. Also a product with none of these. Logged in as ORG_ADMIN. | G14: 1. Create SO/invoice lines for each pricing scenario. 2. Inspect the stored price_source field on each line. | H14: Various products with different pricing rule coverage. | I14: price_source reflects which rule won: CUSTOMER_PRICE > PROMOTION > TIER > LIST_PRICE > NONE. A product with no rule and no list price gets NONE. Diagnostic only — not used in financial calculations. | J14: POST /api/v1/sales-orders/uid/{uid}/lines | POST /api/v1/sales-invoices/uid/{uid}/lines | K14: SALES.ORDER.CREATE | SALES.INVOICE.CREATE | M14: Not Run
... A20: SADV-018 | B20: Pricing Rules | C20: Pricing rules page: axe-core check on Tiers and Customer Prices tabs | D20: Positive | E20: High | F20: Pricing rules with 3+ tiers and 3+ customer prices. Logged in as ORG_ADMIN. | G20: 1. Navigate to /admin/pricing-rules. 2. Click Tiers tab; run axe-core. 3. Click Customer Prices tab; run axe-core. | H20: 3 tiers, 3 customer prices. | I20: Zero critical/serious violations (WCAG 2.1 AA gate). Tab controls have role=tab/tabpanel; labels present; no colour-only contrast failures. | J20: /admin/pricing-rules | K20: SALES.PRICING.RULE.VIEW | M20: Not Run

Sheet POS
A1: POS — UAT
A2: ID | B2: Area | C2: Test Scenario | D2: Type | E2: Priority | F2: Preconditions | G2: Steps | H2: Test Data | I2: Expected Result | J2: Route | K2: Permission | L2: Actual Result | M2: Status | N2: Severity | O2: Tester | P2: Run Date | Q2: Comments
A3: POS-001 | B3: POS Tills | C3: POS nav group visible for user with POS codes; hidden for seeded ORG_ADMIN (Defect PERM) | D3: Permission | E3: High | F3: Three users: rootadmin, ORG_ADMIN (holds SALES.POS.* codes, NOT POS.* codes), NO-PERMISSION user. | G3: 1. Log in as rootadmin; navigate to /admin/home; expand 'Point of Sale' sidebar group; confirm three items (Point of Sale /admin/pos/sell, POS Sessions, POS Tills). 2. Log out; log in as NO-PERMISSION user; confirm POS group and items absent. 3. Log in as ORG_ADMIN; confirm POS items are ALSO hidden (DEFECT-POS-PERM: controllers check POS.* but seed grants SALES.POS.* — mismatch causes 403 for all non-root users). | H3: rootadmin, NO-PERMISSION, ORG_ADMIN credentials. | I3: rootadmin sees all three POS nav links. NO-PERMISSION and seeded ORG_ADMIN see none (DEFECT-POS-PERM). Direct nav to any /admin/pos/* route redirects to /admin/home for the no-perm user. | J3: /admin/pos/tills | /admin/pos/sessions | /admin/pos/sell | K3: POS.TILL.VIEW | POS.SESSION.VIEW | POS.SALE.CREATE (vs seeded SALES.POS.* — mismatch) | M3: Not Run
A4: POS-002 | B4: POS Tills | C4: Create a POS till (manager); deactivate (soft-delete) | D4: Positive | E4: High | F4: Company with at least 1 active branch. A user/role holding POS.TILL.MANAGE (rootadmin or custom). Logged in. | G4: 1. Navigate to /admin/pos/tills; click 'New Till'. 2. Enter Till Name='Counter 1'; pick Branch by name via app-uid-picker. Submit. 3. Verify success alert 'Till created'; new row with status ACTIVE. 4. Click 'Deactivate' on the row; verify status=INACTIVE (HTTP via DELETE). | H4: name='Counter 1', branch by name='Head Office'. | I4: Step 2: HTTP 201; PosTillDto with code server-assigned. Branch chosen by name, no uid typed. Step 4: status=INACTIVE (soft-delete). A cashier role without POS.TILL.MANAGE sees no 'New Till' button and gets 403 on direct POST. | J4: /admin/pos/tills | POST /api/v1/pos/tills | DELETE /api/v1/pos/tills/uid/{uid} | K4: POS.TILL.MANAGE | M4: Not Run
A5: POS-003 | B5: POS Tills | C5: Till list: four states (loading/empty/error/forbidden) + branch filter + cross-tenant denied | D5: Positive | E5: Medium | F5: Multi-branch company with tills in each branch. A cross-tenant till in Company B. | G5: 1. Navigate /admin/pos/tills; assert loading state before table resolves. 2. Select Branch A filter — only branch A tills listed. 3. Select Branch B filter. 4. Select 'All branches' — both shown. 5. Stub GET 500 — error state 'Could not load tills. Please try again.'. 6. Stub 403 — forbidden state. 7. GET /api/v1/pos/tills/uid/{B-till-uid} as Company A user — expect 403. | H5: Two branches with distinct tills. Company B till uid. | I5: Each of four states renders distinctly. Branch filter scopes correctly. Cross-tenant get returns 403. Branch column shows raw numeric branchId (known C1 violation CONVENTION-POS-UID — flag it). | J5: /admin/pos/tills | GET /api/v1/pos/tills | GET /api/v1/pos/tills/uid/{uid} | K5: POS.TILL.VIEW | M5: Not Run
A6: POS-004 | B6: POS Sessions | C6: Open a POS session with opening float; one-open-session-per-till invariant | D6: Positive | E6: High | F6: An ACTIVE till. A user/role holding POS.SESSION.OPEN. Logged in. | G6: 1. Navigate to /admin/pos/sessions; click 'Open Session'. 2. Pick till by name (only ACTIVE tills listed) via app-uid-picker; enter openingFloat=100000.00. Submit. 3. Verify new row with status=OPEN. 4. Attempt to open a SECOND session on the same till while first is OPEN. | H6: ACTIVE till. openingFloatAmount=100000.00. | I6: Step 2: HTTP 201; session status=OPEN, cashierId=acting user, openedAt set. Till chosen by name. Float blank/negative returns 400. Step 4: HTTP 409 'Till already has an OPEN session' (DB ux_pos_session_one_open). | J6: /admin/pos/sessions | POST /api/v1/pos/sessions | K6: POS.SESSION.OPEN | M6: Not Run
A7: POS-005 | B7: POS Sessions | C7: Session list: pagination, company scoping; session uid shown in list (C1 violation flag) | D7: Positive | E7: Medium | F7: At least 21 sessions for the company (default page size 20). Logged in. | G7: 1. Navigate to /admin/pos/sessions. 2. Exercise paginator: NEXT, LAST, FIRST, PREVIOUS. 3. Verify meta {page,size,totalElements,totalPages,hasNext}. 4. Switch company — verify data re-scopes. 5. Note: session uid is rendered in a visible 'Session UID' column — flag as CONVENTION-POS-UID violation. | H7: 21+ sessions. | I7: Paged list. Paginator full control set. Meta populated. Company switch re-scopes. Session uid visible in list column is a known C1 violation (flag but do not block). | J7: /admin/pos/sessions | GET /api/v1/pos/sessions?companyId=&page=&size= | K7: POS.SESSION.VIEW | M7: Not Run
A8: POS-006 | B8: POS Sessions | C8: X-read on OPEN session shows live totals; X-read on non-OPEN session rejected | D8: Positive | E8: High | F8: An OPEN session with at least one sale. Logged in. | G8: 1. Open session detail at /admin/pos/sessions/uid/:uid. 2. Assert X-Read card shows: Sales Total, Payouts, Expected Cash, Invoice Count. 3. Refresh X-read; assert it reloads. 4. Attempt GET .../x-read on a CLOSED session. | H8: OPEN session with sales. | I8: XReadDto: expectedCash = openingFloat + cashSales - payouts. X-read card has loading/error sub-states. Calling x-read on a non-OPEN session returns 409 'Session is not OPEN'. | J8: GET /api/v1/pos/sessions/uid/{uid}/x-read | K8: POS.SESSION.VIEW | M8: Not Run
A9: POS-007 | B9: POS Sessions | C9: Record PAID_OUT and REFUND payouts; payout on non-OPEN session rejected | D9: Positive | E9: High | F9: An OPEN session. Logged in with POS.SESSION.OPEN. | G9: 1. Click 'Record Payout'; type=PAID_OUT, amount=5000, reason='Drawer-to-safe drop'. Submit. 2. Verify X-read Payouts increased by 5000; Expected Cash decreased by 5000. 3. Add type=REFUND, amount=2500, reason='Customer cash refund'. 4. Attempt payout on a CLOSED session. | H9: PAID_OUT amount=5000. REFUND amount=2500. CLOSED session uid. | I9: Steps 1 and 3: Payout persisted; expected cash decreases (both types subtract). Amount<=0 returns 400. Step 4: HTTP 409 'is not OPEN'. Payout uses POS.SESSION.OPEN permission (not a separate payout permission). | J9: POST /api/v1/pos/sessions/uid/{uid}/payouts | K9: POS.SESSION.OPEN | M9: Not Run
A10: POS-008 | B10: POS Sessions | C10: Close session: declare counted cash; zero/over/short variance recorded | D10: Positive | E10: High | F10: An OPEN session with known expectedCash=100000. Logged in with POS.SESSION.CLOSE. | G10: 1. Click 'Close Session'; enter countedCash=100000.00 (exact). Submit. 2. Verify variance=0.00, status=CLOSED. 3. Test close with countedCash=100500 (over): verify variance=+500.00. 4. Test close with countedCash=99500 (short): verify variance=-500.00. 5. Attempt close on an already-CLOSED session. | H10: Expected cash=100000. Test counts: 100000, 100500, 99500. | I10: HTTP 204 each. varianceAmount = counted - expected. Zero variance: no GL yet. Over: +500 badge (info). Short: -500 badge (danger). Closing already-CLOSED returns 409 'is not OPEN'. Blank/negative counted blocked by UI; API has no minimum (negative blocked by DB chk). | J10: POST /api/v1/pos/sessions/uid/{uid}/close | K10: POS.SESSION.CLOSE | M10: Not Run
A11: POS-009 | B11: POS Sessions | C11: Reconcile CLOSED session: zero variance (no journal); over variance (DR Cash/CR 4900); short (DR 5170/CR Cash) | D11: Positive | E11: High | F11: Three CLOSED sessions: zero variance, +500 over, -500 short. GL configs CASH/POS_CASH_OVER/POS_CASH_SHORT seeded (V43). Logged in with POS.SESSION.RECONCILE. | G11: 1. Reconcile zero-variance session: verify status=RECONCILED, Z-Read shows Variance=0, no journalId. 2. Reconcile over-session (+500): verify journalId set; GL journal DR CASH 500 / CR 4900 500. 3. Reconcile short-session (-500): verify journalId set; GL journal DR 5170 500 / CR CASH 500. 4. Attempt reconcile on an already-RECONCILED session. | H11: Three CLOSED sessions. GL config codes: CASH, POS_CASH_OVER (4900), POS_CASH_SHORT (5170). | I11: Step 1: no journal. Steps 2 and 3: balanced journals posted. Step 4: HTTP 409 'Session must be CLOSED before reconciliation'. Missing GL config causes fail-fast on reconcile — session stays CLOSED. | J11: POST /api/v1/pos/sessions/uid/{uid}/reconcile | K11: POS.SESSION.RECONCILE | M11: Not Run
A12: POS-010 | B12: POS Sessions | C12: Illegal session transition matrix | D12: Negative | E12: High | F12: Sessions in OPEN, CLOSED, RECONCILED states. | G12: 1. Reconcile an OPEN session → 409. 2. Close a CLOSED session → 409. 3. Close a RECONCILED session → 409. 4. Reconcile a RECONCILED session → 409. 5. Payout on CLOSED or RECONCILED → 409. 6. X-read on CLOSED or RECONCILED → 409. 7. Sell (/pos/sales) against CLOSED/RECONCILED session → 409. 8. Confirm no endpoint exists to reopen (no backwards transition). | H12: Sessions in each status. | I12: Each illegal transition returns HTTP 409 with the stated message. No state change. Legal chain OPEN→CLOSE→RECONCILE always succeeds in order. | J12: POST /api/v1/pos/sessions/uid/{uid}/close | /reconcile | /payouts | GET .../x-read | POST /api/v1/pos/sales | K12: POS.SESSION.CLOSE | POS.SESSION.RECONCILE | POS.SESSION.OPEN | POS.SALE.CREATE | M12: Not Run
A13: POS-011 | B13: POS Checkout | C13: Quick sale: walk-in customer, single GOODS line, CASH tender, change shown | D13: Positive | E13: High | F13: OPEN session. ACTIVE CASH_WALK_IN customer. Sellable GOODS product with price. ACTIVE agent. User with POS.SALE.CREATE. | G13: 1. Navigate to /admin/pos/sell; select company. 2. Pick session (only OPEN sessions listed) by label; pick customer by name; pick agent by name. 3. Currency=TZS. 4. Add line: pick product by name; qty=2; unitPrice=1500; discount=0. Assert line subtotal=3000 and footer Total 'TZS 3,000.00'. 5. Enter tendered=5000; assert change='TZS 2,000.00' in success colour. 6. Click 'Complete Sale'. 7. Assert receipt: invoice number, 'Total: TZS 3,000.00', 'View Invoice' link, 'New Sale' button. | H13: qty=2 × 1500=3000. tendered=5000. change=2000. | I13: HTTP 201 SalesInvoiceDto. origin=POS. FINALISED status. CASH payment for full gross 3000. posSessionId set. Session cash-sales total increases. All resources chosen by name via picker. | J13: /admin/pos/sell | POST /api/v1/pos/sales | K13: POS.SALE.CREATE | M13: Not Run
A14: POS-012 | B14: POS Checkout | C14: Checkout validation: required fields and line validation block submit | D14: Negative | E14: High | F14: OPEN session present. User with POS.SALE.CREATE. | G14: 1. Submit with no session → 'Session is required.'. 2. Add session; submit with no customer → 'Customer is required.'. 3. Clear currency → 'Currency is required.'. 4. No line items → 'Add at least one line item.'. 5. Line with no product → 'Select a product for every line.'. 6. Line with no unit → 'Select a unit for every line.'. 7. Qty=0 → 'Quantity must be positive for every line.'. 8. Unit price negative → 'Unit price must be non-negative for every line.'. | H14: Each invalid field configuration. | I14: Each missing/invalid field blocks submit with the exact inline error message. No POST fired until all fields valid. | J14: /admin/pos/sell | K14: POS.SALE.CREATE | M14: Not Run
... A25: POS-023 | B25: POS Tills | C25: Tills page: axe-core clean; branchId C1 violation flagged | D25: Positive | E25: High | F25: Company with 3+ tills. Logged in with POS.TILL.VIEW. | G25: 1. Navigate to /admin/pos/tills. 2. Run axe-core. 3. Inspect Branch column — record whether raw numeric branchId is shown instead of code/name. | H25: 3+ tills with known branch names. | I25: Zero axe critical/serious violations. Branch column shows raw numeric branchId (known CONVENTION-POS-UID C1 violation — log defect, do not block gate). Table has caption and scoped headers. | J25: /admin/pos/tills | K25: POS.TILL.VIEW | M25: Not Run

Sheet Procurement (P2P)
A1: Procurement (P2P) — UAT
A2: ID | B2: Area | C2: Test Scenario | D2: Type | E2: Priority | F2: Preconditions | G2: Steps | H2: Test Data | I2: Expected Result | J2: Route | K2: Permission | L2: Actual Result | M2: Status | N2: Severity | O2: Tester | P2: Run Date | Q2: Comments
A3: P2P-001 | B3: Purchase Requisition | C3: Requisition list loads with pagination and four states | D3: Positive | E3: High | F3: User has PURCHASE.REQUISITION.VIEW. At least 26 requisitions exist for the active company so page 2 is available. | G3: 1. Login as PURCHASE_OFFICER. 2. Navigate to /admin/purchase-requisitions. 3. Confirm loading state appears then resolves to table. 4. Verify paginator shows FIRST, PREVIOUS, page numbers, NEXT, LAST. 5. Click NEXT; confirm page 2 loads. 6. Apply status filter = DRAFT; confirm rows narrow. | H3: Company: Acme Trading Ltd. 26+ seeded requisitions. | I3: Table lists requisitions with requisition number, status badge, required-by date. Meta includes page/size/totalElements/totalPages/hasNext. HTTP 200. | J3: /admin/purchase-requisitions | K3: PURCHASE.REQUISITION.VIEW | M3: Not Run
A4: P2P-002 | B4: Purchase Requisition | C4: Create requisition with GOODS line lands in DRAFT status | D4: Positive | E4: High | F4: User has PURCHASE.REQUISITION.CREATE. At least one active GOODS product and unit of measure exist. | G4: 1. Navigate to /admin/purchase-requisitions/create. 2. Set required-by date and optional notes. 3. Add a line: choose product by name via picker; choose unit BAG; enter requestedQty=10, estimatedUnitCost=5000. 4. Submit. | H4: Product: Cement 50kg. Unit: BAG. requestedQty: 10. estimatedUnitCost: 5000. | I4: HTTP 201. Requisition status = DRAFT. Redirect to detail. uid appears only in the URL, not in any visible label. | J4: /admin/purchase-requisitions/create | POST /api/v1/purchase-requisitions | K4: PURCHASE.REQUISITION.CREATE | M4: Not Run
A5: P2P-003 | B5: Purchase Requisition | C5: Submit requisition transitions DRAFT to SUBMITTED | D5: Positive | E5: High | F5: User has PURCHASE.REQUISITION.CREATE. A DRAFT requisition exists. | G5: 1. Open the DRAFT requisition detail. 2. Click Submit. 3. Observe status badge updates. | H5: A DRAFT requisition created in P2P-002. | I5: Status changes to SUBMITTED. submittedAt is set and displayed. Submit button is hidden afterwards. | J5: /admin/purchase-requisitions/uid/:uid | POST /api/v1/purchase-requisitions/uid/{uid}/submit | K5: PURCHASE.REQUISITION.CREATE | M5: Not Run
A6: P2P-004 | B6: Purchase Requisition | C6: Approve a SUBMITTED requisition transitions to APPROVED | D6: Positive | E6: High | F6: User has PURCHASE.REQUISITION.APPROVE. A SUBMITTED requisition exists. | G6: 1. Open the SUBMITTED requisition detail. 2. Click Approve. 3. Observe status badge. | H6: A SUBMITTED requisition from P2P-003. | I6: Status changes to APPROVED. approvedAt is set. Convert action is now offered. | J6: /admin/purchase-requisitions/uid/:uid | POST /api/v1/purchase-requisitions/uid/{uid}/approve | K6: PURCHASE.REQUISITION.APPROVE | M6: Not Run
A7: P2P-005 | B7: Purchase Requisition | C7: Reject a SUBMITTED requisition with required reason | D7: Positive | E7: High | F7: User has PURCHASE.REQUISITION.APPROVE. A SUBMITTED requisition exists. | G7: 1. Open the SUBMITTED requisition detail. 2. Click Reject. 3. Enter reason: Budget exceeded for Q2. 4. Confirm. | H7: reason: Budget exceeded for Q2. | I7: Status changes to REJECTED. rejectedAt is set. Reason captured. Empty reason is blocked by the UI (Rejection reason is required). | J7: /admin/purchase-requisitions/uid/:uid | POST /api/v1/purchase-requisitions/uid/{uid}/reject | K7: PURCHASE.REQUISITION.APPROVE | M7: Not Run
A8: P2P-006 | B8: Purchase Requisition | C8: Convert APPROVED requisition to Purchase Order | D8: Positive | E8: High | F8: User has PURCHASE.REQUISITION.APPROVE. An APPROVED requisition with GOODS lines exists. | G8: 1. Open the APPROVED requisition detail. 2. Open Convert form; select target = Purchase Order. 3. Confirm. | H8: targetType: PURCHASE_ORDER. | I8: Returns created PO uid. Requisition status changes to CONVERTED with convertedToType=PURCHASE_ORDER. A View created PURCHASE_ORDER link routes to /admin/purchase-orders/uid/{uid}. uid is only in the link URL. | J8: /admin/purchase-requisitions/uid/:uid | POST /api/v1/purchase-requisitions/uid/{uid}/convert?targetType=PURCHASE_ORDER | K8: PURCHASE.REQUISITION.APPROVE | M8: Not Run
A9: P2P-007 | B9: Purchase Requisition | C9: Convert APPROVED requisition to RFQ | D9: Positive | E9: High | F9: User has PURCHASE.REQUISITION.APPROVE. An APPROVED requisition exists. | G9: 1. Open the APPROVED requisition detail. 2. Open Convert form; select target = RFQ. 3. Confirm. | H9: targetType: RFQ. | I9: Created RFQ uid returned. Requisition status = CONVERTED, convertedToType = RFQ. Follow link routes to /admin/rfqs/uid/{uid}. | J9: /admin/purchase-requisitions/uid/:uid | POST /api/v1/purchase-requisitions/uid/{uid}/convert?targetType=RFQ | K9: PURCHASE.REQUISITION.APPROVE | M9: Not Run
A10: P2P-008 | B10: Purchase Requisition | C10: Cancel a non-final requisition | D10: Positive | E10: Medium | F10: User has PURCHASE.REQUISITION.CREATE. A DRAFT or SUBMITTED requisition exists. | G10: 1. Open requisition detail. 2. Click Cancel. 3. Optionally enter a reason; confirm. | H10: A DRAFT requisition. | I10: Status changes to CANCELLED. cancelledAt is set. | J10: /admin/purchase-requisitions/uid/:uid | POST /api/v1/purchase-requisitions/uid/{uid}/cancel | K10: PURCHASE.REQUISITION.CREATE | M10: Not Run
A11: P2P-009 | B11: Purchase Requisition | C11: Illegal requisition transitions are rejected | D11: Negative | E11: High | F11: User has PURCHASE.REQUISITION.APPROVE. Requisitions in CONVERTED and CANCELLED states exist. | G11: 1. Attempt to submit an already-SUBMITTED requisition. 2. Attempt to approve a DRAFT (not submitted) requisition. 3. Attempt to cancel a CONVERTED requisition. 4. Attempt to convert a DRAFT requisition. | H11: One requisition in each relevant state. | I11: Each attempt is rejected with an error. Status does not change. Appropriate action buttons are hidden in the UI for terminal/invalid states. | J11: /admin/purchase-requisitions/uid/:uid | K11: PURCHASE.REQUISITION.APPROVE | M11: Not Run
A12: P2P-010 | B12: Purchase Requisition | C12: PURCHASE.REQUISITION.CREATE user cannot approve | D12: Permission | E12: High | F12: A user with PURCHASE.REQUISITION.CREATE but NOT PURCHASE.REQUISITION.APPROVE. A SUBMITTED requisition exists. | G12: 1. Login as the restricted user. 2. Open the SUBMITTED requisition detail. 3. Observe the Approve button. | H12: SUBMITTED requisition. | I12: Approve button is hidden. Direct POST to /api/v1/purchase-requisitions/uid/{uid}/approve returns HTTP 403. | J12: /admin/purchase-requisitions/uid/:uid | K12: PURCHASE.REQUISITION.CREATE (lacking APPROVE) | M12: Not Run
A13: P2P-011 | B13: Purchase Requisition | C13: Cross-tenant requisition access returns forbidden state | D13: Permission | E13: High | F13: A requisition belonging to Company A. User belongs only to Company B. | G13: 1. Login as Company B user. 2. Navigate directly to the Company A requisition uid URL. | H13: Requisition uid from Company A. | I13: API returns 403. The detail component shows the forbidden state (visually distinct from the loading, empty, and error states). | J13: /admin/purchase-requisitions/uid/:uid | K13: PURCHASE.REQUISITION.VIEW (scoped) | M13: Not Run
A14: P2P-020 | B14: RFQ / Sourcing | C14: Create RFQ with supplier invites and GOODS lines (rootadmin only — RBAC defect) | D14: Positive | E14: High | F14: Run as rootadmin. PURCHASE.RFQ.CREATE is NOT seeded so only rootadmin can reach this endpoint. At least 2 active suppliers and 1 GOODS product exist. | G14: 1. Navigate to /admin/rfqs/create. 2. Set response-due date and notes. 3. Invite suppliers: choose each by name via picker (at least 2). 4. Add line: product by name, unit, quantity=100. 5. Submit. | H14: Suppliers: MegaSupply Co, BuildMart. Product: Cement 50kg. qty: 100. | I14: HTTP 201. RFQ status = DRAFT. Invited supplier names visible in the detail. Redirect to detail. uid only in URL. | J14: /admin/rfqs/create | POST /api/v1/rfqs | K14: PURCHASE.RFQ.CREATE (NOT seeded — rootadmin only) | M14: Not Run
... A43: P2P-090 | B43: Full Chain | C43: Full P2P chain: requisition > RFQ > quote > award(PO) > place > receive > landed-cost > bill > match > return | D43: Positive | E43: High | F43: Run as rootadmin. One GOODS supplier, one GOODS product and unit, company with default branch, purchase settings with approval disabled. | G43: 1. Create requisition (DRAFT) with one GOODS line; Submit; Approve; Convert to RFQ. 2. Open RFQ; Send; Capture two quotes (different prices); Award the cheaper — PO created DRAFT. 3. Open PO; Place (ORDERED). 4. Create GR for full qty — PO becomes RECEIVED, GRN-#### assigned. 5. Create landed cost (BY_VALUE, FREIGHT charge) over the GR; Confirm. 6. Enter supplier bill matching PO qty and price; auto match — bill status = MATCHED. 7. Create purchase return for damaged units against the GR; Confirm. | H43: GOODS supplier. GOODS product. Approval disabled. Two quotes with different unit prices. | I43: Every transition lands the expected status: Requisition CONVERTED, RFQ AWARDED, Quote AWARDED/NOT_AWARDED, PO RECEIVED, GR RECEIVED, LC CONFIRMED, Bill MATCHED, Return CONFIRMED. All document numbers are human-readable (PO-####, GRN-####). uids appear only in URLs. | J43: All PROC routes | K43: rootadmin (full chain requires codes not grantable to custom roles) | M43: Not Run

Sheet Inventory
A1: Inventory — UAT
A2: ID | B2: Area | C2: Test Scenario | D2: Type | E2: Priority | F2: Preconditions | G2: Steps | H2: Test Data | I2: Expected Result | J2: Route | K2: Permission | L2: Actual Result | M2: Status | N2: Severity | O2: Tester | P2: Run Date | Q2: Comments
A3: INV-001 | B3: Stock On-Hand | C3: Stock on-hand list loads with pagination and company/branch scope | D3: Positive | E3: High | F3: User has STOCK.VIEW. At least 25 GOODS products with on-hand rows at the active branch. | G3: 1. Navigate to /admin/stock. 2. Confirm table rows with quantity (3-dp), reorder level, and negative/low flags. 3. Verify paginator shows all five controls. 4. Click NEXT; confirm page 2 loads. 5. Click FIRST to return. | H3: Company: Acme HQ. Default branch. | I3: Table shows product code/name, quantity (3-dp), reorder level, negative and low flags. ApiResponse with meta (page/size/totalElements/totalPages/hasNext). HTTP 200. | J3: /admin/stock | GET /api/v1/stock/on-hand | K3: STOCK.VIEW | M3: Not Run
A4: INV-002 | B4: Stock On-Hand | C4: On-hand search filter with debounce resets to page 0 | D4: Positive | E4: Medium | F4: User has STOCK.VIEW. Products including one named WIDGET-100 exist. | G4: 1. Navigate to /admin/stock; go to page 2. 2. Type WIDGET into the search box. 3. Wait for 300ms debounce. 4. Confirm the request fires with q=WIDGET&page=0. | H4: q: WIDGET. | I4: Results filtered to matching rows. Current page resets to 0. No uid visible in the table. | J4: /admin/stock | GET /api/v1/stock/on-hand?q= | K4: STOCK.VIEW | M4: Not Run
A5: INV-003 | B5: Stock On-Hand | C5: On-hand negative and low-stock derived flags are displayed | D5: Positive | E5: Medium | F5: User has STOCK.VIEW. One product with negative on-hand (oversold). One product with quantity at or below its reorderLevel. | G5: 1. Open /admin/stock. 2. Locate the negative-on-hand row and the low-stock row. | H5: Product A: quantity < 0. Product B: quantity <= reorderLevel. | I5: negative=true row is visually flagged with an overselling indicator. low=true row is flagged with a reorder indicator. Both flags are server-derived from StockOnHandDto.from(), not stored columns. | J5: /admin/stock | GET /api/v1/stock/on-hand | K5: STOCK.VIEW | M5: Not Run
A6: INV-004 | B6: Stock On-Hand | C6: NO-PERMISSION user cannot access stock on-hand | D6: Permission | E6: High | F6: A user with zero permissions assigned to a company/branch. | G6: 1. Login as the no-permission user. 2. Inspect the shell nav. 3. Attempt to navigate directly to /admin/stock. | H6: User with no permissions. | I6: No Inventory nav items render. Direct navigation is redirected to /admin/home by the route guard (requirePermission('STOCK.VIEW')). Backend GET /api/v1/stock/on-hand returns 403. | J6: /admin/stock | K6: None (STOCK.VIEW missing) | M6: Not Run
A7: INV-005 | B7: Stock On-Hand | C7: By-Location view shows per-location on-hand rows | D7: Positive | E7: High | F7: User has STOCK.VIEW. Multiple stock locations at the active branch with on-hand. | G7: 1. Navigate to /admin/stock; select a branch. 2. Toggle view mode to By Location. 3. Confirm rows show location code/name, product code/name, quantity, onHandValue, avgCost, currency. | H7: Branch: Main Branch. | I7: LocationOnHandRowDto rows paged. Money formatted with currency. No raw uid visible. companyId and branchId sent as wire params. | J7: /admin/stock | GET /api/v1/stock/on-hand/by-location | K7: STOCK.VIEW | M7: Not Run
A8: INV-006 | B8: Stock On-Hand | C8: By-Product view selects product via picker and lists all holding locations | D8: Positive | E8: High | F8: User has STOCK.VIEW. A GOODS product held at at least 2 locations. | G8: 1. Toggle to By Product. 2. Type product name in the search; pick result by name (code — name format). 3. Confirm per-location breakdown loads. | H8: Product: WIDGET-100. Held at 2 locations. | I8: All locations holding the product shown with quantity/value. productUid placed in URL path only; product chosen by name. | J8: /admin/stock | GET /api/v1/stock/on-hand/by-product/uid/{productUid} | K8: STOCK.VIEW | M8: Not Run
A9: INV-007 | B9: Stock On-Hand | C9: Manual positive adjustment with reason COUNT_CORRECTION | D9: Positive | E9: High | F9: User has STOCK.ADJUST. An on-hand row for a GOODS product exists. | G9: 1. Open /admin/stock; on a row click Adjust. 2. Product is pre-selected by name. Choose reason = COUNT_CORRECTION. 3. Enter quantity=10, note=cycle count fix. 4. Submit. | H9: quantity: 10. reason: COUNT_CORRECTION. | I9: HTTP 201. StockMovementDto with movementType=ADJUSTMENT and direction=IN. On-hand increases by 10. Adjustment is an appended movement row (not an edit). | J9: /admin/stock | POST /api/v1/stock/adjustments | K9: STOCK.ADJUST | M9: Not Run
A10: INV-008 | B10: Stock On-Hand | C10: Manual negative adjustment with reason DAMAGE drives stock down | D10: Positive | E10: Medium | F10: User has STOCK.ADJUST. An on-hand row with quantity > 3 exists. | G10: 1. Open /admin/stock; click Adjust on a row. 2. Choose reason = DAMAGE. 3. Enter quantity=-3. 4. Submit. | H10: quantity: -3. reason: DAMAGE. | I10: HTTP 201. direction=OUT. On-hand decreases by 3. If this creates a negative on-hand, the negative flag is set (allowed but flagged — not a hard reject). | J10: /admin/stock | POST /api/v1/stock/adjustments | K10: STOCK.ADJUST | M10: Not Run
A11: INV-009 | B11: Stock On-Hand | C11: STOCK.VIEW-only user cannot perform manual adjustment | D11: Permission | E11: High | F11: A user with STOCK.VIEW but not STOCK.ADJUST. | G11: 1. Login as the restricted user. 2. Open /admin/stock. 3. Observe the Adjust action on a row. | H11: User with STOCK.VIEW only. | I11: Adjust action is hidden. Direct POST to /api/v1/stock/adjustments returns HTTP 403. | J11: /admin/stock | K11: STOCK.VIEW (lacking STOCK.ADJUST) | M11: Not Run
A12: INV-010 | B12: Stock On-Hand | C12: Opening balance for a never-tracked product | D12: Positive | E12: High | F12: User has STOCK.OPENING. A GOODS product with NO prior stock movement at the active branch. | G12: 1. Open /admin/stock; click Opening balance. 2. Pick the product by name via picker. 3. Enter quantity=100, note=go-live. 4. Submit. | H12: quantity: 100. | I12: HTTP 201. StockMovementDto with movementType=OPENING_BALANCE and direction=IN. On-hand becomes 100. | J12: /admin/stock | POST /api/v1/stock/opening-balances | K12: STOCK.OPENING | M12: Not Run
A13: INV-011 | B13: Stock On-Hand | C13: Opening balance rejected when stock is already tracked | D13: Negative | E13: Medium | F13: User has STOCK.OPENING. A product that already has an opening balance or prior movement. | G13: 1. Open /admin/stock; click Opening balance. 2. Pick the already-tracked product. 3. Enter quantity=50. 4. Submit. | H13: Product with prior movements. | I13: Backend rejects (400/409). Inline error from errors[] array. On-hand unchanged. | J13: /admin/stock | POST /api/v1/stock/opening-balances | K13: STOCK.OPENING | M13: Not Run
A14: INV-012 | B14: Stock On-Hand | C14: Set reorder level then clear it | D14: Positive | E14: Medium | F14: User has STOCK.ADJUST. An on-hand row exists. | G14: 1. Click reorder-level edit on a row; enter 5; save. 2. Confirm the low flag is set if quantity<=5. 3. Edit again; clear the field; save. | H14: reorderLevel: 5, then blank/null. | I14: Returns updated StockOnHandDto. After setting 5, low=true when quantity<=5. After clearing, low=false. uid only in URL path. | J14: /admin/stock | PUT /api/v1/stock/on-hand/uid/{uid}/reorder-level | K14: STOCK.ADJUST | M14: Not Run
... A42: INV-081 | B42: Multi-tenancy | C42: Branch switching changes on-hand and count context | D42: Positive | E42: Medium | F42: User has STOCK.VIEW and STOCK.COUNT.VIEW. User assigned to many branches. | G42: 1. On /admin/stock, switch the branch selector to a non-default branch. 2. Confirm on-hand reloads for that branch. 3. Repeat on counts. | H42: User assigned to multiple branches. | I42: Data follows the active branch. Default-branch and non-default-branch on-hand sets differ. User assigned to only one branch cannot switch to another (denied). | J42: /admin/stock | /admin/stock-counts | K42: STOCK.VIEW + STOCK.COUNT.VIEW | M42: Not Run

Sheet Manufacturing
A1: Manufacturing — UAT
A2: ID | B2: Area | C2: Test Scenario | D2: Type | E2: Priority | F2: Preconditions | G2: Steps | H2: Test Data | I2: Expected Result | J2: Route | K2: Permission | L2: Actual Result | M2: Status | N2: Severity | O2: Tester | P2: Run Date | Q2: Comments
A3: MFG-001 | B3: BOM | C3: BOM list loads with company scope, status filter, and pagination | D3: Positive | E3: High | F3: User has BOM.VIEW. At least one BOM exists. BOMs in DRAFT, ACTIVE, and ARCHIVED statuses exist. | G3: 1. Navigate to /admin/boms. 2. Confirm table renders BOM rows with parent product name/code, version, status badge, output qty, yield %. 3. Select status filter = Draft; confirm only DRAFT BOMs shown. 4. Select Active, then Archived, then All. 5. Page through with paginator. | H3: Company: Acme Manufacturing. BOMs in all three statuses. | I3: Each filter re-queries with status= param and shows only matching rows. Paginator shows all five controls. No uid visible in any column. | J3: /admin/boms | GET /api/v1/boms | K3: BOM.VIEW | M3: Not Run
A4: MFG-002 | B4: BOM | C4: Create BOM (DRAFT) via inline form using product picker | D4: Positive | E4: High | F4: User has BOM.MANAGE. An ACTIVE GOODS product exists in the company. | G4: 1. On /admin/boms, click the create toggle. 2. In the parent product picker, search and select by name. 3. Enter outputQty=10, yieldPercent=95, notes=Pilot batch. 4. Submit. | H4: Product: Widget A. outputQty: 10. yieldPercent: 95. | I4: HTTP 201. New DRAFT row appears with versionNo. uid appears only in the success alert link, not in any visible cell. Parent product shown by name. | J4: /admin/boms | POST /api/v1/boms | K4: BOM.MANAGE | M4: Not Run
A5: MFG-003 | B5: BOM | C5: Add components to a DRAFT BOM — Auto, MAKE, and BUY sourcing | D5: Positive | E5: High | F5: User has BOM.MANAGE. A DRAFT BOM exists. Active component products exist. | G5: 1. Open the DRAFT BOM detail; click Add component. 2. Select component product by name via picker. 3. Enter qtyPer=2, scrapPercent=5, reference=RES-1; sourcing=Auto. 4. Submit. Repeat with MAKE and BUY sourcing. | H5: qtyPer: 2. scrapPercent: 5. reference: RES-1. Sourcing: Auto, MAKE, BUY. | I5: HTTP 201 for each. Component line appended with line number, component code/name, qty per, sourcing, scrap %. With Auto sourcing, server derives MAKE if child has an ACTIVE BOM else BUY. | J5: /admin/boms/uid/:uid | POST /api/v1/boms/uid/{uid}/components | K5: BOM.MANAGE | M5: Not Run
A6: MFG-004 | B6: BOM | C6: Edit and remove BOM component on DRAFT BOM | D6: Positive | E6: Medium | F6: User has BOM.MANAGE. A DRAFT BOM with at least 2 components. | G6: 1. Click edit on a component; change qtyPer=3.5, sourcing=BUY, scrapPercent=0; save. 2. Click remove on another component; confirm. | H6: qtyPer: 3.5. sourcing: BUY. scrapPercent: 0. | I6: Edit returns updated component (200). Remove returns 204 and line disappears. Only DRAFT BOMs allow structural changes (edit/remove hidden on ACTIVE BOMs in UI). | J6: /admin/boms/uid/:uid | PUT .../components/{componentUid} | DELETE .../components/{componentUid} | K6: BOM.MANAGE | M6: Not Run
A7: MFG-005 | B7: BOM | C7: Activate DRAFT BOM — transitions to ACTIVE with effective-from date | D7: Positive | E7: High | F7: User has BOM.MANAGE. A DRAFT BOM with at least one valid component exists. No prior ACTIVE version. | G7: 1. Open the DRAFT BOM detail. 2. Click Activate. 3. Enter effectiveFrom = today. 4. Confirm. | H7: effectiveFrom: 2026-06-14. | I7: Status changes to ACTIVE. effectiveFrom set, effectiveTo null, activatedAt stamped. Success: BOM activated. | J7: /admin/boms/uid/:uid | POST /api/v1/boms/uid/{uid}/activate | K7: BOM.MANAGE | M7: Not Run
A8: MFG-006 | B8: BOM | C8: Activating a new version supersedes the prior ACTIVE BOM (one-active rule) | D8: Positive | E8: High | F8: User has BOM.MANAGE. Product has ACTIVE BOM v1 and DRAFT BOM v2 (same parent). | G8: 1. Open DRAFT v2. 2. Click Activate with effectiveFrom = today. | H8: ACTIVE BOM v1, DRAFT BOM v2 for same parent product. | I8: v2 becomes ACTIVE (effectiveTo null). v1 atomically becomes ARCHIVED with effectiveTo = effectiveFrom and archivedAt stamped. Only one ACTIVE BOM remains for the parent. v1 is archived not deleted. | J8: /admin/boms/uid/:uid | POST /api/v1/boms/uid/{uid}/activate | K8: BOM.MANAGE | M8: Not Run
A9: MFG-007 | B9: BOM | C9: Archive a BOM — DRAFT or ACTIVE transitions to ARCHIVED | D9: Positive | E9: Medium | F9: User has BOM.MANAGE. An ACTIVE BOM and a DRAFT BOM exist. | G9: 1. Open the ACTIVE BOM detail; click Archive; confirm. 2. Repeat for the DRAFT BOM. | H9: One ACTIVE BOM, one DRAFT BOM. | I9: Status changes to ARCHIVED. archivedAt stamped. Header and component edit controls disappear. ARCHIVED BOM is not hard-deleted. | J9: /admin/boms/uid/:uid | POST /api/v1/boms/uid/{uid}/archive | K9: BOM.MANAGE | M9: Not Run
A10: MFG-008 | B10: BOM | C10: Activate a BOM with no components is rejected | D10: Negative | E10: High | F10: User has BOM.MANAGE. A DRAFT BOM with zero components exists. | G10: 1. Open the empty DRAFT BOM. 2. Click Activate; provide effectiveFrom date. | H10: DRAFT BOM with zero components. | I10: HTTP 400: Cannot activate a BOM with no components. Status stays DRAFT. | J10: /admin/boms/uid/:uid | POST /api/v1/boms/uid/{uid}/activate | K10: BOM.MANAGE | M10: Not Run
A11: MFG-009 | B11: BOM | C11: BOM.VIEW-only user cannot create, edit, or activate a BOM | D11: Permission | E11: High | F11: A CUSTOM role with BOM.VIEW only. A DRAFT BOM exists. | G11: 1. Login as the VIEW-only user. 2. Navigate to /admin/boms. 3. Observe the create toggle and the Activate button on a DRAFT BOM detail. | H11: BOM.VIEW-only user. | I11: List renders. Create toggle is hidden (canManage() = false). On the detail, Activate, Add component, and Remove component buttons are hidden. Direct POST to create/activate returns 403. | J11: /admin/boms | /admin/boms/uid/:uid | K11: BOM.VIEW (lacking BOM.MANAGE) | M11: Not Run
A12: MFG-010 | B12: BOM | C12: BOM edit on ACTIVE BOM ignores structural fields (notes update only) | D12: Positive | E12: High | F12: User has BOM.MANAGE. An ACTIVE BOM exists. | G12: 1. Open the ACTIVE BOM detail. 2. Edit notes and attempt to change outputQty. 3. Save. | H12: ACTIVE BOM. New notes. Attempted outputQty change. | I12: Notes updated. outputQty and yieldPercent are ignored on ACTIVE BOMs (service applies structural fields only when DRAFT per BR-BOM-03). UI gates structural fields behind isDraft(). | J12: /admin/boms/uid/:uid | PUT /api/v1/boms/uid/{uid} | K12: BOM.MANAGE | M12: Not Run
A13: MFG-011 | B13: BOM | C13: Activate a BOM containing a structural cycle is rejected | D13: Negative | E13: Medium | F13: User has BOM.MANAGE. Product P has DRAFT BOM containing component Q; Q has ACTIVE BOM containing P. | G13: 1. Attempt to activate P's DRAFT BOM (which would create a cycle). | H13: P > Q > P circular reference. | I13: BomCycleGuard.assertNoCycle rejects activation. HTTP 400 or appropriate error. P's BOM status stays DRAFT. No partial state change. | J13: /api/v1/boms/uid/{uid}/activate | K13: BOM.MANAGE | M13: Not Run
A14: MFG-020 | B14: Work Orders | C14: Work order list loads with status filter and pagination | D14: Positive | E14: High | F14: User has MANUFACTURING.VIEW. WOs in several statuses exist for the company. | G14: 1. Navigate to /admin/work-orders. 2. Cycle the status filter: Planned, Released, In Progress, Completed, Closed, Cancelled, All. 3. Page through. | H14: WOs in all six statuses for one company. | I14: Each filter re-queries with ?status= param and shows matching rows. Rows show WO number, FG product code/name, planned qty, status badge. Paginator shows all five controls. No uid in any visible column. | J14: /admin/work-orders | GET /api/v1/work-orders | K14: MANUFACTURING.VIEW | M14: Not Run
... A40: MFG-046 | B40: BOM API | C40: BOM multi-level explosion API — MAKE components recursed, BUY components are leaves | D40: Positive | E40: Medium | F40: User has BOM.VIEW. A multi-level BOM exists: parent > MAKE sub-assembly > BUY raw material. | G40: 1. Call GET /api/v1/boms/explode?parentProductUid={uid}&outputQty=5&multiLevel=true&withCost=false. 2. Repeat with multiLevel=false. 3. Repeat with withCost=true&branchUid={uid}. | H40: outputQty: 5. multiLevel: true then false. withCost: false then true. | I40: BomExplosionResultDto tree. MAKE components recursed down. BUY components are leaves regardless of any BOM they might have. withCost=true includes cost figures as money strings. | J40: GET /api/v1/boms/explode | K40: BOM.VIEW | M40: Not Run

Sheet General Ledger
A1: General Ledger — UAT
A2: ID | B2: Area | C2: Test Scenario | D2: Type | E2: Priority | F2: Preconditions | G2: Steps | H2: Test Data | I2: Expected Result | J2: Route | K2: Permission | L2: Actual Result | M2: Status | N2: Severity | O2: Tester | P2: Run Date | Q2: Comments
A3: GL-001 | B3: Chart of Accounts | C3: List Chart of Accounts — happy path, paginated, company-scoped | D3: Positive | E3: High | F3: Logged in as ACCOUNTANT (GL.VIEW). Company bootstrapped with seeded CoA. | G3: 1. Navigate to /admin/gl/accounts. 2. Confirm table loads with columns: code, name, type badge, normal balance, status. 3. Verify paginator present (app-paginator). 4. Check meta has page/size/totalElements/totalPages/hasNext. | H3: Default seeded CoA for the active company. | I3: Table renders account rows. Each row shows accountCode, name, AccountType badge, DEBIT/CREDIT, ACTIVE. ApiResponse envelope with meta. No raw uid in any cell. | J3: /admin/gl/accounts | K3: GL.VIEW | M3: Not Run
A4: GL-002 | B4: Chart of Accounts | C4: Create ASSET account — normal balance derived as DEBIT | D4: Positive | E4: High | F4: Logged in as ACCOUNTANT (GL.MANAGE). Active company exists. | G4: 1. Click 'Add account'. 2. Enter code '1100', name 'Bank - Operating', type = ASSET. 3. Submit. 4. Read the returned row. | H4: code=1100, name='Bank - Operating', accountType=ASSET | I4: HTTP 201. Row appears with normalBalance=DEBIT (derived server-side). status=ACTIVE. Duplicate code for same company must return 4xx. | J4: /admin/gl/accounts | K4: GL.MANAGE | M4: Not Run
A5: GL-003 | B5: Chart of Accounts | C5: Create LIABILITY account — normal balance CREDIT | D5: Positive | E5: Medium | F5: Logged in as ACCOUNTANT (GL.MANAGE). | G5: 1. Add account code '2100', name 'VAT Payable', type=LIABILITY. 2. Submit. 3. Check normalBalance. | H5: code=2100, name='VAT Payable', accountType=LIABILITY | I5: normalBalance=CREDIT derived server-side. status=ACTIVE. | J5: /admin/gl/accounts | K5: GL.MANAGE | M5: Not Run
A6: GL-004 | B6: Chart of Accounts | C6: Create EQUITY account (CREDIT) and INCOME account (CREDIT) — normal balance coverage | D6: Positive | E6: Medium | F6: Logged in as ACCOUNTANT (GL.MANAGE). | G6: 1. Add code '3900', name 'Retained Earnings', type=EQUITY. Submit. 2. Add code '4000', name 'Sales Revenue', type=INCOME. Submit. | H6: EQUITY code=3900; INCOME code=4000 | I6: Both return normalBalance=CREDIT. EQUITY account needed for year-end close config. | J6: /admin/gl/accounts | K6: GL.MANAGE | M6: Not Run
A7: GL-005 | B7: Chart of Accounts | C7: Deactivate an account — excluded from journal pickers thereafter | D7: Positive | E7: High | F7: An active account with no postings exists. | G7: 1. Click 'Deactivate' on the account row. 2. Confirm status change. 3. Navigate to /admin/gl/journals/post and open the account dropdown for a line. 4. Confirm the deactivated account is absent. | H7: Any active EXPENSE account with zero postings. | I7: Account becomes inactive. Not selectable in the journal form (listAllActiveAccounts filter). API POST to inactive account uid returns 4xx (BR-GL-04). | J7: /admin/gl/accounts | K7: GL.MANAGE | M7: Not Run
A8: GL-006 | B8: Chart of Accounts | C8: GL.VIEW-only role cannot create accounts — button hidden and API 403 | D8: Permission | E8: High | F8: Custom role with GL.VIEW only (no GL.MANAGE). Logged in as that user. | G8: 1. Navigate to /admin/gl/accounts. 2. Confirm 'Add account' button is absent. 3. POST directly to /api/v1/gl/accounts with valid payload. | H8: Custom role: GL.VIEW only. | I8: UI hides create control. API returns HTTP 403. | J8: /admin/gl/accounts | K8: GL.VIEW (denied for GL.MANAGE action) | M8: Not Run
A9: GL-007 | B9: Chart of Accounts | C9: CoA multi-tenant isolation — company-A user cannot read company-B accounts | D9: Negative | E9: High | F9: Two companies A and B each with distinct accounts. User assigned to company A only. | G9: 1. List accounts as company-A user — only A's accounts shown. 2. Call GET /api/v1/gl/accounts?companyId=<B-id>. 3. Call GET /api/v1/gl/accounts/uid/<B-account-uid>. | H9: Company A accounts; company B account uid. | I9: Step 1: only A's rows. Step 2: 403 from assertCanActIn. Step 3: 403 scope-denied. | J9: /admin/gl/accounts | K9: GL.VIEW | M9: Not Run
A10: GL-008 | B10: Manual Journals | C10: Post a balanced 2-line manual journal — debits equal credits | D10: Positive | E10: High | F10: Two active accounts in an OPEN fiscal period. Logged in as ACCOUNTANT (GL.POST). | G10: 1. Navigate to /admin/gl/journals/post. 2. Enter description 'June accrual'; posting date in an OPEN period. 3. Line 1: account 'Bank - Operating', debit 1000.00. 4. Line 2: account 'Sales Revenue', credit 1000.00. 5. Confirm running totals show Debits=1000, Credits=1000, Difference=0. 6. Click Post. | H10: DR 1000.00 / CR 1000.00; posting date in current OPEN period. | I10: HTTP 201. JB-#### batch number in success toast. Entry has sourceType=MANUAL, reversalOfId=null, two balanced lines. Navigate to detail page /admin/gl/journals/uid/{uid}. | J10: /admin/gl/journals/post | K10: GL.POST | M10: Not Run
A11: GL-009 | B11: Manual Journals | C11: Reject unbalanced journal — client guard disables Post; server enforces BR-GL-01 | D11: Negative | E11: High | F11: Logged in as ACCOUNTANT (GL.POST). OPEN period exists. | G11: 1. Navigate to /admin/gl/journals/post. 2. Enter line1 DR 1000.00, line2 CR 900.00. 3. Observe Difference = 100.00 — 'Post' button remains disabled. 4. Bypass UI: POST unbalanced body directly to /api/v1/gl/journals. | H11: DR=1000.00, CR=900.00 (difference 100.00). | I11: UI never enables Post while unbalanced. Direct API call returns 4xx with errors[] 'Journal entry is unbalanced (BR-GL-01)'. Even 0.01 difference must reject. | J11: /admin/gl/journals/post | K11: GL.POST | M11: Not Run
A12: GL-010 | B12: Manual Journals | C12: Reject posting into a CLOSED fiscal period — BR-GL-03 | D12: Negative | E12: High | F12: A fiscal period that is CLOSED. Balanced journal lines ready. | G12: 1. Close a period (or use an already-closed one). 2. Set posting date inside the closed period. 3. Post a balanced entry. | H12: Posting date = any date within the closed period. | I12: Server rejects: no OPEN period resolved for the date. Error surfaced inline. No partial write (transactional rollback). | J12: /admin/gl/journals/post | K12: GL.POST | M12: Not Run
A13: GL-011 | B13: Manual Journals | C13: Reject line with both debit and credit amounts — BR-GL-08 | D13: Negative | E13: High | F13: Logged in as ACCOUNTANT (GL.POST). | G13: 1. Enter a journal line with DR 500 AND CR 500. 2. Observe UI error. 3. API-post the same line. | H13: Single line: debitAmount=500, creditAmount=500. | I13: UI: 'A line cannot have both a debit and a credit amount.' API: 4xx 'must have a positive debit OR a positive credit, not both or neither (BR-GL-08)'. A line with both zero also rejected. | J13: /admin/gl/journals/post | K13: GL.POST | M13: Not Run
A14: GL-012 | B14: Manual Journals | C14: Reverse a MANUAL journal — append-only correction, BR-GL-02/C9 | D14: Positive | E14: High | F14: A posted MANUAL journal in an OPEN period. Logged in as ACCOUNTANT (GL.POST). | G14: 1. Open the journal detail at /admin/gl/journals/uid/:uid. 2. Click 'Reverse'. 3. Read the new reversing entry. | H14: Original entry JB-0001 with DR Bank 1000 / CR Revenue 1000. | I14: HTTP 201. New entry: lines swapped (DR Revenue 1000 / CR Bank 1000). sourceType=MANUAL. reversalOfId = original id. Original entry unchanged (append-only). Both entries visible in journals list. | J14: /admin/gl/journals/uid/:uid | K14: GL.POST | M14: Not Run
... A37: GL-035 | B37: Multi-Tenancy | C37: GL company switcher re-scopes every GL/costing screen | D37: Positive | E37: Medium | F37: User assigned to multiple companies. GL.VIEW + COSTING.VIEW. | G37: 1. On CoA, journals, periods, trial balance, gl-config, dimensions, values, sliced report — change the company <select>. 2. Verify each screen reloads. | H37: Two companies with distinct CoA and journals. | I37: Each screen reloads data scoped to the newly selected company. No cross-company data visible. Loading indicator shown during reload. | J37: /admin/gl/accounts | K37: GL.VIEW | M37: Not Run

Sheet Accounts Receivable
A1: Accounts Receivable — UAT
A2: ID | B2: Area | C2: Test Scenario | D2: Type | E2: Priority | F2: Preconditions | G2: Steps | H2: Test Data | I2: Expected Result | J2: Route | K2: Permission | L2: Actual Result | M2: Status | N2: Severity | O2: Tester | P2: Run Date | Q2: Comments
A3: AR-001 | B3: AR Invoices List | C3: AR open-items list renders with pagination and ApiResponse envelope | D3: Positive | E3: High | F3: Logged in as ACCOUNTANT (AR.VIEW). At least 21 AR open items in the active company. | G3: 1. Navigate to /admin/ar/invoices. 2. Confirm table loads (document no, customer, original + outstanding amount, currency, dates, status badge). 3. Verify paginator present. 4. Click NEXT, LAST, FIRST. | H3: At least 21 AR open items seeded (via sales posting or opening balances). | I3: Table with meta {page,size,totalElements,totalPages,hasNext}. No raw uid in any cell. Paging changes page param and reloads. NO-PERMISSION user: nav hidden, direct route blocked. | J3: /admin/ar/invoices | K3: AR.VIEW | M3: Not Run
A4: AR-002 | B4: AR Invoices List | C4: Invoice list customer/status filter — FE/BE contract gap (defect hunt TC-AR-041) | D4: Negative | E4: High | F4: At least 2 customers with invoices in different statuses. | G4: 1. Note unfiltered row count. 2. Apply customer filter via picker (by name). 3. Apply status filter = OPEN. 4. Compare count and contents before/after filter. 5. Inspect network request params. | H4: 2 customers: CUST-001 with OPEN invoices; CUST-002 with PAID invoices. | I4: DESIRED: only matching rows. DEFECT: ArService sends customerUid and status params; ArInvoiceController only binds companyId and customerId (Long). Server ignores customerUid/status — list returns all company rows. Assert if filtered count truly narrows; log contract defect if it does not. | J4: /admin/ar/invoices | K4: AR.VIEW | M4: Not Run
A5: AR-003 | B5: Receipts | C5: Record receipt: CASH, auto oldest-first allocation, fully allocated | D5: Positive | E5: High | F5: Customer with at least 2 OPEN invoices. AR.RECEIPT.RECORD permission. | G5: 1. Navigate to /admin/ar/receipts/record. 2. Pick customer by name. 3. Amount=1000.00, currency=TZS, tender=CASH, date=today. 4. Wait for open invoices to load in allocation editor. 5. Click 'Auto oldest-first'. 6. Confirm allocated total=1000.00, unallocated=0. 7. Submit. | H5: Invoice A outstanding 600.00; Invoice B outstanding 400.00. Receipt amount 1000.00. | I5: HTTP 201. ArReceiptDto status=ALLOCATED, unallocatedAmount=0, two allocation lines. Each invoice outstanding → 0, status → PAID. Success alert shows receipt number (RCT-####). | J5: /admin/ar/receipts/record | K5: AR.RECEIPT.RECORD | M5: Not Run
A6: AR-004 | B6: Receipts | C6: Record receipt: MOBILE_MONEY, partial allocation — receipt PARTIAL, invoice PARTIAL | D6: Positive | E6: High | F6: Customer with one OPEN invoice outstanding 1000.00. AR.RECEIPT.RECORD permission. | G6: 1. Pick customer, amount=1000.00, tender=MOBILE_MONEY, bank reference = 'MPE-9001'. 2. Allocate 600.00 against the invoice (leave 400.00 on-account). 3. Submit. | H6: Invoice outstanding 1000.00; allocate 600.00. | I6: HTTP 201. Receipt status=PARTIAL, unallocatedAmount=400.00. Invoice outstanding=400.00, status=PARTIAL. bankReference round-trips to the receipt DTO. | J6: /admin/ar/receipts/record | K6: AR.RECEIPT.RECORD | M6: Not Run
A7: AR-005 | B7: Receipts | C7: Record receipt fully on-account (no allocation) — status UNALLOCATED | D7: Positive | E7: Medium | F7: Customer with zero open invoices. AR.RECEIPT.RECORD permission. | G7: 1. Pick customer, amount=500.00, CASH, no allocations. 2. Submit. | H7: Amount 500.00, no invoice to allocate against. | I7: HTTP 201. Receipt status=UNALLOCATED, unallocatedAmount=500.00, empty allocation list. | J7: /admin/ar/receipts/record | K7: AR.RECEIPT.RECORD | M7: Not Run
A8: AR-006 | B8: Receipts | C8: Client guard blocks over-allocation; server rejects allocation exceeding outstanding (BR-AR-04) | D8: Negative | E8: High | F8: Customer with one invoice outstanding 1000.00. AR.RECEIPT.RECORD permission. | G8: 1. Receipt amount=800.00. Attempt to allocate 900.00 against the invoice. 2. Observe row highlight and submit button state. 3. Via API, POST allocation=150.00 against invoice with outstanding=100.00. | H8: Invoice outstanding 1000.00; receipt 800.00; allocation attempt 900.00. | I8: Step 2: row flagged table-danger, Submit disabled (anyAllocationExceedsOutstanding()). Step 3: 4xx 'exceeds outstanding (BR-AR-04)'. No receipt created (TX rollback). | J8: /admin/ar/receipts/record | K8: AR.RECEIPT.RECORD | M8: Not Run
A9: AR-007 | B9: Receipts | C9: Record receipt with WHT_ON_RECEIPT leg — GL: Cash DR reduced, WHT receivable DR, AR CR | D9: Positive | E9: High | F9: Active WHT type with kind=WHT_ON_RECEIPT. Customer with OPEN invoice. AR.RECEIPT.RECORD permission. | G9: 1. Navigate to /admin/ar/receipts/record. 2. Pick customer, amount=1000.00, fully allocate. 3. Select WHT type by name, enter whtAmount=50.00. 4. Submit. 5. Fetch linked GL entry. | H9: Amount=1000.00; WHT=50.00; invoice outstanding >= 1000.00. | I9: HTTP 201. GL: Cash DR=950.00, WHT Receivable DR=50.00, AR Control CR=1000.00. Total balances. WHT certificate linked to journal entry uid. | J9: /admin/ar/receipts/record | K9: AR.RECEIPT.RECORD | M9: Not Run
A10: AR-008 | B10: Receipts | C10: GL posting failure rolls back the entire receipt (atomicity check) | D10: Negative | E10: Medium | F10: Company missing ACCOUNTS_RECEIVABLE gl_config or period closed for the receipt date. | G10: 1. POST a receipt that will fail GL config resolution or period check. 2. Re-query /api/v1/ar/receipts for the company. | H10: Receipt date in a CLOSED period, or AR gl_config unset. | I10: Error response. No receipt row created. No allocation row. Invoices unchanged. Atomic rollback. | J10: /admin/ar/receipts/record | K10: AR.RECEIPT.RECORD | M10: Not Run
A11: AR-009 | B11: Write-Offs | C11: Write-off an OPEN invoice — status WRITTEN_OFF, GL DR Bad-Debt / CR AR | D11: Positive | E11: High | F11: An OPEN invoice with outstanding > 0. AR.WRITEOFF permission. | G11: 1. Navigate to /admin/ar/invoices. 2. Click 'Write off' on the target invoice row. 3. Enter reason 'Customer insolvent', accept today's date. 4. Submit. | H11: OPEN invoice outstanding 750.00; reason 'Customer insolvent'. | I11: HTTP 201. Invoice outstanding → 0, status → WRITTEN_OFF. GL: DR Bad-Debt Expense / CR AR Control at carrying base. List refreshes, badge secondary. AR.VIEW-only user: action hidden, API 403. | J11: /admin/ar/invoices | K11: AR.WRITEOFF | M11: Not Run
A12: AR-010 | B12: Write-Offs | C12: Write-off illegal transitions — PAID and already WRITTEN_OFF invoices rejected | D12: Negative | E12: High | F12: One PAID invoice; one already WRITTEN_OFF invoice. | G12: 1. POST a write-off against the PAID invoice. 2. POST a write-off against the WRITTEN_OFF invoice. | H12: Invoice-A status=PAID; Invoice-B status=WRITTEN_OFF. | I12: Both return 4xx. Invoice-A: 'is already PAID — cannot write off.' Invoice-B: 'is already WRITTEN_OFF.' No GL post, no write-off row in either case. | J12: /admin/ar/invoices | K12: AR.WRITEOFF | M12: Not Run
A13: AR-011 | B13: Credit Notes | C13: Raise credit note against OPEN invoice — outstanding reduced, status PARTIAL | D13: Positive | E13: High | F13: An OPEN invoice outstanding 1000.00 in TZS. AR.CREDITNOTE permission. | G13: 1. Navigate to /admin/ar/invoices. 2. Click 'Credit note' on the invoice row. 3. Enter net=200.00, VAT=36.00, reason='Price adjustment'. 4. Submit. | H13: Invoice outstanding 1000.00; credit net=200.00, VAT=36.00 (total 236.00). | I13: HTTP 201. Invoice outstanding → 764.00, status PARTIAL. GL: DR Revenue + DR VAT / CR AR Control. AR.VIEW-only: action hidden, API 403. | J13: /admin/ar/invoices | K13: AR.CREDITNOTE | M13: Not Run
A14: AR-012 | B14: Credit Notes | C14: Credit note customerUid contract bug — FE sends numeric supplierId (defect TC-AR-026) | D14: Negative | E14: High | F14: An OPEN invoice on the list. AR.CREDITNOTE permission. | G14: 1. Open the credit-note modal from an invoice row. 2. Enter valid net/VAT/reason and submit. 3. Inspect the request body (customerUid field) and the response. | H14: Any OPEN invoice. | I14: DESIRED: credit note posts successfully. DEFECT: ar-invoices-list.component.ts sends customerUid=String(inv.customerId) (numeric DB id, not the uid). Backend customers.findByCompanyIdAndUid() fails with 404/400 'Customer not found'. Capture response code; log defect if confirmed. | J14: /admin/ar/invoices | K14: AR.CREDITNOTE | M14: Not Run
... A25: AR-023 | B25: Accessibility | C25: Axe accessibility sweep on all AR screens including modals | D25: Positive | E25: Medium | F25: ACCOUNTANT (AR.VIEW + AR.WRITEOFF + AR.CREDITNOTE + AR.RECEIPT.RECORD + AR.STATEMENT.VIEW + AR.OPENING.SET) logged in. | G25: 1. Run axe on: /admin/ar/invoices, /ar/receipts, /ar/receipts/record, /ar/receipts/uid/:uid, /ar/statement, /ar/ageing, /ar/opening-balance. 2. Open write-off and credit-note modals via keyboard; run axe on each open modal. | H25: All AR screens loaded with data. | I25: Axe-clean WCAG 2.1 AA. Tables: captions + scope. Modals: aria-modal, labelled title, focus-trapped, closable via close button/backdrop. Typeahead pickers: role=listbox / role=option, keyboard-reachable. | J25: /admin/ar/invoices | K25: AR.VIEW + AR.WRITEOFF + AR.CREDITNOTE + AR.RECEIPT.RECORD | M25: Not Run

Sheet Accounts Payable
A1: Accounts Payable — UAT
A2: ID | B2: Area | C2: Test Scenario | D2: Type | E2: Priority | F2: Preconditions | G2: Steps | H2: Test Data | I2: Expected Result | J2: Route | K2: Permission | L2: Actual Result | M2: Status | N2: Severity | O2: Tester | P2: Run Date | Q2: Comments
A3: AP-001 | B3: Supplier Bills | C3: Payables list visible to AP.VIEW (ORG_ADMIN); hidden for no-permission user | D3: Positive | E3: High | F3: At least one supplier bill exists. Logged in as ORG_ADMIN (AP.VIEW). NOTE: ACCOUNTANT and PURCHASE_OFFICER are NOT seeded with AP.* perms per V12 — only ORG_ADMIN. | G3: 1. Log in as ORG_ADMIN; navigate to /admin/ap/supplier-bills. 2. Confirm table renders with columns: Bill No., Supplier Inv. No., Supplier, Bill/Due dates, Gross, Outstanding, Currency, Status, Source. 3. Log in as NO-PERMISSION user; confirm nav hidden and direct route blocked. | H3: Company 'Acme TZ Ltd' with at least one supplier bill. | I3: ORG_ADMIN: table renders, paginator present, ApiResponse with meta. NO-PERMISSION: route guard redirects, forbidden alert shown, API 403. | J3: /admin/ap/supplier-bills | K3: AP.VIEW | M3: Not Run
A4: AP-002 | B4: Supplier Bills | C4: Supplier column shows numeric id instead of name — DEF-AP-04 (defect hunt) | D4: Negative | E4: Medium | F4: A bill for a named supplier. ORG_ADMIN logged in. | G4: 1. Open /admin/ap/supplier-bills. 2. Inspect the Supplier column on any row. | H4: Bill for supplier 'Dar Wholesalers'. | I4: DESIRED: human-readable supplier name/code shown. DEFECT: bill.supplierId (numeric DB id) is rendered — C1 violation. Capture the actual rendered value; log DEF-AP-04 if confirmed. | J4: /admin/ap/supplier-bills | K4: AP.VIEW | M4: Not Run
A5: AP-003 | B5: Supplier Bills | C5: Enter GOODS bill against PO — auto 3-way match → MATCHED + GL posted | D5: Positive | E5: High | F5: Approved PO and goods receipt exist for the supplier. ORG_ADMIN (AP.BILL.ENTER + AP.BILL.MATCH). Line cost within 2% tolerance of PO. | G5: 1. Navigate to /admin/ap/supplier-bills/enter. 2. Pick supplier by name (typeahead). 3. Pick PO via picker by PO number. Select PO line per bill line. 4. Enter supplier invoice no, bill date, due date, VAT amount, currency TZS. 5. Add line: description, billed qty=10, unit cost=1000.00. 6. Submit. | H5: supplierInvoiceNo='INV-9001'; line qty=10 @ 1000.00; PO cost=1000.00. | I5: HTTP 201 with DRAFT bill (BILL-####). Inline match returns BillMatchResultDto with each line MATCHED. Bill status → MATCHED. GL: DR Purchases / CR AP-Control posted (postedGlEntryUid appears). ACCOUNTANT: route forbidden (no AP grants per V12). | J5: /admin/ap/supplier-bills/enter | K5: AP.BILL.ENTER + AP.BILL.MATCH | M5: Not Run
A6: AP-004 | B6: Supplier Bills | C6: Bill held on price variance > 2% tolerance; accept variance → MATCHED + GL posts | D6: Positive | E6: High | F6: PO line cost 1000.00. ORG_ADMIN (AP.BILL.MATCH). Bill to be entered at 1200.00. | G6: 1. Enter bill with unit cost=1200.00 (20% over PO cost). 2. Observe inline match result after submit. 3. Confirm bill status=HELD, no GL posted yet. 4. Click 'Accept Variance' for the line. 5. Confirm bill → MATCHED and GL is posted. | H6: PO cost 1000.00; billed 1200.00. | I6: After step 2: line badge HELD_PRICE_VARIANCE with priceVarianceAmount/priceVariancePct. Bill=HELD. After step 4: line=VARIANCE_ACCEPTED, bill=MATCHED, GL posted. User without AP.BILL.MATCH cannot accept (403). | J6: /admin/ap/supplier-bills/enter | K6: AP.BILL.MATCH | M6: Not Run
A7: AP-005 | B7: Supplier Bills | C7: Re-running match on a PAID bill is rejected (illegal transition) | D7: Negative | E7: Medium | F7: A fully-paid bill (status=PAID). ORG_ADMIN (AP.BILL.MATCH). | G7: 1. POST /api/v1/ap/supplier-bills/uid/{paidBillUid}/match/run. | H7: A bill with status=PAID. | I7: 4xx/409 rejected — only DRAFT/HELD are matchable. Bill remains PAID. No double posting. | J7: /admin/ap/supplier-bills/uid/:uid | K7: AP.BILL.MATCH | M7: Not Run
A8: AP-006 | B8: Payments | C8: Payment run over selected MATCHED bills — PAYMENT_RUN kind, GL posted atomically | D8: Positive | E8: High | F8: Supplier with at least 2 MATCHED bills. ORG_ADMIN (AP.PAYMENT.RUN). | G8: 1. Navigate to /admin/ap/payments/record. 2. Pick supplier by name. 3. Select all payable bills; confirm Selected count and total update. 4. Payment date=today, tender=BANK_TRANSFER, bankReference='TT-55'. 5. Submit. | H8: 2 bills: 1000.00 + 500.00; tender=BANK_TRANSFER. | I8: HTTP 201 with ApPaymentDto (kind=PAYMENT_RUN, PAYRUN-####). Each bill moves to PARTIALLY_PAID/PAID. GL: DR AP / CR Cash posted atomically. NOTE: controller returns single ApPaymentDto but FE types response as ApPaymentDto[] — flag render issue if occurs. | J8: /admin/ap/payments/record | K8: AP.PAYMENT.RUN | M8: Not Run
A9: AP-007 | B9: Payments | C9: Payment run with WHT-on-payment — Cash CR reduced by WHT, WHT leg posted | D9: Positive | E9: High | F9: Active WHT type with kind=WHT_ON_PAYMENT. A payable bill. ORG_ADMIN (AP.PAYMENT.RUN). | G9: 1. On Record Payment, pick supplier; select a bill. 2. Choose WHT type by name, enter whtAmount=50.00. 3. Submit. | H9: Bill outstanding 1000.00; WHT=50.00. | I9: HTTP 201. Cash CR = 950.00; WHT payable leg captured. Payment recorded for gross with WHT withheld. WHT amount 0/blank → no WHT leg sent. | J9: /admin/ap/payments/record | K9: AP.PAYMENT.RUN | M9: Not Run
A10: AP-008 | B10: Payments | C10: Pay single bill — partial payment (SINGLE kind) → bill PARTIALLY_PAID | D10: Positive | E10: High | F10: One MATCHED bill outstanding 1000.00. ORG_ADMIN (AP.PAYMENT.RUN). | G10: 1. Navigate to /admin/ap/payments. 2. Open 'Pay Single Bill' form; pick bill by number. 3. Amount=400.00, tender=CASH. 4. Submit. | H10: Bill BILL-0010 outstanding 1000.00; payment 400.00. | I10: HTTP 201. ApPaymentDto kind=SINGLE, allocation=400.00. Bill → PARTIALLY_PAID, outstanding=600.00. GL: DR AP / CR Cash. | J10: /admin/ap/payments | K10: AP.PAYMENT.RUN | M10: Not Run
A11: AP-009 | B11: Payments | C11: Second payment fully settles bill → status PAID, outstanding 0 | D11: Positive | E11: High | F11: A PARTIALLY_PAID bill with 600.00 outstanding. ORG_ADMIN. | G11: 1. Pay the remaining 600.00 via single-pay form. | H11: Bill outstanding 600.00; payment 600.00. | I11: Bill → PAID, outstanding=0.00. A second ApPaymentDto (SINGLE) created — separate append-only payment, not an edit of the prior one. | J11: /admin/ap/payments | K11: AP.PAYMENT.RUN | M11: Not Run
A12: AP-010 | B12: Debit Notes | C12: Raise debit note against MATCHED bill — outstanding reduced, GL posted (DEF-AP-03 watch) | D12: Positive | E12: High | F12: A MATCHED bill outstanding 1000.00. ORG_ADMIN (AP.DEBITNOTE). | G12: 1. On Payables list, click 'Debit Note' on a MATCHED row. 2. Enter Note Date, Net=200.00, VAT=0, Reason='Damaged goods returned'. 3. Submit. | H12: Net=200.00; reason='Damaged goods returned'. | I12: DESIRED: HTTP 201 ApDebitNoteDto (DN number, amount, reason). Bill outstanding → 800.00. GL: DR AP / CR Purchases. DEFECT DEF-AP-03: modal sends supplierUid=String(bill.supplierId) (numeric id). Backend uid-resolution fails → 400/404. Capture response; log if defect confirmed. | J12: /admin/ap/supplier-bills | K12: AP.DEBITNOTE | M12: Not Run
A13: AP-011 | B13: Debit Notes | C13: Debit note action hidden for DRAFT/HELD/PAID status and for roles lacking AP.DEBITNOTE | D13: Permission | E13: Medium | F13: Bills in DRAFT, HELD, PAID statuses. Custom AP.VIEW-only role. | G13: 1. As ORG_ADMIN: confirm 'Debit Note' button only on MATCHED/APPROVED/PARTIALLY_PAID rows. 2. As AP.VIEW-only user: confirm no 'Debit Note' button on any row. | H13: Bills in all status states. | I13: Button visibility = canDebitNote() AND payable status. AP.VIEW-only → button absent on all rows. | J13: /admin/ap/supplier-bills | K13: AP.DEBITNOTE | M13: Not Run
A14: AP-012 | B14: Opening Balance | C14: Set AP opening balance for a supplier — source=OPENING_BALANCE, GL posted | D14: Positive | E14: High | F14: An ACTIVE supplier. ORG_ADMIN (AP.OPENING.SET). ACCOUNTS_PAYABLE and OPENING_BALANCE_EQUITY gl_configs mapped. | G14: 1. Navigate to /admin/ap/opening-balance. 2. Pick supplier by name. 3. Enter gross=5000.00, billDate=2026-01-01, dueDate=2026-01-31, supplierInvoiceNo='OB-2025'. 4. Submit. | H14: Supplier 'Dar Wholesalers'; gross=5000.00. | I14: HTTP 201. SupplierBillDto source=OPENING_BALANCE, status reflects open payable. GL: DR Opening Balance Equity / CR AP posted. Bill appears in supplier's statement and Payables list. | J14: /admin/ap/opening-balance | K14: AP.OPENING.SET | M14: Not Run
... A22: AP-020 | B22: Bill Filters | C22: Supplier/status filter params FE/BE mismatch — DEF-AP-05 (defect hunt) | D22: Negative | E22: High | F22: Two suppliers each with bills in different statuses. ORG_ADMIN. | G22: 1. Apply supplier filter via typeahead; select by name. 2. Apply status filter = MATCHED. 3. Observe the network request params. 4. Check whether the list truly narrows server-side. | H22: Supplier A with MATCHED bills; Supplier B with DRAFT bills. | I22: DESIRED: only MATCHED bills for supplier A. DEFECT DEF-AP-05: FE sends supplierUid and status; backend list endpoint only honours supplierId (Long) and has no status param. Server ignores the filter — list returns all company rows. Assert whether rows truly narrow; log mismatch if not. | J22: /admin/ap/supplier-bills | K22: AP.VIEW | M22: Not Run

Sheet Cash & Bank
A1: Cash & Bank — UAT
A2: ID | B2: Area | C2: Test Scenario | D2: Type | E2: Priority | F2: Preconditions | G2: Steps | H2: Test Data | I2: Expected Result | J2: Route | K2: Permission | L2: Actual Result | M2: Status | N2: Severity | O2: Tester | P2: Run Date | Q2: Comments
A3: CB-001 | B3: Accounts | C3: Cash/bank accounts list renders for CASH.VIEW holder; forbidden for no-permission user | D3: Positive | E3: High | F3: Company with at least 1 CASH and 1 BANK account. Logged in as ORG_ADMIN (CASH.VIEW). NOTE: only ORG_ADMIN seeded with CASH.* per V13. | G3: 1. Navigate to /admin/cash/accounts. 2. Confirm table: Code, Name, Type, Bank, GL Account, Currency, Default, Active. 3. Type column shows CASH/BANK badges. 4. As NO-PERMISSION user: nav hidden, direct route blocked. | H3: Seeded 'Main Cash Drawer' (CASH) + 'CRDB Operating' (BANK). | I3: Table renders. ApiResponse<CashBankAccountDto[]>. No uid anywhere in the table or DOM. axe-clean. NO-PERMISSION: forbidden alert, API 403. | J3: /admin/cash/accounts | K3: CASH.VIEW | M3: Not Run
A4: CB-002 | B4: Accounts | C4: Create CASH account — GL ASSET link required, code auto-generated | D4: Positive | E4: High | F4: At least 1 ASSET GL account. ORG_ADMIN (CASH.ACCOUNT.MANAGE). | G4: 1. Click 'New Account'. 2. Name='Petty Cash Box', Type=CASH. 3. GL Asset Account: pick an ASSET account by 'code - name' label. 4. Click 'Save Account'. | H4: name='Petty Cash Box'; type=CASH; GL='1000 - Cash on Hand'. | I4: HTTP 201. Toast 'Account created · Petty Cash Box'. List shows new row with auto-generated Code, currency=TZS base, Active. For CASH type: bank name/no/branch fields NOT rendered. | J4: /admin/cash/accounts | K4: CASH.ACCOUNT.MANAGE | M4: Not Run
